Workbook

Sheet FR_Définitions
B2: Registre des activités de traitement
B4: Identification du traitement
B5: ID | C5: Numéro unique d'identification du traitement
B6: Etablissement(s) | C6: Si l'organisme à plusieurs établissements, indique le ou les établissements concernés par ce traitement
B7: Nom du traitement | C7: Le nom du traitement doit être suffisamment explicite pour que l'on comprenne de manière macro ce que fait le traitement
B8: Date d'identification du traitement | C8: Date à laquelle le traitement a été créé dans le registre
B9: Date de mise à jour | C9: Date à laquelle les informations sur le traitement ont été mises à jour pour la dernière fois (raccourci clavier CTRL ; )
B10: Historique de modifications | C10: Liste de l'ensemble des modifications qui ont été réalisées dans le registre sur le traitement, afin d'assurer une traçabilité des actions
B11: Data Protection Officer | C11: Nom et coordonnées de la personne ayant le rôle de DPO pour le traitement
B12: Responsable de traitement | C12: Fonction de la personne ayant le rôle de responsable de traitement, c'est-à-dire qui détermine les finalités et les moyens du traitement. Il est donc souvent un membre de la Direction Générale de l'entreprise
B13: Représentant de l'entité responsable de la mise en œuvre du traitement | C13: Fonction du représentant de l'entité ou du service qui est en charge de mettre en œuvre le traitement. Par exemple, le représentant de l'entité responsable du traitement des CV des candidats est le responsable de l'équipe recrutement
B14: Responsable(s) conjoint(s) du traitement | C14: Fonctions des personnes qui déterminent conjointement les finalités et les moyens du traitement
B15: Finalité principale | C15: Objectif final spécifique, explicite et légitime pour lequel le traitement a lieu
B16: Sous-finalités | C16: Les sous-finalités doivent être rattachées à la finalité principale du traitement
B18: Données personnelles traitées
B19: Catégories de personnes concernées par le traitement | C19: Exemples : employés, prestataires, clients, partenaires…
B20: Données d'identification | C20: Exemples : nom, prénom, adresse postale, numéro de téléphone, adresse e-mail, photos, vidéos…
B21: Données de connexion | C21: Exemples : adresse IP, logs, cookies, historique de navigation…
B22: Données de localisation | C22: Exemples : positionnement GPS, GSM…
B23: Données sur le comportement et la vie personnelle | C23: Exemples : situation familiale, habitudes de vie, habitudes de consommation…
B24: Données économiques et financières | C24: Exemples : revenus, situation financière, situation fiscale, numéro de carte bancaire, RIB…
B25: Données professionnelles | C25: Exemples : nom de l'employeur, statut dans l'entreprise, contrat de travail…
B26: Catégories particulières de données | C26: Exemples : données sur l'origine raciale ou ethnique, les opinions politiques, les convictions religieuses ou philosophiques ou l'appartenance syndicale, données génétiques, données biométriques, données concernant la santé, la vie sexuelle, l'orientation sexuelle, données relatives aux condamnations pénales et aux infractions...
B28: Description du traitement
B29: Canaux de collecte des données | C29: Moyens par lesquels les données sont récupérées / collectées pour le traitement. Par exemple : mail, formulaire papier, caméras…
B30: Licéité du traitement | C30: Le traitement n'est licite que si la personne concernée a donné son consentement au traitement de ses données, si le traitement est nécessaire à l'exécution d'un contrat auquel la personne concernée est partie ou si le traitement est nécessaire au respect d'une obligation légale
B31: Recours au traitement automatisé (y compris profilage) | C31: Recours à un traitement non basé sur une intervention ou analyse humaine (y compris toute forme de traitement automatisé consistant à utiliser les données à caractère personnel pour évaluer ou prédire des éléments concernant la santé, la situation économique, les préférences personnelles, le comportement, [...] les déplacements d'une personne physique)
B32: Applications support du traitement | C32: Liste des applications ou logiciels qui sont utilisés dans le but de réaliser le traitement. Attention, une même application peut être considérée comme support de plusieurs traitements
B33: Dispositions existantes pour assurer la sécurité des données | C33: Liste des dispositifs en place pour assurer la sécurité des données du traitement. Il est possible ici de faire référence à des documents tels que le Dossier d'Architecture Technique, le PIA (Privacy Impact Assessment) ou toute autre documentation présentant les mesures de sécurité "standard" existantes dans l'entreprise
B34: Durée d'archivage courant | C34: Durée de conservation pour les archives dites courantes. Les archives courantes sont réservées à l'utilisation courante des données par les services responsables de la mise en œuvre du traitement
B35: Durée d'archivage définitif | C35: Durée de conservation des archives dites définitives. Les archives définitives sont réservées aux archives présentant un intérêt historique, statistique ou scientifique
B36: Catégories de destinataires | C36: Toute personne, service, entreprise filiale ou tiers ayant un accès aux données à caractère personnel du traitement
B37: Raisons du transfert vers les catégories de destinataires | C37: Intérêts des destinataires à recevoir les données à caractère personnel transférées
B38: Transferts hors UE | C38: Communications de données à caractère personnel qui font ou sont destinées à faire l'objet d'un traitement en dehors des Etats membres de l'Union Européenne
B39: Pays destinataires | C39: Pays dans lesquels sont basés les catégories de destinataires à qui les données sont communiquées
C43: Liste des données sensibles
C44: Pas de donnée sensible
C45: Origine raciale ou ethnique
C46: Opinions politiques
C47: Religieuses ou philosophiques
C48: Appartenance syndicale
C49: Données génétiques
C50: Biométriques aux fins d'identification
C51: Concernant la santé
C52: Concerant la vie sexuelle ou l'orientation sexuelle
C53: Condamnations pénales ou infractions
C54: NIR (N° SS)
... C76: Aucun cas retenu

Sheet LookUp_Definition
A1: UIID | B1: Type Definition | C1: Definition Libelle | D1: Scope Client (iid du client)
A2: 1 | B2: Sensibilité | C2: Tres sensible | D2: 1
A3: 2 | B3: Sensibilité | C3: oeu sensible | D3: 1
A4: 3 | B4: Sensibilité | C4: Bof sensible | D4: 1
A5: 4 | B5: Sensibilité | C5: Extreme sensible | D5: 1
A6: 5 | B6: Sensibilité | C6: Aucune importance | D6: 1
A7: 6 | B7: DureeRetention | C7: 1 an | D7: 1
A8: 7 | B8: DureeRetention | C8: 2 ans | D8: -1
A9: 8 | B9: DureeRetention | C9: A vie | D9: 1
A10: 9 | B10: Sensibilité | C10: Tres sensible | D10: 2
A11: 10 | B11: Sensibilité | C11: oeu sensible | D11: 2
A12: 11 | B12: Sensibilité | C12: Bof sensible | D12: 2
A13: 12 | B13: Sensibilité | C13: Extreme sensible | D13: 2
... A17: 16 | B17: DureeRetention | C17: A vie | D17: 2

Sheet Registre de traitement
B1: Grille de collecte / Registre des activités de traitement - Organisme : Association LA BRETECHE
AN4: Analyse de conformité
B5: Identification du traitement | N5: Données personnelles traitées | X5: Description du traitement | AO5: Finalité | AQ5: Minimisation des DCP | AS5: Conservation des DCP | AU5: Sécurité des DCP | AW5: Consentement | AY5: Informations | BA5: Exercice des droits | BC5: Sous-traitance | BE5: Transfert hors UE | BG5: Registe et preuve | BL5: Critères PIA
B6: ID | C6: Etablissement(s) | D6: Données concernées | E6: Nom du traitement | F6: Date d'identification du traitement | G6: Date de mise à jour | H6: Historique des modifications | I6: Data Protection Officer | J6: Responsable de traitement | K6: Gestionnaire de la mise en œuvre du traitement | L6: Finalité principale | M6: Sous-finalités | N6: Catégories de personnes concernées par le traitement | O6: Données d'identification | P6: Données de connexion | Q6: Données de localisation | R6: Données sur le comportement et la vie personnelle | S6: Données économiques et financières | T6: Données professionnelles | U6: Catégories particulières de données (NIR, santé par exemple) | V6: Sensibilité | W6: Etude d'impact (PIA) | X6: Canaux de collecte des données | Y6: Licéité du traitement | Z6: Recours au traitements automatisés (y compris profilage) ? (Oui / Non) | AA6: Emplacement physique du traitement | AB6: Dispositions existantes pour assurer la sécurité des données | AC6: Emplacement numérique du traitement | AD6: Dispositions existantes pour assurer la sécurité des données | AE6: Hébergement | AF6: Durée de conservation | AG6: Archivage ? (Oui / Non) | AH6: Durée d'archivage | AI6: Catégories de destinataires | AJ6: Raisons du transfert vers les catégories de destinataires | AK6: Transferts hors UE (Oui / Non) | AL6: Pays destinataires | AM6: Commentaires | AN6: Impact du traitement | AO6: Détournement de finalité | AP6: Score | AQ6: Collecte de DCP inapprorpiées | AR6: Score2 | AS6: Conservation excessive de DCP | AT6: Score3 | AU6: Sécurisation insuffisante des DCP | AV6: Score4 | AW6: Vices du consentement | AX6: Score5 | AY6: Manque de transparence | AZ6: Score6 | BA6: Incapacité à permettre l'exercice des droits | BB6: Score7 | BC6: Transfert auprès d'un tiers mal encadré | BD6: Score8 | BE6: Transfert hors UE abusif | BF6: score9 | BG6: Défaut de preuve | BH6: Score10 | BI6: Score global | BJ6: Commentaires analyse | BK6: Exposition du traitement | BL6: évaluation / scoring | BM6: décision automatique | BN6: surveillance systématique | BO6: collecte de données sensibles | BP6: collecte de données personnelles à large échelle | BQ6: croisement de données | BR6: personnes vulnérables | BS6: usage innovant | BT6: exclusion du bénéfice d’un droit/contrat
B7: 1 | C7: DIME L'espoir ESAT LA Simonière ESAT Les espoirs Résidence du parc des bois Résidence La Combe SAVA Itinéraire Bis | D7: Demandeurs Familles et proches des demandeurs | E7: Pré inscription | F7: 44277 | G7: 25/06/2024 13/08/2024 23/08/2024 02/09/2024 19/12/2024 24/06/2025 15/07/2025 19/08/2025 | H7: Ajout des informations papiers de la Résidence du parc des bois Pour le SAVS It bis, plus de stockage papier Pour le DIME la Bretèche, ajout de donnée n° IEN, plus de papier Pour le SAVS Tinténiac, ajout info données sensibles Pour l'ESAT Les espoirs, ajout données CV Suppression données papier pour la résidence du parc des bois et ajout de ViaTrajectoire Ajout commentaire pour SAVS Mordelles (15/07/25) Modif données (19/08/2025) | I7: Groupe CREATIVE | J7: Directeur de l'organisme | K7: Chefs de service et directeurs & psychologue | L7: Collecter les informations personnelles permettant d’inscrire les demandeurs sur liste d’attente. | M7: Evaluer les besoins en accompagnement afin de déterminer si les capacité d'accueil sont en adéquation avec les besoins pour donner un avis sur la demande d'admission | N7: Demandeur, Proche des demandeurs, Familles et partenaires | O7: Nom d’usage Nom de naissance Prénom(s) Date de naissance, N° MSA/CAF, adresse, téléphone, email, n° dossier MDPH N° IEN (pour les jeunes scolarisés) | R7: Situation familiale Nombre d’enfant(s) Présence d’un aidant, prestation en place (SSIAD, ADMR…) Mesure de protection juridique, Objet de la demande, Permis de conduire et type (ESAT) | S7: Financements, aides, allocation et prestation de compensation | T7: CV et lettre de motivation pour les candidatures | U7: NIR Dossier médical sous pli (nomalement sauf pour les ESAT) Suivi médical en cours, traitement médicamenteux, médecin traitant, psychiatre, CMP, psychologue (Pas de données médicales au SAVS) ESAT Les espoirs - Pas de données médicales | V7: NIR (N° SS) + Concernant le santé | W7: Données sensibles (Art 9) ou données relatives aux condamnations pénales ou aux infractions (Art 10) | X7: Par le demandeur (usagers / famille / proches des usagers) par mail ou courrier ViaTrajectoire | Y7: Fondé sur le consentement préalable de la personne physique, | Z7: Non | AA7: Bureau de la personne chargée de l'accompagnement sociale à l'ESAT la simmnière SO pour SAVS Tinténiac Bureau du Chef du service social à l'ESAT Les Espoirs | AB7: Dans un classeur dans une armoire du bureau fermé à clé de la personne chargée de l'accompagnement sociale à l'ESAT la simonière Dans une armoire fermée à clé du bureau fermé à clé à l'ESAT Les Espoirs | AC7: Mediateam Messagerie Serveur de fichier ViaTrajectoire | AD7: User + MDP | AE7: Berger Levrault Microsoft AJP GCS SARA | AF7: Supprimer | AG7: Oui | AH7: Editeur | AI7: Interne : Directrice, chefs de service, secrétaire, coordinatrice, Service social, comission d'admission, chargé d'accompagnement, Psychologue Externe :Conseil départemental (MDPH, CLIC) | AJ7: SO | AK7: Non | AL7: SO | AM7: Résidence La Combe : Tout est dans mediateam ESAT Les Espoirs : Projet de passage 100% sur Mediateam SAVS Mordelles - Depuis le 1er appel, tout est sur Mediateam | AN7: 1 | AO7: 0 | AP7: =$AN7*AO7 -> 0 | AQ7: 0 | AR7: =$AN7*AQ7 -> 0 | AS7: 0 | AT7: =$AN7*AS7 -> 0 | AU7: 0 | AV7: =$AN7*AU7 -> 0 | AW7: 0 | AX7: =$AN7*AW7 -> 0 | AY7: 0 | AZ7: =$AN7*AY7 -> 0 | BA7: 0 | BB7: =$AN7*BA7 -> 0 | BC7: 0 | BD7: =$AN7*BC7 -> 0 | BE7: 0 | BF7: =$AN7*BE7 -> 0 | BG7: 0 | BH7: =$AN7*BG7 -> 0 | BI7: =AP7:AP7+AR7:AR7+AT7:AT7+AV7:AV7+AX7:AX7+AZ7:AZ7+BB7:BB7+BD7:BD7+BF7:BF7+BH7:BH7 -> 0 | BJ7: Se référer au document word de préconisation | BK7: 0 | BO7: X | BR7: X
B8: 2 | C8: DIME Rennes | D8: Demandeurs Familles et proches des demandeurs | E8: Pré inscription | F8: 44277 | G8: 45855 | H8: Séparation de ce traitement pour le DIME rennes | I8: Groupe CREATIVE | J8: Directeur de l'organisme | K8: Secrétaire de direction, chefs de service | L8: Collecter les informations personnelles permettant d’inscrire les demandeurs sur liste d’attente. | M8: Evaluer les besoins en accompagnement afin de déterminer si les capacité d'accueil sont en adéquation avec les besoins pour donner un avis sur la demande d'admission | N8: Demandeur, Proche des demandeurs, Familles et partenaires | O8: Nom d’usage Nom de naissance Prénom(s) Date de naissance, adresse, téléphone, email, n° dossier MDPH | P8: Accès à ViaTrajectoire | R8: Situation familiale Présence d’un aidant, prestation en place (SSIAD, ADMR…) Mesure de protection juridique, Objet de la demande | U8: Diagnostics (Suivi médical en cours, bilan médicaux), suivi extérieur existant | V8: Concernant le santé | W8: Données sensibles (Art 9) ou données relatives aux condamnations pénales ou aux infractions (Art 10) | X8: Par le demandeur (usagers / famille / proches des usagers) par mail ou courrier ViaTrajectoire | Y8: Fondé sur le consentement préalable de la personne physique, | Z8: Non | AA8: Bureau du secrétariat | AB8: Classeur dans un meuble du Bureau du secrétariat fermé à clé | AC8: Viatrajectoire Fichier excel sur le serveur (dossier secrétariat) | AD8: User + MDP | AE8: Etat AJP | AF8: 5 ans | AG8: Oui | AH8: Editeur | AI8: Interne : Chefs de service, secrétaire Externe :MDPH | AJ8: SO | AK8: Non | AL8: SO | AN8: 1 | AO8: 0 | AP8: =$AN8*AO8 -> 0 | AQ8: 0 | AR8: =$AN8*AQ8 -> 0 | AS8: 0 | AT8: =$AN8*AS8 -> 0 | AU8: 0 | AV8: =$AN8*AU8 -> 0 | AW8: 0 | AX8: =$AN8*AW8 -> 0 | AY8: 0 | AZ8: =$AN8*AY8 -> 0 | BA8: 0 | BB8: =$AN8*BA8 -> 0 | BC8: 0 | BD8: =$AN8*BC8 -> 0 | BE8: 0 | BF8: =$AN8*BE8 -> 0 | BG8: 0 | BH8: =$AN8*BG8 -> 0 | BI8: =AP8:AP8+AR8:AR8+AT8:AT8+AV8:AV8+AX8:AX8+AZ8:AZ8+BB8:BB8+BD8:BD8+BF8:BF8+BH8:BH8 -> 0 | BJ8: Se référer au document word de préconisation | BK8: 0 | BO8: X | BR8: X
B9: 3 | C9: DIME La Bretèche | D9: Demandeurs Familles et proches des demandeurs | E9: Pré inscription | F9: 44277 | G9: 45855 | H9: Séparation de ce traitement pour le DIME La Bretèche | I9: Groupe CREATIVE | J9: Directeur de l'organisme | K9: Secrétaire de direction, chefs de service | L9: Collecter les informations personnelles permettant d’inscrire les demandeurs sur liste d’attente. | M9: Evaluer les besoins en accompagnement afin de déterminer si les capacité d'accueil sont en adéquation avec les besoins pour donner un avis sur la demande d'admission | N9: Demandeur, Proche des demandeurs, Familles et partenaires | O9: Nom d’usage Nom de naissance Prénom(s) Date de naissance, adresse, téléphone, email, n° dossier MDPH | P9: Accès à ViaTrajectoire | R9: Situation familiale Présence d’un aidant, prestation en place (SSIAD, ADMR…) Mesure de protection juridique, Objet de la demande | U9: Diagnostics (Suivi médical en cours, bilan médicaux), suivi extérieur existant | V9: Concernant le santé | W9: Données sensibles (Art 9) ou données relatives aux condamnations pénales ou aux infractions (Art 10) | X9: Par le demandeur (usagers / famille / proches des usagers) par mail ou courrier ViaTrajectoire | Y9: Fondé sur le consentement préalable de la personne physique, | Z9: Non | AA9: SO | AB9: SO | AC9: Mail Via Trajectoire Mediateam | AD9: User + MDP | AE9: Microsoft Etat Berger Levrault | AF9: 5 ans | AG9: Oui | AH9: Editeur | AI9: Interne : Chefs de service, secrétaire Externe :MDPH | AJ9: SO | AK9: Non | AL9: SO | AN9: 1 | AO9: 0 | AP9: =$AN9*AO9 -> 0 | AQ9: 0 | AR9: =$AN9*AQ9 -> 0 | AS9: 0 | AT9: =$AN9*AS9 -> 0 | AU9: 0 | AV9: =$AN9*AU9 -> 0 | AW9: 0 | AX9: =$AN9*AW9 -> 0 | AY9: 0 | AZ9: =$AN9*AY9 -> 0 | BA9: 0 | BB9: =$AN9*BA9 -> 0 | BC9: 0 | BD9: =$AN9*BC9 -> 0 | BE9: 0 | BF9: =$AN9*BE9 -> 0 | BG9: 0 | BH9: =$AN9*BG9 -> 0 | BI9: =AP9:AP9+AR9:AR9+AT9:AT9+AV9:AV9+AX9:AX9+AZ9:AZ9+BB9:BB9+BD9:BD9+BF9:BF9+BH9:BH9 -> 0 | BJ9: Se référer au document word de préconisation | BK9: 0 | BO9: X | BR9: X
B10: 4 | C10: SAVS Tinténiac | D10: Demandeurs Familles et proches des demandeurs | E10: Pré inscription | F10: 45866 | I10: Groupe CREATIVE | J10: Directeur de l'organisme | K10: Secrétaire de direction | L10: Collecter les informations personnelles permettant d’inscrire les demandeurs sur liste d’attente. | M10: Evaluer les besoins en accompagnement afin de déterminer si les capacité d'accueil sont en adéquation avec les besoins pour donner un avis sur la demande d'admission | N10: Demandeur, Proche des demandeurs, Familles et partenaires | O10: Nom d’usage Nom de naissance Prénom(s) Date de naissance, adresse, téléphone, email, n° dossier MDPH | P10: Nom d’usage Nom de naissance Prénom(s) Date de naissance, , adresse, téléphone, email, n° dossier MDPH | U10: Orientation MDPH | V10: NIR (présent la notification MDPH) | W10: Données sensibles (Art 9) ou données relatives aux condamnations pénales ou aux infractions (Art 10) | X10: Par le demandeur (usagers / famille / proches des usagers) par mail ou courrier ViaTrajectoire | Y10: Fondé sur le consentement préalable de la personne physique, | Z10: Non | AA10: SO | AB10: SO | AC10: Mediateam | AD10: User + MDP | AE10: Berger Levrault | AF10: Supprimer | AG10: Oui | AH10: Editeur | AI10: Interne : Salarié Externe :Conseil départemental (MDPH, CLIC) | AJ10: SO | AK10: Non | AL10: SO | AN10: 1 | AO10: 0 | AP10: =$AN10*AO10 -> 0 | AQ10: 0 | AR10: =$AN10*AQ10 -> 0 | AS10: 0 | AT10: =$AN10*AS10 -> 0 | AU10: 0 | AV10: =$AN10*AU10 -> 0 | AW10: 0 | AX10: =$AN10*AW10 -> 0 | AY10: 0 | AZ10: =$AN10*AY10 -> 0 | BA10: 0 | BB10: =$AN10*BA10 -> 0 | BC10: 0 | BD10: =$AN10*BC10 -> 0 | BE10: 0 | BF10: =$AN10*BE10 -> 0 | BG10: 0 | BH10: =$AN10*BG10 -> 0 | BI10: =AP10:AP10+AR10:AR10+AT10:AT10+AV10:AV10+AX10:AX10+AZ10:AZ10+BB10:BB10+BD10:BD10+BF10:BF10+BH10:BH10 -> 0 | BJ10: Se référer au document word de préconisation | BK10: 0 | BO10: X | BR10: X
B11: 5 | C11: DIME La Bretèche | D11: Usagers Familles et proches des usagers | E11: Admission | F11: 44277 | G11: 45527 | H11: Ajout de données n° IEN, parcours de scolarité du jeune, ancien bilan de parcours (PPA, …), vaccinations, stockage en plus bureau des Assistantes sociales | I11: Groupe CREATIVE | J11: Directeur de l'organisme | K11: Chefs de service et directeurs | L11: Collecter les informations personnelles permettant d’enregistrer administrativement le nouvel usager | M11: - Gestion de l'admission - Etat des présences - Réalisation d'états statistiques ou de listes pour répondre à des besoins de gestion administrative - Gestion des élections des représentants CVS - Gestion des enquêtes (ANAP - EHPA...) - Rapport d'activité - Gestion des mutuelles - Gestion des contacts en cas d'urgence et de la personne de confiance - Gestion décès - Gestion de la facturation des usagers - Gestion du courrier - Gestion du linge - Gestion des repas - Gestion du droit à l'image | N11: Usagers Familles et proches des usagers | O11: Nom d’usage Nom de naissance Prénom(s) Date de naissance, lieu, ancienne adresse N° Sécurité sociale N° CAF/MSA, adresse, téléphone, photographie noms, prénoms, coordonnées téléphoniques et adresses email des intervenants nom et les coordonnées téléphoniques de la personne à contacter en cas d’urgence N° IEN | R11: - Situation familiale - Nombre d’enfant(s) - Lieu de résidence lors de l’enfance - Nombre de frères et sœurs - Origine et profession des parents - Provenance - Mesure de protection juridique - Goûts et loisirs | S11: - aides financieres - demande de prélevement + RIB | T11: Parcours de scolarité du jeune, ancien bilan de parcours (PPA, …) | U11: Carte d’invalidite copie de l’attestation de Sécurité sociale copie de l’extrait de jugement s’il existe une mesure de protection juridique copie de la dernière ordonnance antécédents Copie des vaccinations | V11: NIR (N° SS) Donnée de santé | W11: Données sensibles (Art 9) ou données relatives aux condamnations pénales ou aux infractions (Art 10) | X11: usager / famille / proches des usagers / organisme de protection juridique | Y11: Fondé sur l’exécution d’un contrat avec la personne physique concernée, | Z11: Non | AA11: Infirmerie Couloir Assistante sociale | AB11: Données médicales à l'infirmerie dans un classeur fermé à clé pour cetraines données Armoire du couloir fermée à clé Dans un placard du bureau des assistantes sociales fermé à clé | AC11: Mediateam | AD11: Accès restreint | AE11: Editeur | AF11: Mediateam | AG11: Oui | AH11: Mediateam | AI11: Interne :Directrice et chefs de service, professionnels, infirmière | AJ11: SO | AK11: Non | AL11: SO | AN11: 2 | AO11: 0 | AP11: =$AN11*AO11 -> 0 | AQ11: 0 | AR11: =$AN11*AQ11 -> 0 | AS11: 0 | AT11: =$AN11*AS11 -> 0 | AU11: 0 | AV11: =$AN11*AU11 -> 0 | AW11: 0 | AX11: =$AN11*AW11 -> 0 | AY11: 0 | AZ11: =$AN11*AY11 -> 0 | BA11: 0 | BB11: =$AN11*BA11 -> 0 | BC11: 0 | BD11: =$AN11*BC11 -> 0 | BE11: 0 | BF11: =$AN11*BE11 -> 0 | BG11: 0 | BH11: =$AN11*BG11 -> 0 | BI11: =AP11:AP11+AR11:AR11+AT11:AT11+AV11:AV11+AX11:AX11+AZ11:AZ11+BB11:BB11+BD11:BD11+BF11:BF11+BH11:BH11 -> 0 | BJ11: Se référer au document word de préconisation | BK11: 1 | BO11: X | BR11: X
B12: 6 | C12: DIME Rennes | D12: Usagers Familles et proches des usagers | E12: Admission | F12: 44277 | G12: 45855 | H12: Ajout durée d'archivage | I12: Groupe CREATIVE | J12: Directeur de l'organisme | K12: Chefs de service et directeurs | L12: Collecter les informations personnelles permettant d’enregistrer administrativement le nouvel usager | M12: - Gestion de l'admission - Etat des présences - Réalisation d'états statistiques ou de listes pour répondre à des besoins de gestion administrative - Gestion des élections des représentants CVS - Gestion des enquêtes (ANAP - EHPA...) - Rapport d'activité - Gestion des mutuelles - Gestion des contacts en cas d'urgence et de la personne de confiance - Gestion décès - Gestion de la facturation des usagers - Gestion du courrier - Gestion du linge - Gestion des repas - Gestion du droit à l'image | N12: Usagers Familles et proches des usagers | O12: Nom d’usage Nom de naissance Prénom(s) Date de naissance, lieu, ancienne adresse N° Sécurité sociale N° CAF/MSA, adresse, téléphone, noms, prénoms, coordonnées téléphoniques et adresses email des intervenants nom et les coordonnées téléphoniques de la personne à contacter en cas d’urgence | R12: - Situation familiale - Livret de famille - Lieu de résidence lors de l’enfance - Nombre de frères et sœurs - Origine et profession des parents - Provenance - Mesure de protection juridique - Goûts et loisirs | S12: - aides financieres - demande de prélevement | U12: Carte d’invalidite Copie de l’attestation de Sécurité sociale Copie de l’extrait de jugement s’il existe une mesure de protection juridique Copie de la dernière ordonnance antécédents, carnet de vaccination Bilan de santé | V12: NIR (N° SS) Donnée de santé | W12: Données sensibles (Art 9) ou données relatives aux condamnations pénales ou aux infractions (Art 10) | X12: usager / famille / proches des usagers / organisme de protection juridique | Y12: Fondé sur l’exécution d’un contrat avec la personne physique concernée, | Z12: Non | AA12: Infirmerie IME Bureau du pédopsychiatre | AB12: Classeur des entretiens avec les familles et Dossier médical papier dans une armoire de l'infirmerie IME Affichage de liste des jeunes et de prise en charge thérapeutiques dans l'infirmerie IME Tiroir fermé à clé dans le Bureau du pédopsychiatre | AC12: Serveur Mediateam Viatrajectoire ROR Qualinéo RésidESMS ATIH Enquête éducation nationale 32 Enquêtes ARS | AD12: Sauvegarde sur le serveur dans un répertoire service avec accès restreint User/mdp | AE12: Interne (AJP) Berger Levrault …. | AF12: SO | AG12: Oui | AH12: 20 ans après le départ de l'usager | AI12: Interne : Infirmière IME, secrétaire de direction IME, pédopsychiatre, Assistante sociale Externe : ARS | AJ12: SO | AK12: Non | AL12: SO | AN12: 2 | AO12: 0 | AP12: =$AN12*AO12 -> 0 | AQ12: 0 | AR12: =$AN12*AQ12 -> 0 | AS12: 3 | AT12: =$AN12*AS12 -> 6 | AU12: 1 | AV12: =$AN12*AU12 -> 2 | AW12: 2 | AX12: =$AN12*AW12 -> 4 | AY12: 0 | AZ12: =$AN12*AY12 -> 0 | BA12: 0 | BB12: =$AN12*BA12 -> 0 | BC12: 0 | BD12: =$AN12*BC12 -> 0 | BE12: 0 | BF12: =$AN12*BE12 -> 0 | BG12: 0 | BH12: =$AN12*BG12 -> 0 | BI12: =AP12:AP12+AR12:AR12+AT12:AT12+AV12:AV12+AX12:AX12+AZ12:AZ12+BB12:BB12+BD12:BD12+BF12:BF12+BH12:BH12 -> 12 | BJ12: Se référer au document word de préconisation | BK12: 1 | BO12: X | BR12: X
B13: 7 | C13: ESAT LA Simonière | D13: Usagers Familles et proches des usagers | E13: Admission | F13: 44277 | G13: 45562 | H13: Modif des durées d'archivage | I13: Groupe CREATIVE | J13: Directeur de l'organisme | K13: Chefs de service et directeurs | L13: Collecter les informations personnelles permettant d’enregistrer administrativement le nouvel usager | M13: - Gestion de l'admission - Etat des présences - Réalisation d'états statistiques ou de listes pour répondre à des besoins de gestion administrative - Gestion des élections des représentants CVS - Gestion des enquêtes (ANAP - EHPA...) - Rapport d'activité - Gestion des mutuelles - Gestion des contacts en cas d'urgence et de la personne de confiance - Gestion décès - Gestion du linge pro - Gestion du droit à l'image | N13: Travailleurs | O13: Nom d’usage Nom de naissance Prénom(s) Date de naissance, lieu, N° Sécurité sociale N° CAF/MSA, adresse, téléphone, email photographie nom de la mutuelle nom et les coordonnées téléphoniques de la personne à contacter en cas d’urgence, personne de confiance attestation de responsabilité civile, permis de conduire, médecin traitant et spécialiste, photocopie de la CI | R13: Situation familiale Nombre d’enfant(s) Etablissement d'origine, présence d’un aidant, prestation en place (SSIAD, ADMR…) Mesure de protection juridique Droit à l'image | S13: RIB | T13: Niveau scolaire, expérience professionnelle (CV) | U13: Point de vigilance santé / Comportement Carte vitale Mesure de protection judiciaire et RQTH carte d'invalidité | V13: NIR (N° SS) Donnée de santé | W13: Données sensibles (Art 9) ou données relatives aux condamnations pénales ou aux infractions (Art 10) | X13: usager / famille / proches des usagers / organisme de protection juridique | Y13: Fondé sur l’exécution d’un contrat avec la personne physique concernée, | Z13: Non | AA13: Bureau de l'assistante administrative | AB13: Armoire fermée à clé dans le bureau de l'assistante administrative fermé à clé | AC13: Serveur de fichier Mediateam | AD13: User + Mdp | AE13: Interne Berger Levrault | AF13: O | AG13: OUI | AH13: Pas de suppression | AI13: Interne : Assistante administrative, chef de service, chargé d'accompagnement, moniteur, directrice, psychologue Externe : MSA, médecine du travail, mutuelle, MDPH, CAF, Viatrajectoire, ARS | AJ13: Mutuelle des usagers | AK13: Non | AL13: SO | AM13: Archivage dans le grenier au dessus des vestiaires 03/06/25 : Pas de nettoyage encore, pas encore planifié, beaucoup d'installation de logiciel cette année | AN13: 2 | AO13: 0 | AP13: =$AN13*AO13 -> 0 | AQ13: 0 | AR13: =$AN13*AQ13 -> 0 | AS13: 2 | AT13: =$AN13*AS13 -> 4 | AU13: 0 | AV13: =$AN13*AU13 -> 0 | AW13: 0 | AX13: =$AN13*AW13 -> 0 | AY13: 0 | AZ13: =$AN13*AY13 -> 0 | BA13: 0 | BB13: =$AN13*BA13 -> 0 | BC13: 0 | BD13: =$AN13*BC13 -> 0 | BE13: 0 | BF13: =$AN13*BE13 -> 0 | BG13: 0 | BH13: =$AN13*BG13 -> 0 | BI13: =AP13:AP13+AR13:AR13+AT13:AT13+AV13:AV13+AX13:AX13+AZ13:AZ13+BB13:BB13+BD13:BD13+BF13:BF13+BH13:BH13 -> 4 | BK13: 1 | BO13: X | BR13: X
B14: 8 | C14: ESAT Les espoirs | D14: Usagers Familles et proches des usagers | E14: Admission | F14: 45078 | I14: Groupe CREATIVE | J14: Directeur de l'organisme | K14: Chefs de service et directeurs | L14: Collecter les informations personnelles permettant d’enregistrer administrativement le nouvel usager | M14: - Gestion de l'admission - Etat des présences - Réalisation d'états statistiques ou de listes pour répondre à des besoins de gestion administrative - Gestion des élections des représentants CVS - Gestion des enquêtes (ANAP - EHPA...) - Rapport d'activité - Gestion des mutuelles - Gestion des contacts en cas d'urgence et de la personne de confiance - Gestion décès - Gestion du linge pro - Gestion du droit à l'image | N14: Travailleurs | O14: Nom d’usage Nom de naissance Prénom(s) Date de naissance, lieu, N° Sécurité sociale N° CAF/MSA, adresse, téléphone, email photographie nom et les coordonnées téléphoniques de la personne à contacter en cas d’urgence, et de la personne de confiance | R14: Situation familiale Nombre d’enfant(s), frère(s) et sœur(s) Origine et profession des parents Etablissement d'origine, Mesure de protection juridique Droit à l'image | S14: - aides financières - demande de prélèvement + RIB | T14: Profession exercée profession du conjoint | U14: Carte d’invalidité copie de l’attestation de Sécurité sociale copie de l’extrait de jugement s’il existe une mesure de protection juridique copie de la dernière ordonnance | V14: NIR (N° SS) Donnée de santé | W14: Données sensibles (Art 9) ou données relatives aux condamnations pénales ou aux infractions (Art 10) | X14: usager / famille / proches des usagers / organisme de protection juridique | Y14: Fondé sur l’exécution d’un contrat avec la personne physique concernée, | Z14: Non | AA14: Bureau de la secrétaire de direction Bureau du Chef du service social Bureau du service d'accompagnement | AB14: Dans une armoire fermée à clé de bureau fermé à clé | AC14: Mediateam | AD14: User + Mdp | AE14: Berger Levrault | AF14: Mediateam | AG14: Oui | AH14: Mediateam | AI14: Interne : Secrétaire de direction, directeur, Chef de service social, Chargé d'accompagnement, Psychologue | AJ14: SO | AK14: Non | AL14: SO | AM14: ESAT Les espoirs : Avec l'utilisation massive de Meaditeam en 2025, possible svg en local de chaque dossier | AN14: 2 | AO14: 0 | AP14: =$AN14*AO14 -> 0 | AQ14: 0 | AR14: =$AN14*AQ14 -> 0 | AS14: 0 | AT14: =$AN14*AS14 -> 0 | AU14: 0 | AV14: =$AN14*AU14 -> 0 | AW14: 2 | AX14: =$AN14*AW14 -> 4 | AY14: 0 | AZ14: =$AN14*AY14 -> 0 | BA14: 0 | BB14: =$AN14*BA14 -> 0 | BC14: 0 | BD14: =$AN14*BC14 -> 0 | BE14: 0 | BF14: =$AN14*BE14 -> 0 | BG14: 0 | BH14: =$AN14*BG14 -> 0 | BI14: =AP14:AP14+AR14:AR14+AT14:AT14+AV14:AV14+AX14:AX14+AZ14:AZ14+BB14:BB14+BD14:BD14+BF14:BF14+BH14:BH14 -> 4 | BK14: 1 | BO14: X | BR14: X
B15: 9 | C15: SAVS Tinténiac | D15: Usagers Familles et proches des usagers | E15: Admission | F15: 45090 | G15: 02/09/2024 28/07/2025 | H15: Modif données sensibles colectées Modif données sensibles collectées - 28/07/25 | I15: Groupe CREATIVE | J15: Directeur de l'organisme | K15: Secrétaire | L15: Collecter les informations personnelles permettant d’enregistrer administrativement le nouvel usager | M15: - Gestion du dossier du bénéficiaire - Gestion de l'admission - Etat des présences - Réalisation d'états statistiques ou de listes pour répondre à des besoins de gestion administrative - Gestion des enquêtes (ANAP - EHPA...) - Rapport d'activité - Gestion des contacts en cas d'urgence - Gestion décès - Gestion du courrier - Gestion du droit à l'IMAGE | N15: Usagers Familles et proches des usagers | O15: Nom d’usage Nom de naissance Prénom(s) Date de naissance, lieu, ancienne adresse N° Sécurité sociale, adresse, téléphone, photographie noms, prénoms, coordonnées téléphoniques et adresses email des intervenants nom et les coordonnées téléphoniques de la personne à contacter en cas d’urgence | U15: Notification MDPH une mesure de protection juridique | V15: NIR (N° SS) | W15: Données sensibles (Art 9) ou données relatives aux condamnations pénales ou aux infractions (Art 10) | X15: usager / famille / proches des usagers / organisme de protection juridique | Y15: Fondé sur l’exécution d’un contrat avec la personne physique concernée, | Z15: Non | AA15: SO | AB15: SO | AC15: Mediateam | AD15: User/mdp | AE15: Berger Levrault | AF15: Mediateam | AG15: Oui | AH15: Mediateam | AI15: Interne : Tout le personnel Externe : MDPH & ViaTrajectoire | AJ15: SO | AK15: Non | AL15: SO | AN15: 2 | AO15: 0 | AP15: =$AN15*AO15 -> 0 | AQ15: 0 | AR15: =$AN15*AQ15 -> 0 | AS15: 0 | AT15: =$AN15*AS15 -> 0 | AU15: 0 | AV15: =$AN15*AU15 -> 0 | AW15: 0 | AX15: =$AN15*AW15 -> 0 | AY15: 0 | AZ15: =$AN15*AY15 -> 0 | BA15: 0 | BB15: =$AN15*BA15 -> 0 | BC15: 0 | BD15: =$AN15*BC15 -> 0 | BE15: 0 | BF15: =$AN15*BE15 -> 0 | BG15: 0 | BH15: =$AN15*BG15 -> 0 | BI15: =AP15:AP15+AR15:AR15+AT15:AT15+AV15:AV15+AX15:AX15+AZ15:AZ15+BB15:BB15+BD15:BD15+BF15:BF15+BH15:BH15 -> 0 | BK15: 1 | BO15: X | BR15: X
B16: 10 | C16: SAVA Itinéraire Bis | D16: Usagers Familles et proches des usagers | E16: Admission | F16: 45090 | G16: 45090 | H16: Modification de la partie stockage physique Ajout de précision sur la partie papier (15/07/25) | I16: Groupe CREATIVE | J16: Directeur de l'organisme | K16: Chefs de service et directeurs | L16: Collecter les informations personnelles permettant d’enregistrer administrativement le nouvel usager | M16: - Gestion du dossier du bénéficiaire - Gestion de l'admission - Etat des présences - Réalisation d'états statistiques ou de listes pour répondre à des besoins de gestion administrative - Gestion des enquêtes (ANAP - EHPA...) - Rapport d'activité - Gestion des contacts en cas d'urgence - Gestion décès - Gestion du courrier - Gestion du droit à l'IMAGE | N16: Usagers Familles et proches des usagers | O16: Nom d’usage Nom de naissance Prénom(s) Date de naissance, lieu, ancienne adresse N° Sécurité sociale N° CAF/MSA, adresse, téléphone, photographie noms, prénoms, coordonnées téléphoniques et adresses email des intervenants nom et les coordonnées téléphoniques de la personne à contacter en cas d’urgence (si existe), Assurance, mutuelle, copie carte d'iden-tité, permis de conduire (si donné), justificatif de domicile | R16: - Situation familiale - Nombre d’enfant(s) - Nombre de petits enfants - Lieu de résidence lors de l’enfance - Nombre de frères et sœurs - Provenance - Mesure de protection juridique - Goûts et loisirs | S16: - aides financieres - demande de prélevement + RIB | T16: Profession exercée profession du conjoint | U16: Carte d’invalidite copie de l’attestation de Sécurité sociale copie de l’extrait de jugement s’il existe une mesure de protection juridique copie de la dernière ordonnance antécédents Bilan professionnel de l'ancienne structure | V16: NIR (N° SS) Donnée de santé | W16: Données sensibles (Art 9) ou données relatives aux condamnations pénales ou aux infractions (Art 10) | X16: usager / famille / proches des usagers / organisme de protection juridique | Y16: Fondé sur l’exécution d’un contrat avec la personne physique concernée, | Z16: Non | AA16: Bureau des éducateurs | AB16: Quelques dossiers papier reçu ou imprimé dans le caisson des éducateurs, fermé à clé De moins en moins de dossier papier (informations temporaires avant numérisation) | AC16: Mediateam - serveur | AD16: User/mdp | AE16: Berger Levrault | AF16: Mediateam | AG16: Oui | AH16: Mediateam | AI16: Interne : Tout le personnel Externe : | AJ16: SO | AK16: Non | AL16: SO | AN16: 2 | AO16: 0 | AP16: =$AN16*AO16 -> 0 | AQ16: 0 | AR16: =$AN16*AQ16 -> 0 | AS16: 0 | AT16: =$AN16*AS16 -> 0 | AU16: 0 | AV16: =$AN16*AU16 -> 0 | AW16: 0 | AX16: =$AN16*AW16 -> 0 | AY16: 0 | AZ16: =$AN16*AY16 -> 0 | BA16: 0 | BB16: =$AN16*BA16 -> 0 | BC16: 0 | BD16: =$AN16*BC16 -> 0 | BE16: 0 | BF16: =$AN16*BE16 -> 0 | BG16: 0 | BH16: =$AN16*BG16 -> 0 | BI16: =AP16:AP16+AR16:AR16+AT16:AT16+AV16:AV16+AX16:AX16+AZ16:AZ16+BB16:BB16+BD16:BD16+BF16:BF16+BH16:BH16 -> 0 | BK16: 1 | BO16: X | BR16: X
B17: 11 | C17: Résidence La Combe | D17: Usagers Familles et proches des usagers | E17: Admission | F17: 45076 | G17: 45561 | H17: Données papier seulement à l'infirmerie, plus dans le couloir | I17: Groupe CREATIVE | J17: Directeur de l'organisme | K17: Chefs de service et directeurs | L17: Collecter les informations personnelles permettant d’enregistrer administrativement le nouvel usager | M17: - Gestion de l'admission - Etat des présences - Réalisation d'états statistiques ou de listes pour répondre à des besoins de gestion administrative - Gestion des élections des représentants CVS - Gestion des enquêtes (ANAP - EHPA...) - Rapport d'activité - Gestion des mutuelles - Gestion des contacts en cas d'urgence et de la personne de confiance - Gestion décès - Gestion de la facturation des usagers - Gestion du courrier - Gestion du linge - Gestion des repas - Gestion du droit à l'image | N17: Usagers Familles et proches des usagers | O17: Nom d’usage Nom de naissance Prénom(s) Date de naissance, lieu, ancienne adresse N° Sécurité sociale N° CAF/MSA, adresse, téléphone, photographie noms, prénoms, coordonnées téléphoniques et adresses email des intervenants nom et les coordonnées téléphoniques de la personne à contacter en cas d’urgence | R17: - Situation familiale - Nombre d’enfant(s) - Lieu de résidence lors de l’enfance - Nombre de frères et sœurs - Origine et profession des parents - Provenance - Mesure de protection juridique - Goûts et loisirs | S17: - aides financieres - demande de prélevement + RIB | T17: Profession des parents, expérience professionnelle | U17: Carte d’invalidite copie de l’attestation de Sécurité sociale copie de l’extrait de jugement s’il existe une mesure de protection juridique copie de la dernière ordonnance antécédents | V17: NIR (N° SS) Donnée de santé | W17: Données sensibles (Art 9) ou données relatives aux condamnations pénales ou aux infractions (Art 10) | X17: usager / famille / proches des usagers / organisme de protection juridique | Y17: Fondé sur l’exécution d’un contrat avec la personne physique concernée, | Z17: Non | AA17: Infirmerie | AB17: Données médicales à l'infirmerie dans un classeur fermé à clé pour les données médicales | AC17: Mediateam | AD17: Accès restreint | AE17: Berger Levrault | AF17: Mediateam | AG17: Oui | AH17: Mediateam | AI17: Interne :Directrice et chefs de service, professionnels, infirmière | AJ17: SO | AK17: Non | AL17: SO | AN17: 2 | AO17: 0 | AP17: =$AN17*AO17 -> 0 | AQ17: 0 | AR17: =$AN17*AQ17 -> 0 | AS17: 0 | AT17: =$AN17*AS17 -> 0 | AU17: 0 | AV17: =$AN17*AU17 -> 0 | AW17: 0 | AX17: =$AN17*AW17 -> 0 | AY17: 0 | AZ17: =$AN17*AY17 -> 0 | BA17: 0 | BB17: =$AN17*BA17 -> 0 | BC17: 0 | BD17: =$AN17*BC17 -> 0 | BE17: 0 | BF17: =$AN17*BE17 -> 0 | BG17: 0 | BH17: =$AN17*BG17 -> 0 | BI17: =AP17:AP17+AR17:AR17+AT17:AT17+AV17:AV17+AX17:AX17+AZ17:AZ17+BB17:BB17+BD17:BD17+BF17:BF17+BH17:BH17 -> 0 | BK17: 1 | BO17: X | BR17: X
B18: 12 | C18: Résidence du parc des bois | D18: Usagers Familles et proches des usagers | E18: Admission | F18: 45076 | G18: 45468 | H18: Modification des données collectées et de leur empacement | I18: Groupe CREATIVE | J18: Directeur de l'organisme | K18: Chefs de service et directeurs | L18: Collecter les informations personnelles permettant d’enregistrer administrativement le nouvel usager | M18: - Gestion de l'admission - Etat des présences - Réalisation d'états statistiques ou de listes pour répondre à des besoins de gestion administrative - Gestion des élections des représentants CVS - Gestion des enquêtes (ANAP - EHPA...) - Rapport d'activité - Gestion des mutuelles - Gestion des contacts en cas d'urgence et de la personne de confiance - Gestion décès - Gestion de la facturation des usagers - Gestion du courrier - Gestion du linge - Gestion des repas - Gestion du droit à l'image | N18: Usagers Familles et proches des usagers | O18: Nom d’usage Nom de naissance Prénom(s) Date de naissance, lieu, ancienne adresse N° Sécurité sociale N° CAF/MSA, adresse, téléphone, photographie noms, prénoms, coordonnées téléphoniques et adresses email des intervenants nom et les coordonnées téléphoniques de la personne à contacter en cas d’urgence | R18: - Situation familiale - Nombre d’enfant(s) - Nombre de frères et sœurs - Mesure de protection juridique - Goûts et loisirs - Notification de décision (du Dpt) | S18: - aides financieres pour la comptable - demande de prélevement + RIB pour la comptable | T18: Profession des parents, expérience professionnelle du jeune | U18: Carte d’invalidite copie de l’attestation de Sécurité sociale, mutuelle, pièce d'identité (carte de séjour et extrait de l'acte de naissance) copie de l’extrait de jugement s’il existe une mesure de protection juridique copie de la dernière ordonnance antécédents Orientation MDPH | V18: NIR (N° SS) Donnée de santé | W18: Données sensibles (Art 9) ou données relatives aux condamnations pénales ou aux infractions (Art 10) | X18: usager / famille / proches des usagers / organisme de protection juridique | Y18: Fondé sur l’exécution d’un contrat avec la personne physique concernée, | Z18: Non | AA18: Pharmacie | AB18: Accès sécurisé à la pharmacie pour les données médicales | AC18: Mediateam PC de l'infirmière | AD18: Accès restreint par utilisateur accès spécifique de l'infirmière | AE18: Berger Levrault | AF18: Mediateam | AG18: Oui | AH18: Mediateam | AI18: Interne :Directrice et chefs de service, professionnels, infirmière | AJ18: SO | AK18: Non | AL18: SO | AO18: 0 | AP18: =$AN18*AO18 -> 0 | AQ18: 0 | AS18: 0 | AU18: 0 | AW18: 0 | AY18: 0 | BA18: 0 | BC18: 0 | BG18: 0 | BK18: 1 | BO18: X | BR18: X
B19: 13 | C19: Résidences Les Gantelles et Les Fougères | D19: Usagers Familles et proches des usagers | E19: Admission | F19: 45582 | G19: 45838 | H19: Ajout d'un commentaire | I19: Groupe CREATIVE | J19: Directeur de l'organisme | K19: Cheffe de service | L19: Collecter les informations personnelles permettant d’enregistrer administrativement le nouvel usager | M19: - Gestion de l'admission - Etat des présences - Réalisation d'états statistiques ou de listes pour répondre à des besoins de gestion administrative - Gestion des élections des représentants CVS - Gestion des enquêtes (ANAP - EHPA...) - Rapport d'activité - Gestion des mutuelles - Gestion des contacts en cas d'urgence et de la personne de confiance - Gestion décès - Gestion de la facturation des usagers - Gestion du courrier - Gestion du linge - Gestion des repas - Gestion du droit à l'image | N19: Usagers Familles et proches des usagers | O19: Nom d’usage Nom de naissance Prénom(s) Date de naissance, lieu, ancienne adresse N° Sécurité sociale N° CAF/MSA, adresse, téléphone, photographie noms, prénoms, coordonnées téléphoniques et adresses email des intervenants nom et les coordonnées téléphoniques de la personne à contacter en cas d’urgence | R19: - Situation familiale - Nombre d’enfant(s) - Nombre de frères et sœurs - Mesure de protection juridique - Goûts et loisirs - Notification de décision (du Dpt) | S19: - aides financieres pour la comptable - demande de prélevement + RIB pour la comptable | T19: Profession des parents, expérience professionnelle du jeune | U19: Carte d’invalidite copie de l’attestation de Sécurité sociale, mutuelle, pièce d'identité (carte de séjour et extrait de l'acte de naissance) copie de l’extrait de jugement s’il existe une mesure de protection juridique copie de la dernière ordonnance antécédents Orientation MDPH | V19: NIR (N° SS) Donnée de santé | W19: Données sensibles (Art 9) ou données relatives aux condamnations pénales ou aux infractions (Art 10) | X19: usager / famille / proches des usagers / organisme de protection juridique | Y19: Fondé sur l’exécution d’un contrat avec la personne physique concernée, | Z19: Non | AA19: Bureau de la direction | AB19: Armoire fermée à clé contenant les dossiers des résidents des 2 foyers dans le bureau de la direction fermé à clé | AC19: SO | AD19: SO | AE19: SO | AF19: Non définie | AG19: Oui | AH19: Non définie | AI19: Interne : Cheffe de service, professionnels | AJ19: SO | AK19: Non | AL19: SO | AM19: Actuellement les résidents gèrent les points suivants en attendant que cela reviennent aux foyers : - Gestion des mutuelles - Gestion du courrier - Gestion du linge - Gestion des repas | AN19: 2 | AO19: 0 | AP19: =$AN19*AO19 -> 0 | AQ19: 0 | AR19: =$AN19*AQ19 -> 0 | AS19: 0 | AT19: =$AN19*AS19 -> 0 | AU19: 0 | AV19: =$AN19*AU19 -> 0 | AW19: 2 | AX19: =$AN19*AW19 -> 4 | AY19: 0 | AZ19: =$AN19*AY19 -> 0 | BA19: 0 | BB19: =$AN19*BA19 -> 0 | BC19: 0 | BD19: =$AN19*BC19 -> 0 | BE19: 0 | BF19: =$AN19*BE19 -> 0 | BG19: 0 | BH19: =$AN19*BG19 -> 0 | BI19: =AP19:AP19+AR19:AR19+AT19:AT19+AV19:AV19+AX19:AX19+AZ19:AZ19+BB19:BB19+BD19:BD19+BF19:BF19+BH19:BH19 -> 4 | BK19: 1 | BO19: X | BR19: X
B20: 14 | C20: DIME Rennes | D20: Usagers Familles et proches des usagers | E20: Accompagnement des usagers - Partie non médicale | F20: 44277 | G20: 45855 | H20: Modification des données collectées et de leur empacement | I20: Groupe CREATIVE | J20: Directeur de l'organisme | K20: Chef de service | L20: Collecter et utiliser des données permettant de construire le projet d’accompagnement personnalisé des usagers et d’organiser et tracer l'accompagnement à apporter | M20: - Elaboration des projets d'accompagnement personnalisés - Gestion des prestations non médicales - Préparation des repas adaptés aux besoins de l'usager | N20: Usagers Familles et proches des usagers | O20: Nom d’usage Nom de naissance Prénom(s) | R20: situation familiale informations sur sa vie (généalogie, habitude, parcours, habitudes, plaisirs, hygiène, vêtements, toilette, ...) motricité et deplacement prothèses, caractéristiques sensorielles | U20: Copie MDPH, Copie des pièces d'identité, de jugement, Info sur les échanges avec partenaires, Projet personnalisé des jeunes, NIR | V20: Concernant la santé | W20: Données sensibles (Art 9) ou données relatives aux condamnations pénales ou aux infractions (Art 10) | X20: usager / famille / proches des usagers / organisme de protection juridique | Y20: Fondé sur le consentement préalable de la personne physique, | Z20: Non | AA20: Infirmerie IME Bureau du pédopsychiatre Salle de communication IME | AB20: Classeur des entretiens avec les familles et Dossier médical papier dans une armoire de l'infirmerie IME Affichage de liste des jeunes et de prise en charge thérapeutiques dans l'infirmerie IME Tiroir fermé à clé dans le Bureau du pédopsychiatre Version dans les dossiers papier administratifs dans la salle de communication fermé à clé | AC20: Mediateam | AD20: Accès restreint par utilisateur | AE20: Berger Levrault | AF20: Mediateam | AG20: Oui | AH20: Mediateam | AI20: Interne :Directrice et chefs de service, professionnels, infirmière | AJ20: SO | AK20: Non | AL20: SO | AM20: Encore gestion papier en attendant la gestion des droits sur Mediateam | AN20: 1 | AO20: 0 | AP20: =$AN20*AO20 -> 0 | AQ20: 0 | AR20: =$AN20*AQ20 -> 0 | AS20: 0 | AT20: =$AN20*AS20 -> 0 | AU20: 0 | AV20: =$AN20*AU20 -> 0 | AW20: 2 | AX20: =$AN20*AW20 -> 2 | AY20: 0 | AZ20: =$AN20*AY20 -> 0 | BA20: 0 | BB20: =$AN20*BA20 -> 0 | BC20: 0 | BD20: =$AN20*BC20 -> 0 | BE20: 0 | BF20: =$AN20*BE20 -> 0 | BG20: 0 | BH20: =$AN20*BG20 -> 0 | BI20: =AP20:AP20+AR20:AR20+AT20:AT20+AV20:AV20+AX20:AX20+AZ20:AZ20+BB20:BB20+BD20:BD20+BF20:BF20+BH20:BH20 -> 2 | BJ20: Se référer au document word de préconisation | BK20: 1 | BO20: X | BR20: X
B21: 15 | C21: DIME La Bretèche | D21: Usagers Familles et proches des usagers | E21: Accompagnement des usagers - Partie non médicale | F21: 44277 | G21: 45527 | H21: Pas de donnée de santé | I21: Groupe CREATIVE | J21: Directeur de l'organisme | K21: Chef de service | L21: Collecter et utiliser des données permettant de construire le projet d’accompagnement personnalisé des usagers et d’organiser et tracer l'accompagnement à apporter | M21: - Elaboration des projets d'accompagnement personnalisés - Gestion des prestations non médicales - Préparation des repas adaptés aux besoins de l'usager | N21: Usagers Familles et proches des usagers | O21: Nom d’usage Nom de naissance Prénom(s) | R21: Dernier lieu de provenance (établissement d'origine, GEVASCO, PPA) Situation familiale informations sur sa vie (généalogie, habitude, parcours, plaisirs, hygiène, vêtements, toilette, ...) motricité, caractéristiques sensorielles | V21: Concernant la santé | W21: Données sensibles (Art 9) ou données relatives aux condamnations pénales ou aux infractions (Art 10) | X21: usager / famille / proches des usagers | Y21: Fondé sur le consentement préalable de la personne physique, | Z21: Non | AA21: Couloir près de la directrice | AB21: Armoire fermée à clé | AC21: Mediateam | AD21: Accès restreint par utilisateur | AE21: Berger Levrault | AF21: Mediateam | AG21: Oui | AH21: Mediateam | AI21: Interne : tous les professionnels Externe ::Partenaire (Stage) | AJ21: Présentation du jeune et de son dossier pour un stage auprès du partenaire | AK21: Non | AL21: SO | AN21: 1 | AO21: 0 | AP21: =$AN21*AO21 -> 0 | AQ21: 0 | AR21: =$AN21*AQ21 -> 0 | AS21: 0 | AT21: =$AN21*AS21 -> 0 | AU21: 0 | AV21: =$AN21*AU21 -> 0 | AW21: 0 | AX21: =$AN21*AW21 -> 0 | AY21: 0 | AZ21: =$AN21*AY21 -> 0 | BA21: 0 | BB21: =$AN21*BA21 -> 0 | BC21: 1 | BD21: =$AN21*BC21 -> 1 | BE21: 0 | BF21: =$AN21*BE21 -> 0 | BG21: 0 | BH21: =$AN21*BG21 -> 0 | BI21: =AP21:AP21+AR21:AR21+AT21:AT21+AV21:AV21+AX21:AX21+AZ21:AZ21+BB21:BB21+BD21:BD21+BF21:BF21+BH21:BH21 -> 1 | BJ21: Se référer au document word de préconisation | BK21: 1 | BO21: X | BR21: X
B22: 16 | C22: ESAT LA Simonière | D22: Usagers Familles et proches des usagers | E22: Accompagnement des usagers - Partie non médicale | F22: 44277 | G22: 45562 | H22: Modif des durées d'archivage et des données collectées | I22: Groupe CREATIVE | J22: Directeur de l'organisme | K22: Chef de service | L22: Collecter et utiliser des données permettant de construire le projet d’accompagnement personnalisé des usagers et d’organiser et tracer l'accompagnement à apporter | M22: - Elaboration des projets d'accompagnement personnalisés - Paiement des usagers (rémunération garantie) | N22: Usagers | O22: Nom d’usage Nom de naissance Prénom(s) Date de naissance, lieu, N° Sécurité sociale N° CAF/MSA, adresse, téléphone, email photographie nom de la mutuelle nom et les coordonnées téléphoniques de la personne à contacter en cas d’urgence, personne de confiance attestation de responsabilité civile, permis de conduire, médecin traitant et spécialiste, photocopie de la CI, suivi des heures, convention de stage | R22: Situation familiale Nombre d’enfant(s) Etablissement d'origine, présence d’un aidant, prestation en place (SSIAD, ADMR…) Mesure de protection juridique Droit à l'image | T22: Niveau scolaire, expérience professionnelle (CV) Projet personnalisé, contrat de soutien et d'aide par le travail, formations réalisées, DIPC | U22: Point de vigilance santé / Comportement Carte vitale Mesure de protection judiciaire et RQTH carte d'invalidité Titre de séjour + validité | V22: Concernant la santé | W22: Données sensibles (Art 9) ou données relatives aux condamnations pénales ou aux infractions (Art 10) | X22: Usagers / famille / proches des usagers | Y22: Fondé sur le consentement préalable de la personne physique, | Z22: Non | AA22: Bureau de l'assistante administrative Bureau de la chef de service | AB22: Armoire fermée à clé dans le bureau de l'assistante administrative fermé à clé Copie du PAP dans une armoire du bureau de la chef de service fermé à clé | AC22: serveur & Mediateam & Mail | AD22: Compte rendu d'acc sur le serveur & Médiateam & Mail (sécurisé par User & MDP) | AE22: Interne Berger Levrault | AF22: O | AG22: OUI | AH22: Pas de suppression | AI22: Interne : chef de service, psychologue, moniteurs, animatrice, chargé d'accompagnement social, MPA, directrice, assistante administrative Service RH (formation) et service Paie au siège Externe : OPCO | AJ22: SO | AK22: Non | AL22: SO | AN22: 1 | AO22: 0 | AP22: =$AN22*AO22 -> 0 | AQ22: 0 | AR22: =$AN22*AQ22 -> 0 | AS22: 3 | AT22: =$AN22*AS22 -> 3 | AU22: 0 | AV22: =$AN22*AU22 -> 0 | AW22: 0 | AX22: =$AN22*AW22 -> 0 | AY22: 0 | AZ22: =$AN22*AY22 -> 0 | BA22: 0 | BB22: =$AN22*BA22 -> 0 | BC22: 0 | BD22: =$AN22*BC22 -> 0 | BE22: 0 | BF22: =$AN22*BE22 -> 0 | BG22: 0 | BH22: =$AN22*BG22 -> 0 | BI22: =AP22:AP22+AR22:AR22+AT22:AT22+AV22:AV22+AX22:AX22+AZ22:AZ22+BB22:BB22+BD22:BD22+BF22:BF22+BH22:BH22 -> 3 | BK22: 1 | BO22: X | BR22: X
B23: 17 | C23: ESAT Les espoirs | D23: Usagers Familles et proches des usagers | E23: Accompagnement des usagers - Partie non médicale | F23: 45078 | G23: 19/12/2024 19/08/2025 | H23: MAJ du comentaire MAJ du comentaire (19/08/25) | I23: Groupe CREATIVE | J23: Directeur de l'organisme | K23: Chef de service | L23: Collecter et utiliser des données permettant de construire le projet d’accompagnement personnalisé des usagers et d’organiser et tracer l'accompagnement à apporter | M23: - Elaboration des projets d'accompagnement personnalisés - Paiement des usagers (rémunération garantie) - Gestion des prestations non médicales - Préparation des repas adaptés aux besoins de l'usagers | N23: Usagers | O23: Nom d’usage Nom de naissance Prénom(s) Date d'entrée | R23: situation familiale informations sur sa vie (généalogie, habitude, parcours, habitudes, plaisirs, hygiène, vêtements, toilette, ...) motricité et déplacement prothèses, caractéristiques sensorielles nb d'enfants / d'enfants décédés | T23: Dernière profession | U23: Médecin traitant Contrainte alimentaires | V23: Concernant la santé | W23: Données sensibles (Art 9) ou données relatives aux condamnations pénales ou aux infractions (Art 10) | X23: Usagers / famille / proches des usagers | Y23: Fondé sur le consentement préalable de la personne physique, | Z23: Non | AA23: Bureau de la secrétaire de direction Bureau du Chef du service social Bureau du service d'accompagnement | AB23: Dans une armoire fermée à clé de bureau fermé à clé | AC23: Mediateam Dossier individuel sur le serveur (P:) | AD23: User + MDP Serveur de fichier accessible par tous les salariés | AE23: Interne Berger Levrault | AF23: Mediateam | AG23: Oui | AH23: Mediateam | AI23: Interne : chef de service, assistant social, psychologue, ES, animateur, CESF, moniteurs Externe : Tuteurs/curateurs | AJ23: SO | AK23: Non | AL23: SO | AM23: Prévoit un accompagnement par examen/certification pour aider les usagers à progresser (lecture, écriture, etc…) | AN23: 1 | AO23: 0 | AP23: =$AN23*AO23 -> 0 | AQ23: 0 | AR23: =$AN23*AQ23 -> 0 | AS23: 0 | AT23: =$AN23*AS23 -> 0 | AU23: 0 | AV23: =$AN23*AU23 -> 0 | AW23: 0 | AX23: =$AN23*AW23 -> 0 | AY23: 0 | AZ23: =$AN23*AY23 -> 0 | BA23: 0 | BB23: =$AN23*BA23 -> 0 | BC23: 1 | BD23: =$AN23*BC23 -> 1 | BE23: 0 | BF23: =$AN23*BE23 -> 0 | BG23: 0 | BH23: =$AN23*BG23 -> 0 | BI23: =AP23:AP23+AR23:AR23+AT23:AT23+AV23:AV23+AX23:AX23+AZ23:AZ23+BB23:BB23+BD23:BD23+BF23:BF23+BH23:BH23 -> 1 | BK23: 1 | BO23: X | BR23: X
B24: 18 | C24: SAVS Tinténiac | D24: Usagers Familles et proches des usagers | E24: Accompagnement des usagers - Partie non médicale | F24: 45090 | G24: 02/09/2024 28/07/2025 | H24: Modif du stockage numérique que sur Mediateam Modif données sensibles colectées 28/07/25 | I24: Groupe CREATIVE | J24: Directeur de l'organisme | K24: Chef de service | L24: Collecter et utiliser des données permettant de construire le projet d’accompagnement personnalisé des usagers et d’organiser et tracer l'accompagnement à apporter | M24: - Elaboration des projets d'accompagnement personnalisés - Gestion des prestations non médicales - Participation financière versée en fin d'année par les personnes accompagnées (30€) | N24: Usagers Familles et proches des usagers | O24: Nom d’usage Nom de naissance Prénom(s) | R24: Dernière profession situation familiale informations sur sa vie (généalogie, habitude, parcours...) motricité et déplacement, caractéristiques handicap nb d'enfants / d'enfants décédés | S24: - aides financières AH & PCH & APL& APA - Fiche d'impôt - demande de virement | T24: Parcours scolaire et professionnel | V24: Pas de donnée sensible | W24: Aucun cas retenu | X24: Usagers / famille / proches des usagers | Y24: Fondé sur le consentement préalable de la personne physique, | Z24: Non | AA24: SO | AB24: SO | AC24: Mediateam | AD24: Accès User + MDP | AE24: Berger Levrault | AF24: Durée de l'éditeur | AG24: Oui | AH24: Durée de l'éditeur | AI24: Interne : Salariés Externe : SO | AJ24: SO | AK24: Non | AL24: SO | AO24: 0 | AP24: =$AN24*AO24 -> 0 | AQ24: 0 | AR24: =$AN24*AQ24 -> 0 | AS24: 0 | AT24: =$AN24*AS24 -> 0 | AU24: 0 | AV24: =$AN24*AU24 -> 0 | AW24: 0 | AX24: =$AN24*AW24 -> 0 | AY24: 0 | AZ24: =$AN24*AY24 -> 0 | BA24: 0 | BB24: =$AN24*BA24 -> 0 | BC24: 0 | BD24: =$AN24*BC24 -> 0 | BE24: 0 | BF24: =$AN24*BE24 -> 0 | BG24: 0 | BH24: =$AN24*BG24 -> 0 | BI24: =AP24:AP24+AR24:AR24+AT24:AT24+AV24:AV24+AX24:AX24+AZ24:AZ24+BB24:BB24+BD24:BD24+BF24:BF24+BH24:BH24 -> 0 | BK24: 1 | BO24: X | BR24: X
B25: 19 | C25: SAVA Itinéraire Bis | D25: Usagers Familles et proches des usagers | E25: Accompagnement des usagers | F25: 45090 | G25: 13/08/2024 15/07/2025 | H25: Modification de la partie stockage physique Ajout de précision sur la partie papier (15/07/25) | I25: Groupe CREATIVE | J25: Directeur de l'organisme | K25: Chef de service | L25: Collecter et utiliser des données permettant de construire le projet d’accompagnement personnalisé des usagers et d’organiser et tracer l'accompagnement à apporter | M25: - Elaboration des projets d'accompagnement personnalisés - Gestion des prestations non médicales - Préparation des repas adaptés aux besoins de l'usager | N25: Usagers Familles et proches des usagers | O25: Nom d’usage Nom de naissance Prénom(s) | R25: Dernière profession situation familiale informations sur sa vie (généalogie, habitude, parcours, habitudes, plaisirs, hygiène, vêtements, toilette, ...) motricité et deplacement prothèses, caractéristiques sensorielles nb d'enfants / d'enfants décédés | V25: Pas de donnée sensible | W25: Aucun cas retenu | X25: Usagers / famille / proches des usagers | Y25: Fondé sur le consentement préalable de la personne physique, | Z25: Non | AA25: Bureau des éducateurs | AB25: Quelques dossiers papier reçu ou imprimé dans le caisson des éducateurs, fermé à clé De moins en moins de dossier papier (informations temporaires avant numérisation) | AC25: Mediateam | AD25: User + mdp | AE25: Berger Levrault | AF25: Mediateam | AG25: Oui | AH25: Mediateam | AI25: Interne : Equipe pédagogique Externe : SO | AJ25: SO | AK25: Non | AL25: SO | AO25: 0 | AP25: =$AN25*AO25 -> 0 | AQ25: 0 | AR25: =$AN25*AQ25 -> 0 | AS25: 2 | AT25: =$AN25*AS25 -> 0 | AU25: 0 | AV25: =$AN25*AU25 -> 0 | AW25: 0 | AX25: =$AN25*AW25 -> 0 | AY25: 0 | AZ25: =$AN25*AY25 -> 0 | BA25: 0 | BB25: =$AN25*BA25 -> 0 | BC25: 0 | BD25: =$AN25*BC25 -> 0 | BE25: 0 | BF25: =$AN25*BE25 -> 0 | BG25: 0 | BH25: =$AN25*BG25 -> 0 | BI25: =AP25:AP25+AR25:AR25+AT25:AT25+AV25:AV25+AX25:AX25+AZ25:AZ25+BB25:BB25+BD25:BD25+BF25:BF25+BH25:BH25 -> 0 | BK25: 1 | BO25: X | BR25: X
B26: 20 | C26: Résidence La Combe | D26: Usagers Familles et proches des usagers | E26: Accompagnement des usagers - Partie non médicale | F26: 45076 | G26: 45561 | H26: Changement des Données sur le comportement et la vie personnelle et ajout de l'emplacement physique pour les données de jugement | I26: Groupe CREATIVE | J26: Directeur de l'organisme | K26: Chef de service | L26: Collecter et utiliser des données permettant de construire le projet d’accompagnement personnalisé des usagers et d’organiser et tracer l'accompagnement à apporter | M26: - Elaboration des projets d'accompagnement personnalisés - Gestion des prestations non médicales - Préparation des repas adaptés aux besoins de l'usager | N26: Usagers Familles et proches des usagers | O26: Nom d’usage Nom de naissance Prénom(s) | R26: dernière profession situation familiale informations sur sa vie (généalogie, habitude, parcours, plaisirs, hygiène, ...) motricité et deplacement prothèses, caractéristiques sensorielles nb d'enfants / d'enfants décédés | U26: Copie MDPH, Copie des pièces d'identité, de jugement (tutelle/curatelle et infraction pénale & délit/crime), Info sur les échanges avec partenaires, Projet personnalisé, NIR | V26: Condamnations pénales ou infractions & NIR | W26: Données sensibles (Art 9) ou données relatives aux condamnations pénales ou aux infractions (Art 10) | X26: usager / famille / proches des usagers / organisme de protection juridique | Y26: Fondé sur le consentement préalable de la personne physique, | Z26: Non | AA26: Bureau de la cheffe de service | AB26: Jugement dans une armoire du bureau de la cheffe de service fermé à clé | AC26: Mediateam | AD26: Accès restreint par utilisateur | AE26: Berger Levrault | AF26: Mediateam | AG26: Oui | AH26: Mediateam | AI26: Interne :Directrice et chefs de service, professionnels, infirmière | AJ26: SO | AK26: Non | AL26: SO | AN26: 1 | AO26: 0 | AP26: =$AN26*AO26 -> 0 | AQ26: 0 | AR26: =$AN26*AQ26 -> 0 | AS26: 0 | AT26: =$AN26*AS26 -> 0 | AU26: 0 | AV26: =$AN26*AU26 -> 0 | AW26: 0 | AX26: =$AN26*AW26 -> 0 | AY26: 0 | AZ26: =$AN26*AY26 -> 0 | BA26: 0 | BB26: =$AN26*BA26 -> 0 | BC26: 0 | BD26: =$AN26*BC26 -> 0 | BE26: 0 | BF26: =$AN26*BE26 -> 0 | BG26: 0 | BH26: =$AN26*BG26 -> 0 | BI26: =AP26:AP26+AR26:AR26+AT26:AT26+AV26:AV26+AX26:AX26+AZ26:AZ26+BB26:BB26+BD26:BD26+BF26:BF26+BH26:BH26 -> 0 | BJ26: Se référer au document word de préconisation | BK26: 1 | BO26: X | BR26: X
B27: 21 | C27: Résidence du parc des bois | D27: Usagers Familles et proches des usagers | E27: Accompagnement des usagers | F27: 45076 | G27: 25/06/2024 24/06/2025 | H27: Ajout des informations papiers Ajout précision sur Médiateam | I27: Groupe CREATIVE | J27: Directeur de l'organisme | K27: Chef de service | L27: Collecter et utiliser des données permettant de construire le projet d’accompagnement personnalisé des usagers et d’organiser et tracer l'accompagnement à apporter | M27: - Elaboration des projets d'accompagnement personnalisés - Gestion des prestations non médicales - Préparation des repas adaptés aux besoins de l'usager | N27: Usagers Familles et proches des usagers | O27: Nom d’usage Nom de naissance Prénom(s) | R27: dernière profession situation familiale informations sur sa vie (généalogie, habitude, parcours, habitudes, plaisirs, hygiène, vêtements, toilette, ...) motricité et deplacement prothèses, caractéristiques sensorielles nb d'enfants / d'enfants décédés | U27: Copie MDPH, Copie des pièces d'identité, de jugement, Info sur les échanges avec partenaires, Projet personnalisé des jeunes, NIR | V27: Concernant la santé | W27: Données sensibles (Art 9) ou données relatives aux condamnations pénales ou aux infractions (Art 10) | X27: usager / famille / proches des usagers / organisme de protection juridique | Y27: Fondé sur le consentement préalable de la personne physique, | Z27: Non | AA27: Bureau des éducateurs | AB27: Dossiers papier des usagers dans le bureau des éducateurs (remis au départ de l'usager) | AC27: Mediateam (principalement) | AD27: Accès restreint par utilisateur | AE27: Berger Levrault | AF27: Mediateam | AG27: Oui | AH27: Mediateam | AI27: Interne :Directrice et chefs de service, professionnels, infirmière | AJ27: SO | AK27: Non | AL27: SO | AN27: 1 | AO27: 0 | AP27: =$AN27*AO27 -> 0 | AQ27: 0 | AR27: =$AN27*AQ27 -> 0 | AS27: 0 | AT27: =$AN27*AS27 -> 0 | AU27: 0 | AV27: =$AN27*AU27 -> 0 | AW27: 0 | AX27: =$AN27*AW27 -> 0 | AY27: 0 | AZ27: =$AN27*AY27 -> 0 | BA27: 0 | BB27: =$AN27*BA27 -> 0 | BC27: 0 | BD27: =$AN27*BC27 -> 0 | BE27: 0 | BF27: =$AN27*BE27 -> 0 | BG27: 0 | BH27: =$AN27*BG27 -> 0 | BI27: =AP27:AP27+AR27:AR27+AT27:AT27+AV27:AV27+AX27:AX27+AZ27:AZ27+BB27:BB27+BD27:BD27+BF27:BF27+BH27:BH27 -> 0 | BJ27: Se référer au document word de préconisation | BK27: 1 | BO27: X | BR27: X
B28: 22 | C28: Résidences Les Gantelles et Les Fougères | D28: Usagers Familles et proches des usagers | E28: Accompagnement des usagers - Partie non médicale | F28: 45582 | G28: 45838 | H28: Ajout d'un commentaire + données info médicales ajoutées et leurs stockages | I28: Groupe CREATIVE | J28: Directeur de l'organisme | K28: Cheffe de service | L28: Collecter et utiliser des données permettant de construire le projet d’accompagnement personnalisé des usagers et d’organiser et tracer l'accompagnement à apporter | M28: - Elaboration des projets d'accompagnement personnalisés - Gestion des prestations non médicales - Préparation des repas adaptés aux besoins de l'usager | N28: Usagers Familles et proches des usagers | O28: Nom d’usage Nom de naissance Prénom(s) | R28: dernière profession situation familiale informations sur sa vie (généalogie, habitude, parcours, habitudes, plaisirs, hygiène, vêtements, toilette, ...) motricité et deplacement prothèses, caractéristiques sensorielles nb d'enfants / d'enfants décédés | U28: Copie MDPH, Copie des pièces d'identité, de jugement, Info sur les échanges avec partenaires, Projet personnalisé des jeunes, NIR Certaines informations médicales fournies par le résident | V28: Concernant la santé | W28: Données sensibles (Art 9) ou données relatives aux condamnations pénales ou aux infractions (Art 10) | X28: usager / famille / proches des usagers / organisme de protection juridique | Y28: Fondé sur le consentement préalable de la personne physique, | Z28: Non | AA28: Bureau du personnel Les Fougères Bureau du personnel Les Fougères Entrée Foyer Les Gantelles Bureau de service Foyer Les Gantelles Bureau des salariés Foyer Les Gantelles | AB28: Archives des transmissions, de la liste des résidents avec n° de chambre, nom et prénom et bannette par usagers, tableau des transmissions avec nom-prénom, n° de chambre, heures de kiné et douche, Armoire avec les dossiers des résidents et Affichage de l'annuaire résident dans le bureau du personnel Les Fougères fermé à clé Dossier des accompagnements temporaires sur l'ordinateur dans le bureau du personnel Les Fougères fermé à clé Boites aux lettres avec nom-prénom et n° d'appartement aux Foyer Les Gantelles Boites à clés des appartements dans le bureau de service Foyer Les Gantelles fermé à clé Boite des dossiers résidents au quotidien (PAP), Caisson des transmissions, Classeur contenant l'agenda des activités et des sorties des résidents et Affichage des transissions dans le bureau des salariés Foyer Les Gantelles fermés à clé Classeur des résidents avec potentiellement des données médicales dans la salle de professionnelle fermée à clé | AC28: SO | AD28: SO | AE28: SO | AF28: Non définie | AG28: Oui | AH28: Non définie | AI28: Interne: Cheffe de service, professionnels | AJ28: SO | AK28: Non | AL28: SO | AM28: Actuellement les résidents gèrent les points suivants en attendant que cela reviennent aux foyers : - Préparation des repas adaptés aux besoins de l'usager | AN28: 1 | AO28: 0 | AP28: =$AN28*AO28 -> 0 | AQ28: 0 | AR28: =$AN28*AQ28 -> 0 | AS28: 0 | AT28: =$AN28*AS28 -> 0 | AU28: 0 | AV28: =$AN28*AU28 -> 0 | AW28: 0 | AX28: =$AN28*AW28 -> 0 | AY28: 0 | AZ28: =$AN28*AY28 -> 0 | BA28: 0 | BB28: =$AN28*BA28 -> 0 | BC28: 0 | BD28: =$AN28*BC28 -> 0 | BE28: 0 | BF28: =$AN28*BE28 -> 0 | BG28: 0 | BH28: =$AN28*BG28 -> 0 | BI28: =AP28:AP28+AR28:AR28+AT28:AT28+AV28:AV28+AX28:AX28+AZ28:AZ28+BB28:BB28+BD28:BD28+BF28:BF28+BH28:BH28 -> 0 | BJ28: Se référer au document word de préconisation | BK28: 1 | BO28: X | BR28: X
B29: 23 | C29: DIME Rennes | D29: Usagers, familles, proches | E29: Accompagnement médical des usagers | F29: 44277 | G29: 45855 | H29: Modification des données collectées | I29: Groupe CREATIVE | J29: Directeur de l'organisme | K29: Responsable des soins infirmiers | L29: Organisation du parcours de soin | M29: - Assurer un suivi médicalisé adapté à la personne concernée - Gestion du dossier médical (Médiateam) - Gestion des résultats d'analyse / radio / compte-rendus médicaux - Gestion de décision - Gestion des RV médicaux - Gestion du planning de consultation… - Gestion des traitements de soins - Gestion des traitements médicamenteux - Gestion du DLU - Gestion des campganes de vaccination - Gestion du DMP | N29: Usagers | O29: Nom, prénom, date de naissance, photo | U29: Santé, ordonannce, NIR, carnet de vaccination | V29: Concernant la santé + NIR | W29: Données concernant des personnes dans l’incapacité de consentir ou d’exercer leurs droits (Enfants, patients, personnes agées…) | X29: usager, personnes médicales et para médicales | Y29: Fondé sur l’exécution d’un contrat avec la personne physique concernée, | Z29: Non | AA29: Salle de communication IME Bureau du docteur de l'IME Infirmerie IME | AB29: Version dans les dossiers papier administratifs dans la salle de communication fermé à clé Notes personnels dans armoire fermé et bureau du docteur de l'IME fermé Dossier dans l'infirmerie dans armoire fermé et bureau fermé | AC29: Serveur (Assistante sociale) Mediateam | AD29: Accès restreint par utilisateur | AE29: Interne Berger Levrault | AF29: SO | AG29: OUI | AH29: 3 ans Pas de destruction pour le docteur IME | AI29: Interne : Chargée d'insertion IME, Docteur IME, Infirmière IME Externe : | AJ29: SO | AK29: Non | AL29: SO | AN29: 2 | AO29: 0 | AP29: =$AN29*AO29 -> 0 | AQ29: 0 | AR29: =$AN29*AQ29 -> 0 | AS29: 2 | AT29: =$AN29*AS29 -> 4 | AU29: 0 | AV29: =$AN29*AU29 -> 0 | AW29: 0 | AX29: =$AN29*AW29 -> 0 | AY29: 0 | AZ29: =$AN29*AY29 -> 0 | BA29: 0 | BB29: =$AN29*BA29 -> 0 | BC29: 0 | BD29: =$AN29*BC29 -> 0 | BE29: 0 | BF29: =$AN29*BE29 -> 0 | BG29: 0 | BH29: =$AN29*BG29 -> 0 | BI29: =AP29:AP29+AR29:AR29+AT29:AT29+AV29:AV29+AX29:AX29+AZ29:AZ29+BB29:BB29+BD29:BD29+BF29:BF29+BH29:BH29 -> 4 | BJ29: Se référer au document word de préconisation | BK29: 1 | BO29: X | BR29: X
B30: 24 | C30: DIME La Bretèche | D30: Usagers, familles, proches | E30: Accompagnement médical des usagers | F30: 44277 | G30: 23/08/2024 18/07/2025 | H30: Ajout donnée Ancien bilan médicaux, Analyses sanguines et autres… Ajout commentaire - 18/07/2025 | I30: Groupe CREATIVE | J30: Directeur de l'organisme | K30: Responsable des soins infirmiers | L30: Organisation du parcours de soin | M30: - Assurer un suivi médicalisé adapté à la personne concernée - Gestion du dossier médical (Médiateam) - Gestion des résultats d'analyse / radio / compte-rendus médicaux - Gestion de décision - Gestion des RV médicaux - Gestion du planning de consultation… - Gestion des traitements de soins - Gestion des traitements médicamenteux - Gestion du DLU - Gestion des campganes de vaccination - Gestion du DMP | N30: Usagers | O30: Nom, prénom, date de naissance, photo | U30: Dossier de Santé, ordonannce, NIR, Ancien bilan médicaux (ortho, neuro, psychomot, pédopsy…), Analyses sanguines et autres… | V30: Concernant la santé + NIR | W30: Données concernant des personnes dans l’incapacité de consentir ou d’exercer leurs droits (Enfants, patients, personnes agées…) | X30: usager, personnes médicales et para médicales | Y30: Fondé sur l’exécution d’un contrat avec la personne physique concernée, | Z30: Non | AA30: DIME La Bretèche Internat | AB30: Transmission des régimes alimentaires (PAI) aux restaurants scolaires par le DIME La Bretèche Copie des ordonnances par délégation des infirmières pour la distribution des médicaments à l'internat | AC30: SO | AD30: SO | AE30: Interne | AF30: SO | AG30: OUI | AH30: 3 ans | AI30: Interne : Directrice et chefs de service Externe : | AJ30: SO | AK30: Non | AL30: SO | AM30: Tout en papier actuellement A venir sur médiateam fin 2025 Chaque chauffeur aura sous scellé une fiche d'urgence | AN30: 2 | AO30: 0 | AP30: =$AN30*AO30 -> 0 | AQ30: 0 | AR30: =$AN30*AQ30 -> 0 | AS30: 1 | AT30: =$AN30*AS30 -> 2 | AU30: 1 | AV30: =$AN30*AU30 -> 2 | AW30: 0 | AX30: =$AN30*AW30 -> 0 | AY30: 0 | AZ30: =$AN30*AY30 -> 0 | BA30: 0 | BB30: =$AN30*BA30 -> 0 | BC30: 0 | BD30: =$AN30*BC30 -> 0 | BE30: 0 | BF30: =$AN30*BE30 -> 0 | BG30: 0 | BH30: =$AN30*BG30 -> 0 | BI30: =AP30:AP30+AR30:AR30+AT30:AT30+AV30:AV30+AX30:AX30+AZ30:AZ30+BB30:BB30+BD30:BD30+BF30:BF30+BH30:BH30 -> 4 | BJ30: Se référer au document word de préconisation | BK30: 1 | BO30: X | BR30: X
B31: 25 | C31: Siège | D31: Candidats | E31: Gestion des recrutements | F31: 44277 | G31: 25/07/2024 08/07/2025 | H31: RH - Ajout d'un commentaire | I31: Groupe CREATIVE | J31: Directeur de l'organisme | K31: Service RH | L31: Recruter | M31: - Récolte des CV et lettre de motivation par mail + plateforme jobboard + Site internet + Boite mail - Entretien - Utilisation de cabinet extérieur (de temps en temps) - Appel aux agences d'intérim - Tests de compétence | N31: Candidats | O31: Nom, prénom, date de naissance, n°de tel, adresse mail, adresse postale | R31: Situation de famille, loisirs, âge | S31: Demande de salaire | T31: Formations, expériences précédentes | U31: SO | V31: Pas de donnée sensible | W31: Aucun cas retenu | X31: Par candidat | Y31: Fondé sur le consentement préalable de la personne physique, | Z31: Oui | AA31: Bureau du Service RH Directeur de l'établissement concerné Chef de service DIME La Bretèche | AB31: Bureau RH fermé à clé pour les candidats retenus Pochette dans le bureau des chefs de service DIME la Bretèche fermé à clé Bureau de la directrce de l'ESAT | AC31: Mail+ jobborard( indeed, Apec, pole emploi) Dossier Réseau RH Serveur ESAT Candidature via le site internet | AD31: Accès au répertoire réseau réservé au service RH, directeur et chefs de service Plateforme sécurisé Regroupement des candidature sur une seule adresse mail | AE31: Serveur + cabinet+ fournisseur | AF31: Papier : destruction Mail : pas de gestion de l'archivage ESAT : pas de conservation | AG31: Non | AH31: SO | AI31: Interne : Service RH/Paie Directeur chef de service Moniteur Principaux d'Atelier Externe : Médecin MSA, Pole emploi | AJ31: SO | AK31: Non | AL31: SO | AM31: Pas de contrôle ni de mail envoyé aux candidats sur la durée de conservation des données (A vérifier). Pas de logiciel de suivi des recrutement. Toutes les secrétaires d'établissement accèdent à ce traitement pour les recrutements concernant leur établissement Mise en place d'une procédure sur le recrutement. | AO31: 0 | AP31: =$AN31*AO31 -> 0 | AQ31: 0 | AR31: =$AN31*AQ31 -> 0 | AS31: 1 | AT31: =$AN31*AS31 -> 0 | AU31: 1 | AV31: =$AN31*AU31 -> 0 | AW31: 0 | AX31: =$AN31*AW31 -> 0 | AY31: 0 | AZ31: =$AN31*AY31 -> 0 | BA31: 0 | BB31: =$AN31*BA31 -> 0 | BC31: 0 | BD31: =$AN31*BC31 -> 0 | BE31: 0 | BF31: =$AN31*BE31 -> 0 | BG31: 0 | BH31: =$AN31*BG31 -> 0 | BI31: =AP31:AP31+AR31:AR31+AT31:AT31+AV31:AV31+AX31:AX31+AZ31:AZ31+BB31:BB31+BD31:BD31+BF31:BF31+BH31:BH31 -> 0 | BJ31: Se référer au document word de préconisation | BK31: 0
B32: 26 | C32: Siège | D32: Professionnels | E32: Gestion administrative du personnel | F32: 44277 | G32: 25/07/2024 10/07/2025 | H32: Ajout des infos papier du service Paie | I32: Groupe CREATIVE | J32: Directeur de l'organisme | K32: Responsables RH | L32: Gestion administrative et paye du personnel | M32: - Gestion du dossier professionnel des salariés; (( CV, pièce administrative tel que casier judiciaire, carte d'identité, diplome, RIB, carte vitale, permis) - gestion de la paie - gestion des contrats de travail, avenants, documents disciplinaires - réalisation d'états statistiques ou de listes d'employés pour répondre à des besoins de gestion administrative ; - gestion des élections professionnelles - gestion des réunions du CSE - gestion des aptitudes médicales par rapport au poste - gestion des mutuelles et prévoyances - gestion des contacts en cas d'urgence - gestion des absences (congés, maladie, évènements familaiux, …) - gestion des accidents de travail (et presque accident) - gestion RQTH - entretien de carrière / individuel - gestion du droit à l'image - gestion des mots de passe - gestion des courrriers divers avec le salariés (démission, mécontentement,...) | N32: Salariés | O32: Nom, prénom, date de naissance, n°de tel, adresse mail, adresse postale extrait bulletin casier judiciaire permis / carte grise numéro d'urgence-personne à prévenir | P32: Accès aux messageries professionnelles Identifiants des sessions Identifiants applications (liste) Identifiants sites (liste) | R32: Situation de famille (enfant), vaccination | S32: revenus, données bancaires, taux d'imposition, saisie sur salaire | T32: CV, situation professionnelle, scolarité, formation, diplômes, expériences précédentes, situation professionnelle du conjoint, certificat de travail | U32: - données sur les mineurs et conjoint (nom, prénom, date de naissance pour congé paternité, maternité, ) - N° SS : déclaration d'embauche à l'URSAAF, adhésion mutuelle et prévoyance - informations évènements familiaux (mariage, naissance, décès) - titre de séjour + validité - attestation RQTH - appartenance à un syndicat - attestation de la médecine du travail ou certificat médical scolaire - casier judiciaire ou bulletin n°3 | V32: NIR (N° SS) Condamnations pénales ou infractions | W32: Données sensibles (Art 9) ou données relatives aux condamnations pénales ou aux infractions (Art 10) | X32: Par le salarié | Y32: Fondé sur l’exécution d’un contrat avec la personne physique concernée, | Z32: Non | AA32: Bureau RH Bureau Paie | AB32: Dossier salarié dans armoire fermant à clé Bulletin de paie dans un placard du bureau Pais fermé à clé Archive bulletin de paie dans les bureaux Paie fermé clé ou dans une salle d'archives fermé à clé | AC32: ALPHA GRH, EXCEL Onedrive (DIME La Bretèche) Serveur | AD32: Accès réservé au service RH Assistante de direction IME : Met à jour la BDD (ficher Excel) du personnel interne de l'établissement Dossier partagé pour les chefs de services et directrice du DIME La Bretèche Tableau Excel avec MDP de chacun sur le serveur de fichier accessible par tout le monde pour le SAVA Itinéraire bis | AE32: Interne | AF32: Pas de délais au cours de l’exécution du contrat de travail Délais en cas de rupture du contrat de travail | AG32: Oui | AH32: Pas de délais sauf en cas de rupture du contrat de travail : - 10 ans pour les bulletins de paie - 5 après pour les dossiers du personnel 5 ans à l'IME | AI32: Interne : Service RH Directeur, chefs de service Prestataire informatique secrétaire de direction IME Externe : URSAAF, caisse de retraite, gestionnaire complémentaire santé et prévoyance | AJ32: Transmission des informations obligatoires | AK32: Non | AL32: SO | AM32: Attention archivage papier RH accessible par toutes personnes ayant une clé de l'établissement de Saint symphorien. ESAT : contrat de travail, Entretien pro et annuel (svg serveur et bureau de la directrice), vérif des permis, extrait de casier judiciaire, formation, suivi des rendez-vous médecine du travail | AN32: 2 | AO32: 0 | AP32: =$AN32*AO32 -> 0 | AQ32: 0 | AR32: =$AN32*AQ32 -> 0 | AS32: 1 | AT32: =$AN32*AS32 -> 2 | AU32: 0 | AV32: =$AN32*AU32 -> 0 | AW32: 0 | AX32: =$AN32*AW32 -> 0 | AY32: 0 | AZ32: =$AN32*AY32 -> 0 | BA32: 0 | BB32: =$AN32*BA32 -> 0 | BC32: 1 | BD32: =$AN32*BC32 -> 2 | BE32: 0 | BF32: =$AN32*BE32 -> 0 | BG32: 0 | BH32: =$AN32*BG32 -> 0 | BI32: =AP32:AP32+AR32:AR32+AT32:AT32+AV32:AV32+AX32:AX32+AZ32:AZ32+BB32:BB32+BD32:BD32+BF32:BF32+BH32:BH32 -> 4 | BJ32: Se référer au document word de préconisation | BK32: 1 | BO32: X
B33: 27 | C33: Résidences Les Gantelles et Les Fougères | D33: Professionnels | E33: Gestion administrative du personnel | F33: 45582 | G33: 45838 | H33: Ajout d'un commentaire | I33: Groupe CREATIVE | J33: Directeur de l'organisme | K33: Cheffe de service | L33: Gestion administrative et paye du personnel | M33: - Gestion du dossier professionnel des salariés; (( CV, pièce administrative tel que casier judiciaire, carte d'identité, diplome, RIB, carte vitale, permis) - gestion de la paie - gestion des contrats de travail, avenants, documents disciplinaires - réalisation d'états statistiques ou de listes d'employés pour répondre à des besoins de gestion administrative ; - gestion des élections professionnelles - gestion des réunions du CSE - gestion des aptitudes médicales par rapport au poste - gestion des mutuelles et prévoyances - gestion des contacts en cas d'urgence - gestion des absences (congés, maladie, évènements familaiux, …) - gestion des accidents de travail (et presque accident) - gestion RQTH - entretien de carrière / individuel - gestion du droit à l'image - gestion des mots de passe - gestion des courrriers divers avec le salariés (démission, mécontentement,...) | N33: Salariés | O33: Nom, prénom, date de naissance, n°de tel, adresse mail, adresse postale extrait bulletin casier judiciaire permis / carte grise numéro d'urgence-personne à prévenir | P33: Accès aux messageries professionnelles Identifiants des sessions Identifiants applications (liste) Identifiants sites (liste) | R33: Situation de famille (enfant), vaccination | S33: revenus, données bancaires, taux d'imposition, saisie sur salaire | T33: CV, situation professionnelle, scolarité, formation, diplômes, expériences précédentes, situation professionnelle du conjoint, certificat de travail | U33: - données sur les mineurs et conjoint (nom, prénom, date de naissance pour congé paternité, maternité, ) - N° SS : déclaration d'embauche à l'URSAAF, adhésion mutuelle et prévoyance - informations évènements familiaux (mariage, naissance, décès) - titre de séjour + validité - attestation RQTH - appartenance à un syndicat - attestation de la médecine du travail ou certificat médical scolaire - casier judiciaire ou bulletin n°3 | V33: NIR (N° SS) Condamnations pénales ou infractions | W33: Données sensibles (Art 9) ou données relatives aux condamnations pénales ou aux infractions (Art 10) | X33: Par le salarié | Y33: Fondé sur l’exécution d’un contrat avec la personne physique concernée, | Z33: Non | AA33: Bureau de la direction Bureau du personnel Les Fougères Bureau de service Foyer Les Gantelles Bureau des salariés Foyer Les Gantelles | AB33: Bannette individuelle contenant les dossiers du personnel avec nom-prénom sur chacune dans le bureau de la direction fermé à clé Armoire fermée à clé contenant les registre du personnel dans le bureau de la direction fermé à clé Affichage de l'annuaire salarié, Affichage des CR de réunions de service et Casier du personnel individuel avec cadenas fourni par l'établissement dans le bureau du personnel Les Fougères fermé à clé Affichage des numéros de téléphone dans le bureau de service Foyer Les Gantelles fermé à clé Bannette professionnelle, Affichage numéros de téléphone et Casier salarié avec cadenas dans le bureau des salariés Foyer Les Gantelles fermés à clé | AC33: SO | AD33: SO | AE33: SO | AF33: Non définie | AG33: Oui | AH33: Non définie | AI33: Interne : Service RH Directeur, chefs de service Externe : URSAAF, caisse de retraite, gestionnaire complémentaire santé et prévoyance | AJ33: Transmission des informations obligatoires | AK33: Non | AL33: SO | AM33: Attention archivage papier dans chaque foyer, à regrouper au siège après complète intégration des 2 foyers Copie des dossiers transmises au service RH | AN33: 2 | AO33: 0 | AP33: =$AN33*AO33 -> 0 | AQ33: 0 | AR33: =$AN33*AQ33 -> 0 | AS33: 2 | AT33: =$AN33*AS33 -> 4 | AU33: 0 | AV33: =$AN33*AU33 -> 0 | AW33: 0 | AX33: =$AN33*AW33 -> 0 | AY33: 0 | AZ33: =$AN33*AY33 -> 0 | BA33: 0 | BB33: =$AN33*BA33 -> 0 | BC33: 1 | BD33: =$AN33*BC33 -> 2 | BE33: 0 | BF33: =$AN33*BE33 -> 0 | BG33: 0 | BH33: =$AN33*BG33 -> 0 | BI33: =AP33:AP33+AR33:AR33+AT33:AT33+AV33:AV33+AX33:AX33+AZ33:AZ33+BB33:BB33+BD33:BD33+BF33:BF33+BH33:BH33 -> 6 | BJ33: Se référer au document word de préconisation | BK33: 1 | BO33: X
B34: 28 | C34: Résidence du parc des bois | D34: Intérimaires | E34: Gestion des intérimaires | F34: 44277 | G34: 25/06/2024 24/06/2025 | H34: Ajout du trt spécifique pour la résidence du parc des bois suite revue du trt Ajout d'un commenraire | I34: Groupe CREATIVE | J34: Directeur de l'organisme | K34: Chefs de service et directeurs | L34: Collecter et utiliser des données permettant d'accueillir des intérimaires (contrats, plannings,…) | M34: - gestion du dossier ( CV, pièce administrative tel que casier judiciaire, carte d'identité, diplome, RIB, carte vitale) - gestion des conventions, contrat, documents disciplinaires - réalisation d'états statistiques pour répondre à des besoins de gestion administrative ; - gestion des contacts en cas d'urgence - gestion des absences (congés, maladie, évènements familaiux, …) - gestion des heures - Facturation | N34: Intérimaires | O34: Nom, prénom, date de naissance, n°de tel | S34: Rémunération | V34: Pas de donnée sensible | W34: Aucun cas retenu | X34: Par l'intérimaire et l'agence intérim | Y34: Fondé sur le consentement préalable de la personne physique, | Z34: Oui | AA34: SO | AB34: SO | AC34: SKORANN (ancinnement Medicoop) | AD34: Accès réservé aux directeurs, chef de service et service RH) | AE34: SKORANN | AF34: 0 | AG34: Oui | AH34: Ne sait pas | AI34: Interne : Chefs de service et directeurs, Secrétaires d'établissement Externe : SKORANN | AJ34: Transmission des informations obligatoires | AK34: Non | AL34: SO | AM34: Mise en place de CDD car une loi oblige les intérims à avoir 2 ans d'XP | AO34: 0 | AP34: =$AN34*AO34 -> 0 | AQ34: 0 | AR34: =$AN34*AQ34 -> 0 | AS34: 2 | AT34: =$AN34*AS34 -> 0 | AU34: 0 | AV34: =$AN34*AU34 -> 0 | AW34: 0 | AX34: =$AN34*AW34 -> 0 | AY34: 0 | AZ34: =$AN34*AY34 -> 0 | BA34: 0 | BB34: =$AN34*BA34 -> 0 | BC34: 0 | BD34: =$AN34*BC34 -> 0 | BF34: =$AN34*BE34 -> 0 | BG34: 0 | BH34: =$AN34*BG34 -> 0 | BI34: =AP34:AP34+AR34:AR34+AT34:AT34+AV34:AV34+AX34:AX34+AZ34:AZ34+BB34:BB34+BD34:BD34+BF34:BF34+BH34:BH34 -> 0 | BK34: 1
B35: 29 | C35: DIME La Bretèche DIME L'espoir DIME Rennes Résidence La Combe Résidences Les Gantelles et Les Fougères SAVA Itinéraire Bis | D35: Intérimaires | E35: Gestion des intérimaires | F35: 44277 | G35: 25/06/2024 23/08/2024 30/06/2025 | H35: séparation des infos spécifique pour la résidence du parc des bois suite revue du trt DIME La Bretèche : ajout de société d'intérim Ajout commentaire pour Les Foyers | I35: Groupe CREATIVE | J35: Directeur de l'organisme | K35: Chefs de service et directeurs | L35: Collecter et utiliser des données permettant d'accueillir des intérimaires (contrats, plannings,…) | M35: - gestion du dossier ( CV, pièce administrative tel que casier judiciaire, carte d'identité, diplome, RIB, carte vitale) - gestion des conventions, contrat, documents disciplinaires - réalisation d'états statistiques pour répondre à des besoins de gestion administrative ; - gestion des contacts en cas d'urgence - gestion des absences (congés, maladie, évènements familaiux, …) - gestion des heures - Facturation | N35: Intérimaires | O35: Nom, prénom, date de naissance, n°de tel, adresse mail, matricule, adresse postale | R35: Situation de famille (enfant) Casier judiciaire | S35: Rémunération | T35: CV Formations, expériences précédentes | U35: - informations évènements familiaux (mariage, naissance, décès - titre de séjour + validité | V35: NIR (N° SS) | W35: Données sensibles (Art 9) ou données relatives aux condamnations pénales ou aux infractions (Art 10) | X35: Par l'intérimaire et l'agence intérim | Y35: Fondé sur le consentement préalable de la personne physique, | Z35: Oui | AA35: SO | AB35: SO | AC35: SKORANN (Remplace Medicoop) avec le logiciel UNI TT ADECCO médical JOBANDBOX APPEL Médical CDD de l'asso La Bretèche pour Les foyers | AD35: Accès réservé aux directeurs, chef de service et service RH) | AE35: SKORANN ADECCO médical JOBANDBOX APPEL Médical | AF35: Propre à chaque société | AG35: Oui | AH35: Propre à chaque société | AI35: Interne : Chefs de service et directeurs, Secrétaires d'établissement Externe : SKORANN | AJ35: Transmission des informations obligatoires | AK35: Non | AL35: SO | AM35: Directeur, Chef de services => accède aux dossiers pour l'admission Foyer Les Gantelles et Les Fougères : utilise des CDD de l'asso La Bretèche | AO35: 0 | AP35: =$AN35*AO35 -> 0 | AQ35: 0 | AR35: =$AN35*AQ35 -> 0 | AS35: 0 | AT35: =$AN35*AS35 -> 0 | AU35: 0 | AV35: =$AN35*AU35 -> 0 | AW35: 0 | AX35: =$AN35*AW35 -> 0 | AY35: 0 | AZ35: =$AN35*AY35 -> 0 | BA35: 0 | BB35: =$AN35*BA35 -> 0 | BC35: 0 | BD35: =$AN35*BC35 -> 0 | BF35: =$AN35*BE35 -> 0 | BG35: 0 | BH35: =$AN35*BG35 -> 0 | BI35: =AP35:AP35+AR35:AR35+AT35:AT35+AV35:AV35+AX35:AX35+AZ35:AZ35+BB35:BB35+BD35:BD35+BF35:BF35+BH35:BH35 -> 0 | BK35: 1 | BO35: X
B36: 30 | C36: ESAT LA Simonière | D36: Intérimaires | E36: Gestion des intérimaires | F36: 44277 | J36: Directeur de l'organisme | K36: Chefs de service et directeurs | L36: Collecter et utiliser des données permettant d'accueillir des intérimaires (contrats, plannings,…) | M36: - gestion du dossier ( CV, pièce administrative tel que casier judiciaire, carte d'identité, diplome, RIB, carte vitale) - gestion des conventions, contrat, documents disciplinaires - réalisation d'états statistiques pour répondre à des besoins de gestion administrative ; - gestion des contacts en cas d'urgence - gestion des absences (congés, maladie, évènements familaiux, …) - gestion des heures - Facturation | N36: Intérimaires | O36: Nom, prénom, date de naissance, n°de tel, adresse mail, matricule, adresse postale | R36: Situation de famille (enfant) Casier judiciaire | S36: Rémunération | T36: CV Formations, expériences précédentes | U36: - informations évènements familiaux (mariage, naissance, décès - titre de séjour + validité | V36: NIR (N° SS) | W36: Données sensibles (Art 9) ou données relatives aux condamnations pénales ou aux infractions (Art 10) | X36: Par l'intérimaire et l'agence intérim | Y36: Fondé sur le consentement préalable de la personne physique, | Z36: Oui | AA36: Bureau de la comptable | AB36: Fermé à clé | AC36: AGRI Intérim, Job Intérim, … | AD36: Accès réservé aux directeurs, chef de service et service RH) | AE36: Editeur | AF36: A voir avec les sociétés d'intérim | AG36: Oui | AH36: Archivés mais pas détruit | AI36: Interne : Chefs de service et directeurs Externe : Société d'intérim | AJ36: Transmission des informations obligatoires | AK36: Non | AL36: SO | AN36: 2 | AO36: 0 | AP36: =$AN36*AO36 -> 0 | AQ36: 0 | AR36: =$AN36*AQ36 -> 0 | AS36: 2 | AT36: =$AN36*AS36 -> 4 | AU36: 0 | AV36: =$AN36*AU36 -> 0 | AW36: 0 | AX36: =$AN36*AW36 -> 0 | AY36: 0 | AZ36: =$AN36*AY36 -> 0 | BA36: 0 | BB36: =$AN36*BA36 -> 0 | BC36: 1 | BD36: =$AN36*BC36 -> 2 | BE36: 0 | BF36: =$AN36*BE36 -> 0 | BG36: 0 | BH36: =$AN36*BG36 -> 0 | BI36: =AP36:AP36+AR36:AR36+AT36:AT36+AV36:AV36+AX36:AX36+AZ36:AZ36+BB36:BB36+BD36:BD36+BF36:BF36+BH36:BH36 -> 6 | BK36: 1 | BO36: X
B37: 31 | C37: Siège | D37: Salariés | E37: Dématérialisation des élections professionnelles | F37: 44277 | I37: Groupe CREATIVE | J37: Directeur de l'organisme | K37: responsable RH | L37: Collecter les votes et les données nécessaire à l'identification pour le vote des élections | M37: - vote | N37: salariés | O37: nom , prénom, adresse mail, adresse postal | R37: date de niassance | S37: / | T37: / | U37: / | V37: Pas de donnée sensible | W37: Aucun cas retenu | X37: par l'association | Y37: Fondé sur le consentement préalable de la personne physique, | Z37: oui | AA37: Dans les bureaux d'AKG-SOLUTIONS situés au 1 rue de l'Artisanat à Ste Gemmes sur Loire, 49130 | AB37: Les bureaux sont protégés par un système d'alarme avec télésurveillance reliés à un centre de contrôle et de gardiennage 24/24. L'entrée principale se fait par clef + badge électronique. L'entrée dans le bureau se fait par une porte verrouillée à clef (différente de la porte principale). Les ordinateurs professionnels des salariés comportent tous un accès avec porte verrouillée + deux mots de passe (1 pour accéder au poste informatique et 1 pour accéder aux données de vote) | AC37: Les données numériques sont stockées par l'hébergeur GANDI dans un datacenter situé à Paris et redondé à Marseille | AD37: Accès réservé au service RH | AE37: GANDI | AF37: Durée des élections + 15 jours supplémentaires (obligation légale pour les élections CSE après clôture du vote) | AG37: Non | AH37: SO | AI37: Interne : Service RH | AJ37: Validation des votes | AK37: Non | AL37: SO | AO37: 0 | AP37: =$AN37*AO37 -> 0 | AQ37: 0 | AR37: =$AN37*AQ37 -> 0 | AT37: =$AN37*AS37 -> 0 | AV37: =$AN37*AU37 -> 0 | AW37: 0 | AX37: =$AN37*AW37 -> 0 | AY37: 0 | AZ37: =$AN37*AY37 -> 0 | BA37: 0 | BB37: =$AN37*BA37 -> 0 | BD37: =$AN37*BC37 -> 0 | BE37: 0 | BF37: =$AN37*BE37 -> 0 | BG37: 0 | BH37: =$AN37*BG37 -> 0 | BI37: =AP37:AP37+AR37:AR37+AT37:AT37+AV37:AV37+AX37:AX37+AZ37:AZ37+BB37:BB37+BD37:BD37+BF37:BF37+BH37:BH37 -> 0 | BJ37: Se référer au document word de préconisation | BK37: 1
B38: 32 | C38: DIME La Bretèche DIME L'espoir DIME Rennes ESAT Les espoirs Résidence du parc des bois Résidence La Combe SAVA Itinéraire Bis | D38: Stagiaires | E38: Gestion des stagiaires salariés (gratifié ou non) | F38: 44277 | G38: 25/06/2024 23/08/2024 26/09/2024 15/07/2025 | H38: séparation des infos spécifique pour la résidence du parc des bois suite revue du trt Ajout de donnée pour le DIME La Bretèche Ajout de l'info pour la Résidence La Combe : pas d'accès à ces données Ajout d'une précision pour le SAVS Mordelles (15/07/25) | I38: Groupe CREATIVE | J38: Directeur de l'organisme | K38: Chef de service | L38: Collecter et utiliser des données permettant d'accueillir des stagiaires (convention, plannings,…) | M38: - gestion du dossier ; - gestion des conventions, documents disciplinaires - réalisation d'états statistiques pour répondre à des besoins de gestion administrative ; - gestion des contacts en cas d'urgence - gestion des absences (congés, maladie, évènements familaiux, …) | N38: stagaires/apprentis | O38: Nom, prénom, date de naissance, n°de tel, adresse mail, matricule, adresse postale | R38: Situation de famille (enfant) Casier judiciaire, volet 3 | S38: Rémunération | T38: Formations, expériences précédentes (CV), RIB, permis de conduire, convention de stage | U38: - données sur les mineurs et conjoint (nom, prénom, date de naissance pour congé paternité, maternité, ). - N° SS : déclaration d'embauche à l'URSAAF, adhésion mutuelle et prévoyance - informations évènements familiaux (mariage, naissance, décès) - contact en cas d'urgence - titre de séjour + validité Casier judiciaire, volet 2 (via l'ARS) | V38: NIR (N° SS) | W38: Données sensibles (Art 9) ou données relatives aux condamnations pénales ou aux infractions (Art 10) | X38: par l'association | Y38: Fondé sur l’exécution d’un contrat avec la personne physique concernée, | Z38: Non | AA38: Bureau RH | AB38: Dossier salarié dans armoire fermant à clé + informatique ( dossier du personnel) | AC38: ALPHA GRH, EXCEL (de moins en moins) Serveur | AD38: Accès réservé au service RH Accès User+mdp sur serveur pour les chefs de service | AE38: Interne | AF38: non défini | AG38: Oui | AH38: Non défini | AI38: Interne : Service RH Directeur Prestataire informatique Chef de service Externe : URSAAF, caisse de retraite, gestionnaire complémentaire santé et prévoyance | AJ38: Gestion des droits d'accès Diffusion des infos aux responsables Transmission des informations obligatoires | AK38: Non | AL38: SO | AM38: Projet Octime à venir pour la planification, phase pilote en novembre pour le SAVS Mordelles Données sensibles au siège Résidence La Combe : pas d'accès à ces données | AN38: 2 | AO38: 0 | AP38: =$AN38*AO38 -> 0 | AQ38: 0 | AR38: =$AN38*AQ38 -> 0 | AS38: 2 | AT38: =$AN38*AS38 -> 4 | AU38: 0 | AV38: =$AN38*AU38 -> 0 | AW38: 0 | AX38: =$AN38*AW38 -> 0 | AY38: 0 | AZ38: =$AN38*AY38 -> 0 | BA38: 0 | BB38: =$AN38*BA38 -> 0 | BC38: 1 | BD38: =$AN38*BC38 -> 2 | BE38: 0 | BF38: =$AN38*BE38 -> 0 | BG38: 0 | BH38: =$AN38*BG38 -> 0 | BI38: =AP38:AP38+AR38:AR38+AT38:AT38+AV38:AV38+AX38:AX38+AZ38:AZ38+BB38:BB38+BD38:BD38+BF38:BF38+BH38:BH38 -> 6 | BJ38: Se référer au document word de préconisation | BK38: 1 | BO38: X
B39: 33 | C39: ESAT LA Simonière | D39: Stagiaires | E39: Gestion des stagiaires professionnels | F39: 44277 | G39: 45562 | H39: Modif du stockage physique et numérique des données | J39: Directeur de l'organisme | K39: Chef de service | L39: Collecter et utiliser des données permettant d'accueillir des stagiaires (convention, plannings,…) | M39: - gestion du dossier ; - gestion des conventions, documents disciplinaires - réalisation d'états statistiques pour répondre à des besoins de gestion administrative ; - gestion des contacts en cas d'urgence - gestion des absences (congés, maladie, évènements familaiux, …) | N39: stagaires/apprentis | O39: Nom, prénom, date de naissance, n°de tel, adresse mail, matricule, adresse postale | R39: Situation de famille (enfant) Casier judiciaire | S39: Rémunération | T39: Formations, expériences précédentes | U39: - données sur les mineurs - N° SS : déclaration d'embauche à l'URSAAF, adhésion mutuelle et prévoyance - contact en cas d'urgence - titre de séjour + validité | V39: NIR (N° SS) | W39: Données sensibles (Art 9) ou données relatives aux condamnations pénales ou aux infractions (Art 10) | X39: par l'association | Y39: Fondé sur l’exécution d’un contrat avec la personne physique concernée, | Z39: Non | AA39: bureau de l'assistante administrative Services RH et Paie au siège | AB39: Convention de stage dans une armoire fermée à clé dans le bureau de l'assistante administrative fermé à clé Bureaux des Services RH et Paie au siège fermés à clé | AC39: Serveur de fichier Logiciel de Paie | AD39: User /Mdp | AE39: Interne Editeur | AF39: Non définie | AG39: Oui | AH39: Non définie | AI39: Interne : Ass Adm, comptable, chef de service, directrice, service de paie Externe : | AJ39: SO | AK39: Non | AL39: SO | AO39: 0 | AP39: =$AN39*AO39 -> 0 | AQ39: 0 | AS39: 2 | AU39: 0 | AW39: 0 | AY39: 0 | BA39: 0 | BC39: 0 | BG39: 0 | BK39: 1 | BO39: X
B40: 34 | C40: Résidences Les Gantelles et Les Fougères | D40: Stagiaires | E40: Gestion des stagiaires professionnels | F40: 45582 | J40: Directeur de l'organisme | K40: Cheffe de service | L40: Collecter et utiliser des données permettant d'accueillir des stagiaires (convention, plannings,…) | M40: - gestion du dossier ; - gestion des conventions, documents disciplinaires - réalisation d'états statistiques pour répondre à des besoins de gestion administrative ; - gestion des contacts en cas d'urgence - gestion des absences (congés, maladie, évènements familaiux, …) | N40: stagaires/apprentis | O40: Nom, prénom, date de naissance, n°de tel, adresse mail, matricule, adresse postale | R40: Situation de famille (enfant) Casier judiciaire | S40: Rémunération | T40: Formations, expériences précédentes | U40: - données sur les mineurs - N° SS : déclaration d'embauche à l'URSAAF, adhésion mutuelle et prévoyance - contact en cas d'urgence - titre de séjour + validité | V40: NIR (N° SS) | W40: Données sensibles (Art 9) ou données relatives aux condamnations pénales ou aux infractions (Art 10) | X40: par l'association | Y40: Fondé sur l’exécution d’un contrat avec la personne physique concernée, | Z40: Non | AA40: Bureau de la direction Bureau du personnel Les Fougères | AB40: Armoire fermée à clé contenant les Convention de stage et le registre des stagiaires dans le bureau de la direction fermé à clé Boite à clés des outils, chaufferie et voitures dans le bureau du personnel Les Fougères fermé à clé | AC40: SO | AD40: SO | AE40: SO | AF40: Non définie | AG40: Non | AH40: Non définie | AI40: Interne : Cheffe de service et AES Externe : | AJ40: SO | AK40: Non | AL40: SO | AN40: 2 | AO40: 0 | AP40: =$AN40*AO40 -> 0 | AQ40: 0 | AR40: =$AN40*AQ40 -> 0 | AS40: 2 | AT40: =$AN40*AS40 -> 4 | AU40: 0 | AV40: =$AN40*AU40 -> 0 | AW40: 0 | AX40: =$AN40*AW40 -> 0 | AY40: 0 | AZ40: =$AN40*AY40 -> 0 | BA40: 0 | BB40: =$AN40*BA40 -> 0 | BC40: 0 | BD40: =$AN40*BC40 -> 0 | BE40: 0 | BF40: =$AN40*BE40 -> 0 | BG40: 0 | BH40: =$AN40*BG40 -> 0 | BI40: =AP40:AP40+AR40:AR40+AT40:AT40+AV40:AV40+AX40:AX40+AZ40:AZ40+BB40:BB40+BD40:BD40+BF40:BF40+BH40:BH40 -> 4 | BK40: 1 | BO40: X
B41: 35 | C41: ESAT LA Simonière | D41: Demandeurs Familles et proches des demandeurs | E41: Gestion des stagiaires travailleurs ESAT | F41: 44277 | I41: Groupe CREATIVE | J41: Directeur de l'organisme | K41: Chefs de service et directeurs | L41: Permettre de découvrir un nouvel environnement de travail | M41: Premier stage pour permettre de découvrir un nouvel environnement de travail Deuxième stage, pour préparer une admission | N41: Demandeur, Familles et partenaires | O41: Nom d’usage Nom de naissance Prénom(s) Date de naissance, N° MSA/CAF, adresse, téléphone, email | R41: Situation familiale Nombre d’enfant(s) Etablissement d'origine, présence d’un aidant, prestation en place (SSIAD, ADMR…) Mesure de protection juridique | S41: Financements, aides, allocation et prestation de compensation | T41: Savoir fondamentaux (lire/écrire/compter) CV Bilans professionnels | U41: NIR Données comportement et handicap | V41: NIR (N° SS) + Concernant le santé | W41: Données sensibles (Art 9) ou données relatives aux condamnations pénales ou aux infractions (Art 10) | X41: Par le demandeur (usager / famille / xxx ) par mail ou courrier | Y41: Fondé sur le consentement préalable de la personne physique, | Z41: Non | AA41: Bureau de la personne chargée d'accompagnement sociale | AB41: Dans un classeur dans une armoire du bureau fermé à clé de la personne chargée d'accompagnement sociale | AC41: Mediateam Serveur de fichier | AD41: User + Mdp | AE41: Berger Levrault Interne | AF41: Mediateam | AG41: Oui | AH41: Mediateam | AI41: Interne :Service social, moniteur, service de paie (MISPE) Externe : MDPH | AJ41: SO | AK41: Non | AL41: SO | AM41: Archives dans le bureau de la resp service sociale pour les stagiaires non admis | AN41: 2 | AO41: 0 | AP41: =$AN41*AO41 -> 0 | AQ41: 0 | AR41: =$AN41*AQ41 -> 0 | AS41: 0 | AT41: =$AN41*AS41 -> 0 | AU41: 0 | AV41: =$AN41*AU41 -> 0 | AW41: 0 | AX41: =$AN41*AW41 -> 0 | AY41: 0 | AZ41: =$AN41*AY41 -> 0 | BA41: 0 | BB41: =$AN41*BA41 -> 0 | BC41: 0 | BD41: =$AN41*BC41 -> 0 | BE41: 0 | BF41: =$AN41*BE41 -> 0 | BG41: 0 | BH41: =$AN41*BG41 -> 0 | BI41: =AP41:AP41+AR41:AR41+AT41:AT41+AV41:AV41+AX41:AX41+AZ41:AZ41+BB41:BB41+BD41:BD41+BF41:BF41+BH41:BH41 -> 0 | BK41: 1 | BO41: X | BR41: X
B42: 36 | C42: Siège | D42: salariés | E42: Formation : OPCO | F42: 44277 | I42: Groupe CREATIVE | J42: Directeur de l'organisme | K42: responsable RH | L42: Intégrer les données du salariés afin d'obtenir les financements de la formation | M42: - Création du dossier - réalisation de statistique | N42: salariés | O42: Nom, prénom, date de naissance, poste, établissement adresse postale, numéro de téléphone, adresse de courriel, nationalité, | S42: Rémunération | T42: Diplôme, poste occupé, catégorie socioprofessionnelle, type de contrat de travail, RQTH, titre, certification professionnelle obtenue, attestation de fin de formation | U42: NIR : obligatoire pour toute demande de prise en charge de formation professionnelle | V42: NIR (N° SS) | W42: Données sensibles (Art 9) ou données relatives aux condamnations pénales ou aux infractions (Art 10) | X42: par l'association | Y42: Fondé sur l’exécution d’un contrat avec la personne physique concernée, | Z42: oui | AA42: OPCO | AB42: Chez le prestaire | AC42: OPCO SANTE | AD42: Accès réservé au service RH | AE42: Terminal de l’OPCO | AF42: 13 mois maximum | AG42: Oui | AH42: 10 ans maximum uniquement pour les opérations de gestion administrative et financière des demandes de formation | AI42: Interne : Service RH Externe : OPCO | AJ42: • Traiter les demandes de prise en charge de formation • Collecter les contributions à la formation professionnelle • Proposer une offre de services aux entreprises relevant de son champ d’intervention • Apporter un appui technique aux branches adhérentes pour établir la GPEC • Assurer le suivi des actions financées et acteurs associés • Assurer la transmission des données de prise en charge au SI de l’Etat notamment AGORA et DECA (DGEFP) • Prendre en compte les demandes d’information • Communiquer à travers des campagnes téléphoniques ou d’e-mailing • Permettre de postuler à des offres d’emploi • Gérer l’adhésion aux différents services fournis par ses plateformes • Assurer la gestion amiable des contentieux engendrés par son activité • Assurer la gestion des instances constitutives d’OPCO Santé • Réaliser des statistiques d’audience afin d’améliorer et proposer une expérience de navigation optimale | AK42: non | AL42: so | AN42: 1 | AO42: 0 | AP42: =$AN42*AO42 -> 0 | AQ42: 0 | AR42: =$AN42*AQ42 -> 0 | AS42: 0 | AT42: =$AN42*AS42 -> 0 | AU42: 0 | AV42: =$AN42*AU42 -> 0 | AW42: 0 | AX42: =$AN42*AW42 -> 0 | AY42: 0 | AZ42: =$AN42*AY42 -> 0 | BA42: 0 | BB42: =$AN42*BA42 -> 0 | BC42: 0 | BD42: =$AN42*BC42 -> 0 | BE42: 0 | BF42: =$AN42*BE42 -> 0 | BG42: 0 | BH42: =$AN42*BG42 -> 0 | BI42: =AP42:AP42+AR42:AR42+AT42:AT42+AV42:AV42+AX42:AX42+AZ42:AZ42+BB42:BB42+BD42:BD42+BF42:BF42+BH42:BH42 -> 0 | BJ42: Se référer au document word de préconisation | BK42: 1 | BO42: X | BR42: X
B43: 37 | C43: Siège | D43: Usagers Familles et proches des usagers Professionnels Sous traitants Membre du CA Elus | E43: Gestion financière | F43: 44277 | G43: 45862 | H43: Modification de l'emplacement des documents | I43: Groupe CREATIVE | J43: Directeur de l'organisme | K43: RAF | L43: Gestion financière | M43: - Facturation des usagers - Reporting financier - Réglements et facturation | N43: Usagers, sous-traitants | O43: Nom, prénom, adresse, tel | P43: Login, IP, Mot de passe possible | S43: RIB | V43: Pas de donnée sensible | W43: Aucun cas retenu | X43: Par l'usager ou sa famille, par les sous-traitants | Y43: Fondé sur l’exécution d’un contrat avec la personne physique concernée, | Z43: Non | AA43: Bureau des comptables | AB43: Factures fournisseurs papier dans le bureau des comptables fermé à clé | AC43: Serveur de fichier | AD43: Accès à revoir pour savoir qui accès (Refonte des serveurs en cours) | AE43: Interne | AF43: Aucune | AG43: Oui | AH43: Illimité | AI43: Interne : RAF et Services Comptabilité Externe : Expert comptable, CAC | AJ43: Bilan comptable | AK43: Non | AL43: so | AM43: Revoir les droits d'accès au répertoire RAF | AO43: 0 | AP43: =$AN43*AO43 -> 0 | AQ43: 0 | AR43: =$AN43*AQ43 -> 0 | AT43: =$AN43*AS43 -> 0 | AV43: =$AN43*AU43 -> 0 | AW43: 0 | AX43: =$AN43*AW43 -> 0 | AY43: 0 | AZ43: =$AN43*AY43 -> 0 | BA43: 0 | BB43: =$AN43*BA43 -> 0 | BD43: =$AN43*BC43 -> 0 | BE43: 0 | BF43: =$AN43*BE43 -> 0 | BG43: 0 | BH43: =$AN43*BG43 -> 0 | BI43: =AP43:AP43+AR43:AR43+AT43:AT43+AV43:AV43+AX43:AX43+AZ43:AZ43+BB43:BB43+BD43:BD43+BF43:BF43+BH43:BH43 -> 0 | BJ43: Se référer au document word de préconisation | BK43: 0
B44: 38 | C44: ESAT LA Simonière | D44: Professionnels & intérimaires | E44: Gestion de la planification | F44: 44277 | G44: 27/09/2024 03/06/2025 | H44: Modif du stockage physique et numérique des données Ajout info Octime | I44: Groupe CREATIVE | J44: Directeur de l'organisme | K44: Chef de service | L44: Collecter et utiliser des données permettant de gérer les équipes (plannings, congés, remplacements, mobilisation en cas de crise ou situation d’urgence…) | N44: Salariés, intérimaires | O44: Nom, prénom | R44: Situation de famille (enfant) | T44: Ancienneté | V44: Pas de donnée sensible | W44: Aucun cas retenu | X44: Par le salarié | Y44: Fondé sur l’exécution d’un contrat avec la personne physique concernée, | Z44: Non | AA44: Couloir de l'ESAT Bureau des moniteurs | AB44: InfoHebdo dans le couloir de l'ESAT (absences et arrivées) Fiche horaire vierge dans une bannette dans le couloir Affichage des plannings dans le couloir et répartition des usagers/monteurs dans le bureau des moniteurs | AC44: Serveur de fichier Mail OCTIME | AD44: Accès User + MDP | AE44: Interne Octime | AF44: Aucune | AG44: Oui | AH44: Illimité | AI44: Interne : tout les salariés et les usagers Externe : | AJ44: SO | AK44: Non | AL44: SO | AM44: Projet en cours avec Octime (pour les travailleurs : quasi déployé, espère l'utiliser avant les congés d'été, Contient des éléments de salaire) | AO44: 0 | AP44: =$AN44*AO44 -> 0 | AQ44: 0 | AR44: =$AN44*AQ44 -> 0 | AS44: 2 | AT44: =$AN44*AS44 -> 0 | AU44: 1 | AV44: =$AN44*AU44 -> 0 | AW44: 0 | AX44: =$AN44*AW44 -> 0 | AY44: 0 | AZ44: =$AN44*AY44 -> 0 | BA44: 0 | BB44: =$AN44*BA44 -> 0 | BC44: 0 | BD44: =$AN44*BC44 -> 0 | BE44: 0 | BF44: =$AN44*BE44 -> 0 | BG44: 0 | BH44: =$AN44*BG44 -> 0 | BI44: =AP44:AP44+AR44:AR44+AT44:AT44+AV44:AV44+AX44:AX44+AZ44:AZ44+BB44:BB44+BD44:BD44+BF44:BF44+BH44:BH44 -> 0 | BJ44: Se référer au document word de préconisation | BK44: 1
B45: 39 | C45: ESAT Les espoirs | D45: Professionnels & intérimaires | E45: Gestion de la planification | F45: 45078 | G45: 45645 | H45: Pas de données sensibles gérées | I45: Groupe CREATIVE | J45: Directeur de l'organisme | K45: Chef de service | L45: Collecter et utiliser des données permettant de gérer les équipes (plannings, congés, remplacements, mobilisation en cas de crise ou situation d’urgence…) | N45: Salariés, intérimaires | O45: Nom, prénom, date de naissance, n° de tel, adresse mail, adresse postale | R45: Situation de famille (enfant) | T45: CV Formations, expériences précédentes | V45: Pas de donnée sensible | W45: Aucun cas retenu | X45: Par le salarié | Y45: Fondé sur l’exécution d’un contrat avec la personne physique concernée, | Z45: Non | AA45: Bureau secrétaire de direction et directeur | AB45: Fermé à clé | AC45: Serveur de fichier | AD45: Accès User + MDP | AE45: Interne | AF45: non défini | AG45: Oui | AH45: Non défini | AI45: Interne : Chefs de service et directeurs Externe : | AJ45: SO | AK45: Non | AL45: SO | AM45: Projet en cours avec Octime | AO45: 0 | AP45: =$AN45*AO45 -> 0 | AQ45: 0 | AR45: =$AN45*AQ45 -> 0 | AS45: 2 | AT45: =$AN45*AS45 -> 0 | AU45: 0 | AV45: =$AN45*AU45 -> 0 | AW45: 0 | AX45: =$AN45*AW45 -> 0 | AY45: 0 | AZ45: =$AN45*AY45 -> 0 | BA45: 0 | BB45: =$AN45*BA45 -> 0 | BC45: 0 | BD45: =$AN45*BC45 -> 0 | BF45: =$AN45*BE45 -> 0 | BG45: 0 | BH45: =$AN45*BG45 -> 0 | BI45: =AP45:AP45+AR45:AR45+AT45:AT45+AV45:AV45+AX45:AX45+AZ45:AZ45+BB45:BB45+BD45:BD45+BF45:BF45+BH45:BH45 -> 0 | BK45: 1
B46: 40 | C46: SAVS Tinténiac | D46: Professionnels & intérimaires | E46: Gestion de la planification | F46: 44277 | G46: 45537 | H46: Plus de données sensibles collectées | I46: Groupe CREATIVE | J46: Directeur de l'organisme | K46: Chef de service | L46: Collecter et utiliser des données permettant de gérer les équipes (plannings, congés, remplacements, mobilisation en cas de crise ou situation d’urgence…) | N46: Salariés, intérimaires | O46: Nom, prénom, date de naissance, n° de tel, adresse mail, adresse postale | V46: Pas de donnée sensible | W46: Aucun cas retenu | X46: Par le salarié | Y46: Fondé sur l’exécution d’un contrat avec la personne physique concernée, | Z46: Non | AA46: Accueil & Bureaux | AB46: Affichage planning à l'accueil et dans les bureaux | AC46: Octime Serveur de fichier | AD46: Accès User + MDP Un dossier par salarié avec accès à tous | AE46: Editeur Interne | AF46: 1 An | AG46: Oui | AH46: 4 ans | AI46: Interne : Secrétaire et chef de service Externe : SO | AJ46: SO | AK46: Non | AL46: SO | AM46: Projet en cours avec Octime (2026) | AN46: 1 | AO46: 0 | AP46: =$AN46*AO46 -> 0 | AQ46: 0 | AR46: =$AN46*AQ46 -> 0 | AS46: 2 | AT46: =$AN46*AS46 -> 2 | AU46: 1 | AV46: =$AN46*AU46 -> 1 | AW46: 0 | AX46: =$AN46*AW46 -> 0 | AY46: 0 | AZ46: =$AN46*AY46 -> 0 | BA46: 0 | BB46: =$AN46*BA46 -> 0 | BC46: 0 | BD46: =$AN46*BC46 -> 0 | BE46: 0 | BF46: =$AN46*BE46 -> 0 | BG46: 0 | BH46: =$AN46*BG46 -> 0 | BI46: =AP46:AP46+AR46:AR46+AT46:AT46+AV46:AV46+AX46:AX46+AZ46:AZ46+BB46:BB46+BD46:BD46+BF46:BF46+BH46:BH46 -> 3 | BJ46: Se référer au document word de préconisation | BK46: 1 | BO46: X
B47: 41 | C47: SAVA Itinéraire Bis | D47: Professionnels & intérimaires | E47: Gestion de la planification | F47: 45077 | G47: 45853 | H47: Ajout de précision sur la partie commentaire (15/07/25) | I47: Groupe CREATIVE | J47: Directeur de l'organisme | K47: Chef de service | L47: Collecter et utiliser des données permettant de gérer les équipes (plannings, congés, remplacements, mobilisation en cas de crise ou situation d’urgence…) | N47: Salariés, intérimaires | O47: Nom, prénom | V47: Pas de donnée sensible | W47: Aucun cas retenu | X47: Par le salarié | Y47: Fondé sur l’exécution d’un contrat avec la personne physique concernée, | Z47: Non | AA47: SO | AB47: SO | AC47: Serveur de fichier, répertoire SAVA | AD47: Accès réservé aux salariés du SAVA | AE47: Interne | AF47: Non | AG47: Non | AH47: SO | AI47: Interne : Salariés Externe : SO | AJ47: SO | AK47: Non | AL47: SO | AM47: Projet en cours avec Octime, phase pilote en novembre | AO47: 0 | AP47: =$AN47*AO47 -> 0 | AQ47: 0 | AR47: =$AN47*AQ47 -> 0 | AT47: =$AN47*AS47 -> 0 | AV47: =$AN47*AU47 -> 0 | AW47: 0 | AX47: =$AN47*AW47 -> 0 | AY47: 0 | AZ47: =$AN47*AY47 -> 0 | BA47: 0 | BB47: =$AN47*BA47 -> 0 | BD47: =$AN47*BC47 -> 0 | BE47: 0 | BF47: =$AN47*BE47 -> 0 | BG47: 0 | BH47: =$AN47*BG47 -> 0 | BI47: =AP47:AP47+AR47:AR47+AT47:AT47+AV47:AV47+AX47:AX47+AZ47:AZ47+BB47:BB47+BD47:BD47+BF47:BF47+BH47:BH47 -> 0 | BJ47: Se référer au document word de préconisation | BK47: 1
B48: 42 | C48: Résidence du parc des bois | D48: Professionnels & intérimaires | E48: Gestion de la planification | F48: 44277 | G48: 25/06/2024 24/06/2025 | H48: Ajout du trt spécifique pour la résidence du parc des bois suite revue du trt Ajout d'un commentaire | I48: Groupe CREATIVE | J48: Directeur de l'organisme | K48: Chef de service | L48: Collecter et utiliser des données permettant de gérer les équipes (plannings, congés, remplacements, mobilisation en cas de crise ou situation d’urgence…) | N48: Salariés, intérimaires | O48: Nom, prénom | R48: Situation de famille (enfant) | T48: Ancienneté | V48: Pas de donnée sensible | W48: Aucun cas retenu | X48: Par le salarié | Y48: Fondé sur l’exécution d’un contrat avec la personne physique concernée, | Z48: Non | AA48: Bureau du responsable | AB48: Dans une armoire du bureau du responsable contenant une copie du casier judiciaire, contrat de travail et entretien pro | AC48: Serveur de fichier | AD48: Accès User + MDP | AE48: Interne | AF48: Aucune | AG48: non | AH48: Aucune | AI48: Interne : tout les salariés Externe : | AJ48: SO | AK48: Non | AL48: SO | AM48: Archivage gérée par le service RH du siège Partie papier en cours d'envoi au siège | AO48: 0 | AP48: =$AN48*AO48 -> 0 | AQ48: 0 | AR48: =$AN48*AQ48 -> 0 | AS48: 0 | AT48: =$AN48*AS48 -> 0 | AU48: 1 | AV48: =$AN48*AU48 -> 0 | AW48: 0 | AX48: =$AN48*AW48 -> 0 | AY48: 0 | AZ48: =$AN48*AY48 -> 0 | BA48: 0 | BB48: =$AN48*BA48 -> 0 | BC48: 0 | BD48: =$AN48*BC48 -> 0 | BE48: 0 | BF48: =$AN48*BE48 -> 0 | BG48: 0 | BH48: =$AN48*BG48 -> 0 | BI48: =AP48:AP48+AR48:AR48+AT48:AT48+AV48:AV48+AX48:AX48+AZ48:AZ48+BB48:BB48+BD48:BD48+BF48:BF48+BH48:BH48 -> 0 | BJ48: Se référer au document word de préconisation | BK48: 1
B49: 43 | C49: DIME La Bretèche DIME L'espoir DIME Rennes Résidence La Combe SAVA Itinéraire Bis | D49: Professionnels & intérimaires | E49: Gestion de la planification | F49: 44277 | G49: 25/06/2024 23/08/2024 26/09/2024 10/07/2025 | H49: séparation des infos spécifique pour la résidence du parc des bois suite revue du trt Ajout de l'emplacement physique au DIME La Bretèche Remarque sur la réception du planning pour la résidence La Combe 2025 - Service Paie - Ajout info SI | I49: Groupe CREATIVE | J49: Directeur de l'organisme | K49: Chef de service | L49: Collecter et utiliser des données permettant de gérer les équipes (plannings, congés, remplacements, mobilisation en cas de crise ou situation d’urgence…) | N49: Salariés, intérimaires | O49: Nom, prénom | R49: Situation de famille (enfant) | T49: Ancienneté | V49: Pas de donnée sensible | W49: Aucun cas retenu | X49: Par le salarié | Y49: Fondé sur l’exécution d’un contrat avec la personne physique concernée, | Z49: Non | AA49: Salle du personnel au DIME La Bretèche | AB49: Horaires affichées en salle du personnel au DIME La Bretèche | AC49: Serveur de fichier Octime | AD49: Accès User + MDP User + Mdp | AE49: Interne Octime | AF49: Non | AG49: Non | AH49: SO | AI49: Interne : tout les salariés Externe : | AJ49: SO | AK49: Non | AL49: SO | AM49: Projet en cours avec Octime, déjà utilisé par le service Paie pour l'alimenter Résidence La Combe : le salarié recoit son planning avce son contrat de travail annuellement. Les modifications sont affichés sur le répertoire S Service du serveur de fichier | AO49: 0 | AP49: =$AN49*AO49 -> 0 | AQ49: 0 | AS49: 0 | AT49: =$AN49*AS49 -> 0 | AU49: 1 | AV49: =$AN49*AU49 -> 0 | AW49: 0 | AY49: 0 | BA49: 0 | BC49: 0 | BD49: =$AN49*BC49 -> 0 | BG49: 0 | BK49: 1
B50: 44 | C50: Résidences Les Gantelles et Les Fougères | D50: Professionnels & intérimaires | E50: Gestion de la planification | F50: 45582 | I50: Groupe CREATIVE | J50: Directeur de l'organisme | K50: Cheffe de service | L50: Collecter et utiliser des données permettant de gérer les équipes (plannings, congés, remplacements, mobilisation en cas de crise ou situation d’urgence…) | N50: Salariés, intérimaires | O50: Nom, prénom | R50: Situation de famille (enfant) | T50: Ancienneté | V50: Pas de donnée sensible | W50: Aucun cas retenu | X50: Par le salarié | Y50: Fondé sur l’exécution d’un contrat avec la personne physique concernée, | Z50: Non | AA50: Bureau du personnel Les Fougères Bureau de service Foyer Les Gantelles Bureau des salariés Foyer Les Gantelles | AB50: Affichage du planning dans le bureau du personnel Les Fougères fermé à clé Affichage du planning dans le bureau de service Foyer Les Gantelles fermé à clé Affichage planning dans le bureau des salariés Foyer Les Gantelles fermés à clé | AC50: SO | AD50: SO | AE50: SO | AF50: Non définie | AG50: Oui | AH50: Non définie | AI50: Interne : tout les salariés Externe : | AJ50: SO | AK50: Non | AL50: SO | AM50: Projet en cours avec Octime | AO50: 0 | AP50: =$AN50*AO50 -> 0 | AQ50: 0 | AR50: =$AN50*AQ50 -> 0 | AT50: =$AN50*AS50 -> 0 | AV50: =$AN50*AU50 -> 0 | AW50: 0 | AX50: =$AN50*AW50 -> 0 | AY50: 0 | AZ50: =$AN50*AY50 -> 0 | BA50: 0 | BB50: =$AN50*BA50 -> 0 | BD50: =$AN50*BC50 -> 0 | BE50: 0 | BF50: =$AN50*BE50 -> 0 | BG50: 0 | BH50: =$AN50*BG50 -> 0 | BI50: =AP50:AP50+AR50:AR50+AT50:AT50+AV50:AV50+AX50:AX50+AZ50:AZ50+BB50:BB50+BD50:BD50+BF50:BF50+BH50:BH50 -> 0 | BJ50: Se référer au document word de préconisation | BK50: 1
B51: 45 | C51: Siège Résidence La Combe SAVA Itinéraire Bis | D51: Professionnels | E51: Gestion des accès clés | F51: 44277 | G51: 04/07/2024 26/09/2024 24/07/2025 | H51: Les clés sont gérés en local sur chaque site et non plus par la cadre en batiment Résidence de La Combe : géré par l'agent de maintenance Ajout commentaire 24/07/25 | I51: Groupe CREATIVE | J51: Directeur de l'organisme | K51: Directeurs des établissements Agents techniques | L51: Permettre à chacun d'accéder aux bureau et zones utiles à son travail | M51: - Gestion des entrées / sorties - Suivi des présents - Gestion des alarmes liées aux accès - Gestion des accès aux zones sécurisées - Journalisation des accès | N51: Externes (clients, visiteurs sous-traitants, candidats, …) Salariés | O51: Nom, Prénom | V51: Pas de donnée sensible | W51: Aucun cas retenu | X51: Par les salariés | Y51: Aux fins des intérêts légitimes poursuivis par le responsable du traitement (C47 -48- 49) | Z51: Non | AA51: Boite à clés au siège Dans chaque établissement de façon autonome Bureau de l'agent de maintenance de la résidence La Combe | AB51: Code d'accès donné à tous les salariés du siège, boite à clé en face de l'assistante de direction Feuille affichée dans un tiroir dans le bureau de l'agent de maintenance de la résidence La Combe fermé à clé | AC51: SO | AD51: SO | AE51: SO | AF51: SO | AG51: Non | AH51: SO | AI51: Interne : Personnes intéressées, Directeurs d'établissement, agents techniques Externe : | AJ51: SO | AK51: Non | AL51: SO | AM51: Gestion des clés en cours au siège suite au déménagement, accès clé au batiment plus un accès par bureau (en cours de mise en place), les RH suivent l'attribution des clés | AO51: 0 | AP51: =$AN51*AO51 -> 0 | AQ51: 0 | AR51: =$AN51*AQ51 -> 0 | AS51: 0 | AT51: =$AN51*AS51 -> 0 | AU51: 0 | AV51: =$AN51*AU51 -> 0 | AW51: 0 | AX51: =$AN51*AW51 -> 0 | AY51: 0 | AZ51: =$AN51*AY51 -> 0 | BA51: 0 | BB51: =$AN51*BA51 -> 0 | BC51: 0 | BD51: =$AN51*BC51 -> 0 | BE51: 0 | BF51: =$AN51*BE51 -> 0 | BG51: 0 | BH51: =$AN51*BG51 -> 0 | BI51: =AP51:AP51+AR51:AR51+AT51:AT51+AV51:AV51+AX51:AX51+AZ51:AZ51+BB51:BB51+BD51:BD51+BF51:BF51+BH51:BH51 -> 0 | BJ51: Se référer au document word de préconisation | BK51: 0
B52: 46 | C52: Résidence du parc des bois | D52: Professionnels | E52: Gestion des accès clés | F52: 44277 | G52: 45468 | H52: Ajout du trt spécifique pour la résidence du parc des bois suite revue du trt | I52: Groupe CREATIVE | J52: Directeur de l'organisme | K52: Responsable cadre bâtiment Agents techniques | L52: Permettre à chacun d'accéder aux bureau et zones utiles à son travail | M52: - Gestion des entrées / sorties - Suivi des présents - Gestion des alarmes liées aux accès - Gestion des accès aux zones sécurisées - Journalisation des accès | N52: Externes (clients, visiteurs sous-traitants, candidats, …) Salariés | O52: Nom, Prénom | V52: Pas de donnée sensible | W52: Aucun cas retenu | X52: Par les salariés | Y52: Aux fins des intérêts légitimes poursuivis par le responsable du traitement (C47 -48- 49) | Z52: Non | AA52: Bureau du directeur | AB52: Organigramme des clés dans le bureau du directeur fermé à clé | AC52: AJP Mediateam | AD52: User + Mdp | AE52: AJP Berger Levrault | AF52: Supprimer au départ du salarié | AG52: Non | AH52: SO | AI52: Interne : Personnes intéressées, copie Responsable cadre Bâtiment Externe : | AJ52: SO | AK52: Non | AL52: SO | AO52: 0 | AP52: =$AN52*AO52 -> 0 | AQ52: 0 | AS52: 0 | AT52: =$AN52*AS52 -> 0 | AU52: 0 | AW52: 0 | AY52: 0 | BA52: 0 | BC52: 0 | BD52: =$AN52*BC52 -> 0 | BG52: 0 | BK52: 0
B53: 47 | C53: Résidences Les Gantelles et Les Fougères | D53: Professionnels/usagers | E53: Gestion des accès clés | F53: 45582 | G53: 45838 | H53: Ajout boite à clés | I53: Groupe CREATIVE | J53: Directeur de l'organisme | K53: Cheffe de service | L53: Permettre à chacun d'accéder aux bureau et zones utiles à son travail ou pour son quotidien | M53: - Gestion des entrées / sorties - Suivi des présents - Gestion des accès aux zones sécurisées | N53: Usagers Salariés | O53: Nom, Prénom | V53: Pas de donnée sensible | W53: Aucun cas retenu | X53: Par les salariés | Y53: Aux fins des intérêts légitimes poursuivis par le responsable du traitement (C47 -48- 49) | Z53: Non | AA53: Bureau de la direction Bureau du personnel Les Fougères | AB53: Armoire à clés des résidences et double des casiers des salariés du bureau de la direction fermé à clé Armoire à clés des outils, chaufferie et voitures dans le bureau du personnel Les Fougères fermé à clé Boite à clés dans le couloir des Gantelles - clés de secours | AC53: SO | AD53: SO | AE53: SO | AF53: Non définie | AG53: Non | AH53: SO | AI53: Interne : Cheffe de service Externe : | AJ53: SO | AK53: Non | AL53: SO | AM53: Médaillon donné aux résidents pour ouvrir depuis l'intérieur de la structure leur porte de logement ou de l'établissement | AO53: 0 | AP53: =$AN53*AO53 -> 0 | AQ53: 0 | AR53: =$AN53*AQ53 -> 0 | AT53: =$AN53*AS53 -> 0 | AV53: =$AN53*AU53 -> 0 | AW53: 0 | AX53: =$AN53*AW53 -> 0 | AY53: 0 | AZ53: =$AN53*AY53 -> 0 | BA53: 0 | BB53: =$AN53*BA53 -> 0 | BD53: =$AN53*BC53 -> 0 | BE53: 0 | BF53: =$AN53*BE53 -> 0 | BG53: 0 | BH53: =$AN53*BG53 -> 0 | BI53: =AP53:AP53+AR53:AR53+AT53:AT53+AV53:AV53+AX53:AX53+AZ53:AZ53+BB53:BB53+BD53:BD53+BF53:BF53+BH53:BH53 -> 0 | BJ53: Se référer au document word de préconisation | BK53: 0
B54: 48 | C54: SAVS Tinténiac | D54: Professionnels | E54: Gestion des accès clés | F54: 45090 | G54: 02/09/2024 28/07/2025 | H54: Fichier de suivi mis en place en 2024 Chgt emplacement physique et commentaire - 28/07/25 | I54: Groupe CREATIVE | J54: Directeur de l'organisme | K54: Agent technique | L54: Permettre à chacun d'accéder aux bureau et zones utiles à son travail | M54: - Gestion des entrées / sorties - Suivi des présents - Gestion des alarmes liées aux accès - Gestion des accès aux zones sécurisées - Journalisation des accès | N54: Externes (clients, visiteurs sous-traitants, candidats, …) Salariés | O54: Nom, Prénom | P54: numéro de clé | V54: Pas de donnée sensible | W54: Aucun cas retenu | X54: Salariés | Y54: Aux fins des intérêts légitimes poursuivis par le responsable du traitement (C47 -48- 49) | Z54: non | AA54: Bureau de l'agent d'entretien (Résidence La Combe) | AB54: Maison est fermée à clé, listing des détenteurs des clés | AC54: Serveur | AD54: User / Mdp | AE54: SO | AF54: SO | AG54: SO | AH54: SO | AI54: Interne : Cheffe de service, homme d'entretien Externe : | AJ54: SO | AK54: Non | AL54: SO | AM54: Fichier mis en place en 2024, sera que Qualiéno après la formation prévue en septembre | AO54: 0 | AP54: =$AN54*AO54 -> 0 | AQ54: 0 | AR54: =$AN54*AQ54 -> 0 | AS54: 0 | AT54: =$AN54*AS54 -> 0 | AU54: 0 | AV54: =$AN54*AU54 -> 0 | AW54: 0 | AX54: =$AN54*AW54 -> 0 | AY54: 0 | AZ54: =$AN54*AY54 -> 0 | BA54: 0 | BB54: =$AN54*BA54 -> 0 | BC54: 0 | BD54: =$AN54*BC54 -> 0 | BE54: 0 | BF54: =$AN54*BE54 -> 0 | BG54: 0 | BH54: =$AN54*BG54 -> 0 | BI54: =AP54:AP54+AR54:AR54+AT54:AT54+AV54:AV54+AX54:AX54+AZ54:AZ54+BB54:BB54+BD54:BD54+BF54:BF54+BH54:BH54 -> 0 | BJ54: Se référer au document word de préconisation | BK54: 0
B55: 49 | C55: SAVA Itinéraire Bis | D55: Professionnels | E55: Gestion des accès clés | F55: 45077 | G55: 25/06/2024 15/07/2025 | H55: Modif du commentaure car futur projet de gestion des clés Ajout de précision sur la partie commentaire (15/07/25) | I55: Groupe CREATIVE | J55: Directeur de l'organisme | K55: Directrice | L55: Permettre à chacun d'accéder aux bureau et zones utiles à son travail | M55: Gestion des entrées / sorties | N55: Externes (clients, visiteurs sous-traitants, candidats, …) Salariés | O55: Nom, Prénom | P55: numéro de clé | T55: Nom de l'entreprise | V55: Pas de donnée sensible | W55: Aucun cas retenu | X55: Salariés | Y55: Aux fins des intérêts légitimes poursuivis par le responsable du traitement (C47 -48- 49) | Z55: non | AA55: SO | AB55: SO | AC55: SO | AD55: SO | AE55: SO | AF55: SO | AG55: SO | AH55: SO | AI55: Interne : Externe : | AJ55: SO | AK55: Non | AL55: SO | AM55: Chacun à une clé, géré par la cheffe de service Mise en place d'une attestation de remise de matériel à faire signer puis déposée dans Qualinéo | AO55: 0 | AP55: =$AN55*AO55 -> 0 | AQ55: 0 | AR55: =$AN55*AQ55 -> 0 | AS55: 0 | AT55: =$AN55*AS55 -> 0 | AU55: 0 | AV55: =$AN55*AU55 -> 0 | AW55: 0 | AX55: =$AN55*AW55 -> 0 | AY55: 0 | AZ55: =$AN55*AY55 -> 0 | BA55: 0 | BB55: =$AN55*BA55 -> 0 | BC55: 0 | BD55: =$AN55*BC55 -> 0 | BE55: 0 | BF55: =$AN55*BE55 -> 0 | BG55: 0 | BH55: =$AN55*BG55 -> 0 | BI55: =AP55:AP55+AR55:AR55+AT55:AT55+AV55:AV55+AX55:AX55+AZ55:AZ55+BB55:BB55+BD55:BD55+BF55:BF55+BH55:BH55 -> 0 | BJ55: Se référer au document word de préconisation | BK55: 0
B56: 50 | C56: DIME Rennes | D56: Professionnels | E56: Gestion des accès clés / badges / Digicodes | F56: 44277 | G56: 45855 | H56: Modification de l'emplacement physique et numérique | I56: Groupe CREATIVE | J56: Directeur de l'organisme | K56: Agent technique | L56: Permettre à chacun d'accéder aux bureau et zones utiles à son travail | M56: - Gestion des entrées / sorties - Suivi des présents - Gestion des alarmes liées aux accès - Gestion des accès aux zones sécurisées - Journalisation des accès | N56: Externes (clients, visiteurs sous-traitants, candidats, …) Salariés | O56: Nom, Prénom, numéro de badge | P56: numéro de badge | T56: Nom de l'entreprise | U56: Journalisation d'évènements (données traitées uniquement en cas de besoin sécurité) | V56: Pas de donnée sensible | W56: Aucun cas retenu | X56: Lecteurs de badges | Y56: Aux fins des intérêts légitimes poursuivis par le responsable du traitement (C47 -48- 49) | Z56: non | AA56: Bureau de l'agent technique IME Serveur administratif | AB56: Affichage des organigrammes papier des clés dans le bureau de l'agent technique IME fermé à clé Boite à clé des doubles près du serveur administratif fermé à clé | AC56: IPEVIA (Badge) | AD56: Assistante de direction : User/mdp | AE56: Castel | AF56: Non | AG56: Oui | AH56: Illimité | AI56: Interne : Agent technique, secrétaire de direction IME Externe : | AJ56: SO | AK56: Non | AL56: SO | AM56: La secrétaire de direction crée une lettre de décharge | AO56: 0 | AP56: =$AN56*AO56 -> 0 | AQ56: 0 | AR56: =$AN56*AQ56 -> 0 | AT56: =$AN56*AS56 -> 0 | AV56: =$AN56*AU56 -> 0 | AW56: 0 | AX56: =$AN56*AW56 -> 0 | AY56: 0 | AZ56: =$AN56*AY56 -> 0 | BA56: 0 | BB56: =$AN56*BA56 -> 0 | BD56: =$AN56*BC56 -> 0 | BE56: 0 | BF56: =$AN56*BE56 -> 0 | BG56: 0 | BH56: =$AN56*BG56 -> 0 | BI56: =AP56:AP56+AR56:AR56+AT56:AT56+AV56:AV56+AX56:AX56+AZ56:AZ56+BB56:BB56+BD56:BD56+BF56:BF56+BH56:BH56 -> 0 | BJ56: Se référer au document word de préconisation | BK56: 0
B57: 51 | C57: DIME La Bretèche | D57: Professionnels | E57: Gestion des accès clés | F57: 44277 | G57: 23/08/2024 18/07/2025 | H57: Modification de l'emplacement physique et de la durée de conservation 18/07/2025 - Ajout emplacement boitte à clés | I57: Groupe CREATIVE | J57: Directeur de l'organisme | K57: Agent technique | L57: Permettre à chacun d'accéder aux bureau et zones utiles à son travail | M57: - Gestion des entrées / sorties - Suivi des présents - Gestion des alarmes liées aux accès - Gestion des accès aux zones sécurisées - Journalisation des accès | N57: Externes (clients, visiteurs sous-traitants, candidats, …) Salariés | O57: Nom, Prénom | T57: Nom de l'entreprise | U57: Journalisation d'évènements (données traitées uniquement en cas de besoin sécurité) | V57: Pas de donnée sensible | W57: Aucun cas retenu | X57: Lecteurs de badges | Y57: Aux fins des intérêts légitimes poursuivis par le responsable du traitement (C47 -48- 49) | Z57: non | AA57: Maison Patton Extérieur de l'internat Infirmerie Secrétariat | AB57: Attestation de remise des clés stockée au secrétariat du DIME La Bretèche Boite à clés : Maison Patton à Rennes à l'extérieur de l'internat, à l'infirmerie et au secrétariat | AC57: SO | AD57: SO | AE57: SO | AF57: Stockage au secrétariat dans une armoire | AG57: Non | AI57: Interne : DIME La Bretèche Externe : | AJ57: SO | AK57: Non | AL57: SO | AO57: 0 | AP57: =$AN57*AO57 -> 0 | AQ57: 0 | AR57: =$AN57*AQ57 -> 0 | AS57: 0 | AT57: =$AN57*AS57 -> 0 | AU57: 0 | AV57: =$AN57*AU57 -> 0 | AW57: 0 | AX57: =$AN57*AW57 -> 0 | AY57: 0 | AZ57: =$AN57*AY57 -> 0 | BA57: 0 | BB57: =$AN57*BA57 -> 0 | BC57: 0 | BD57: =$AN57*BC57 -> 0 | BE57: 0 | BF57: =$AN57*BE57 -> 0 | BG57: 0 | BH57: =$AN57*BG57 -> 0 | BI57: =AP57:AP57+AR57:AR57+AT57:AT57+AV57:AV57+AX57:AX57+AZ57:AZ57+BB57:BB57+BD57:BD57+BF57:BF57+BH57:BH57 -> 0 | BJ57: Se référer au document word de préconisation | BK57: 0
B58: 52 | C58: ESAT LA Simonière | D58: Professionnels | E58: Gestion des accès clés / badges (portail) / Digicodes (portail et alarme) | F58: 44277 | G58: 45562 | H58: Modif du stockage physique et numérique des données | I58: Groupe CREATIVE | J58: Directeur de l'organisme | K58: Directrice | L58: Permettre à chacun d'accéder aux bureau et zones utiles à son travail | M58: - Gestion des entrées / sorties - Suivi des présents - Gestion des alarmes liées aux accès - Gestion des accès aux zones sécurisées - Journalisation des accès | N58: Salariés | O58: Nom, Prénom | P58: Code de digicodes | V58: Pas de donnée sensible | W58: Aucun cas retenu | X58: Lecteurs de badges | Y58: Aux fins des intérêts légitimes poursuivis par le responsable du traitement (C47 -48- 49) | Z58: non | AA58: Bureau de la directrice Accueil | AB58: Carnet de suivi, double des clés dans le bureau de la directrice Double des clés des vestiaires des travailleurs dans un local à l'accueil fermé à clé | AC58: SO | AD58: SO | AE58: SO | AF58: Aucune | AG58: Oui | AH58: Illimité | AI58: Interne : les salariés Externe : | AJ58: SO | AK58: Non | AL58: SO | AO58: 0 | AP58: =$AN58*AO58 -> 0 | AQ58: 0 | AR58: =$AN58*AQ58 -> 0 | AS58: 3 | AT58: =$AN58*AS58 -> 0 | AU58: 0 | AV58: =$AN58*AU58 -> 0 | AW58: 0 | AX58: =$AN58*AW58 -> 0 | AY58: 0 | AZ58: =$AN58*AY58 -> 0 | BA58: 0 | BB58: =$AN58*BA58 -> 0 | BC58: 0 | BD58: =$AN58*BC58 -> 0 | BE58: 0 | BF58: =$AN58*BE58 -> 0 | BG58: 0 | BH58: =$AN58*BG58 -> 0 | BI58: =AP58:AP58+AR58:AR58+AT58:AT58+AV58:AV58+AX58:AX58+AZ58:AZ58+BB58:BB58+BD58:BD58+BF58:BF58+BH58:BH58 -> 0 | BK58: 0
B59: 53 | C59: ESAT Les espoirs | D59: Professionnels | E59: Gestion des accès clés | F59: 45078 | I59: Groupe CREATIVE | J59: Directeur de l'organisme | K59: Agent technique | L59: Permettre à chacun d'accéder aux bureau et zones utiles à son travail | M59: - Gestion des entrées / sorties - Suivi des présents - Gestion des alarmes liées aux accès - Gestion des accès aux zones sécurisées - Journalisation des accès | N59: Externes (clients, visiteurs sous-traitants, candidats, …) Salariés | O59: Nom, Prénom | V59: Pas de donnée sensible | W59: Aucun cas retenu | X59: Salariés | Y59: Aux fins des intérêts légitimes poursuivis par le responsable du traitement (C47 -48- 49) | Z59: non | AA59: Bureau de l'agent de maintenance | AB59: Fermé à clé | AC59: Serveur de fichier | AD59: Répertoire de l'agent de maintenance | AE59: Interne | AF59: non défini | AG59: Oui | AH59: Non défini | AI59: Interne : les salariés Externe : | AJ59: SO | AK59: Non | AL59: SO | AO59: 0 | AP59: =$AN59*AO59 -> 0 | AQ59: 0 | AR59: =$AN59*AQ59 -> 0 | AT59: =$AN59*AS59 -> 0 | AV59: =$AN59*AU59 -> 0 | AW59: 0 | AX59: =$AN59*AW59 -> 0 | AY59: 0 | AZ59: =$AN59*AY59 -> 0 | BA59: 0 | BB59: =$AN59*BA59 -> 0 | BD59: =$AN59*BC59 -> 0 | BF59: =$AN59*BE59 -> 0 | BG59: 0 | BH59: =$AN59*BG59 -> 0 | BI59: =AP59:AP59+AR59:AR59+AT59:AT59+AV59:AV59+AX59:AX59+AZ59:AZ59+BB59:BB59+BD59:BD59+BF59:BF59+BH59:BH59 -> 0 | BK59: 0
B60: 54 | C60: DIME Rennes | D60: Professionnels, usagers Familles et proches des usagers | E60: Gestion des évènements indésirables | F60: 44277 | G60: 45855 | H60: Modification de l'emplacement physique et numérique | I60: Groupe CREATIVE | J60: Directeur de l'organisme | K60: Chef de service | L60: Gestion des évènements indésirables survenues au sein de l'organisme | M60: - Assurer la remontée des informations aux instances et autorités compétentes concernant des dysfonctionnements graves ou évènements pouvant compromettre la santé, la sécurité ou le bien-être des usagers - Etablir des statistiques - Evaluer la qualité des activités et prestations et les améliorer si besoin - Identification de besoins à couvrir - Garantir le respect des droits des personnes accompagnées - Garantir la protection des biens et des personnes | N60: Toute personne | O60: Nom, prénom | R60: Toute donnée selon la situation | S60: Toute donnée selon la situation | T60: Toute donnée selon la situation | V60: Toute donnée selon la situation | W60: Données sensibles (Art 9) ou données relatives aux condamnations pénales ou aux infractions (Art 10) | X60: Toute personne témoin de l'évènement | Y60: Fondé sur une obligation légale à laquelle le responsable du traitement est soumis | Z60: non | AA60: Bureau de la secrétaire de direction de l'IME | AB60: IME : Cahier de tracabilité des plaintes et réclamations, remplacé par Qualinéo | AC60: Qualinéo | AD60: User/mdp | AE60: Qualinéo | AF60: non défini | AG60: Oui | AH60: Non défini | AI60: Interne : Personnes utiles suivant la situation Externe : | AJ60: SO | AK60: Non | AL60: SO | AN60: 3 | AO60: 0 | AP60: =$AN60*AO60 -> 0 | AQ60: 0 | AR60: =$AN60*AQ60 -> 0 | AS60: 3 | AT60: =$AN60*AS60 -> 9 | AU60: 1 | AV60: =$AN60*AU60 -> 3 | AW60: 0 | AX60: =$AN60*AW60 -> 0 | AY60: 0 | AZ60: =$AN60*AY60 -> 0 | BA60: 0 | BB60: =$AN60*BA60 -> 0 | BC60: 0 | BD60: =$AN60*BC60 -> 0 | BE60: 0 | BF60: =$AN60*BE60 -> 0 | BG60: 0 | BH60: =$AN60*BG60 -> 0 | BI60: =AP60:AP60+AR60:AR60+AT60:AT60+AV60:AV60+AX60:AX60+AZ60:AZ60+BB60:BB60+BD60:BD60+BF60:BF60+BH60:BH60 -> 12 | BJ60: Se référer au document word de préconisation | BK60: 2 | BO60: X | BR60: X
B61: 55 | C61: DIME La Bretèche | D61: Professionnels, usagers Familles et proches des usagers | E61: Gestion des évènements indésirables | F61: 44277 | G61: 23/08/2024 18/07/2025 | H61: Précision en commentaire pour les évènements concernant un salarié 18/07/2025 ajout de Qualinéo | I61: Groupe CREATIVE | J61: Directeur de l'organisme | K61: Chef de service | L61: Gestion des évènements indésirables survenues au sein de l'organisme | M61: - Assurer la remontée des informations aux instances et autorités compétentes concernant des dysfonctionnements graves ou évènements pouvant compromettre la santé, la sécurité ou le bien-être des usagers - Etablir des statistiques - Evaluer la qualité des activités et prestations et les améliorer si besoin - Identification de besoins à couvrir - Garantir le respect des droits des personnes accompagnées - Garantir la protection des biens et des personnes | N61: Toute personne | O61: Nom, prénom | R61: Toute donnée selon la situation | S61: Toute donnée selon la situation | T61: Toute donnée selon la situation | V61: Toute donnée selon la situation | W61: Données sensibles (Art 9) ou données relatives aux condamnations pénales ou aux infractions (Art 10) | X61: Toute personne témoin de l'évènement | Y61: Fondé sur une obligation légale à laquelle le responsable du traitement est soumis | Z61: non | AA61: Secrétariat | AB61: Classeur dans une armoire fermée à clé | AC61: Serveur One Drive Qualinéo | AD61: User + MDP | AE61: Interne Qualinéo | AF61: Non | AG61: Oui | AH61: Illimité | AI61: Interne : Personnes utiles suivant la situation Externe : ARS (CORSSI), informations préoccupantes, signalements au procureur | AJ61: SO | AK61: Non | AL61: SO | AM61: Les fiches concernant un personnel sont différentiées des autres fiches, stockées dans un autre classeur et dossier numérique (non accessible à tous) Qualinéo depuis juillet - pas de reprise des stocks | AN61: 3 | AO61: 0 | AP61: =$AN61*AO61 -> 0 | AQ61: 0 | AR61: =$AN61*AQ61 -> 0 | AS61: 3 | AT61: =$AN61*AS61 -> 9 | AU61: 0 | AV61: =$AN61*AU61 -> 0 | AW61: 0 | AX61: =$AN61*AW61 -> 0 | AY61: 0 | AZ61: =$AN61*AY61 -> 0 | BA61: 0 | BB61: =$AN61*BA61 -> 0 | BC61: 1 | BD61: =$AN61*BC61 -> 3 | BE61: 0 | BF61: =$AN61*BE61 -> 0 | BG61: 0 | BH61: =$AN61*BG61 -> 0 | BI61: =AP61:AP61+AR61:AR61+AT61:AT61+AV61:AV61+AX61:AX61+AZ61:AZ61+BB61:BB61+BD61:BD61+BF61:BF61+BH61:BH61 -> 12 | BK61: 2 | BO61: X | BR61: X
B62: 56 | C62: SAVS Tinténiac | D62: Professionnels, usagers Familles et proches des usagers | E62: Gestion des évènements indésirables | F62: 45090 | G62: 02/09/2024 28/07/2025 | H62: Mise en place de l'outil Qualinéo en 2025 Modif lié à Qualinéo - 28/07/25 | I62: Groupe CREATIVE | J62: Directeur de l'organisme | K62: Chef de service | L62: Gestion des évènements indésirables survenues au sein de l'organisme | M62: - Assurer la remontée des informations aux instances et autorités compétentes concernant des dysfonctionnements graves ou évènements pouvant compromettre la santé, la sécurité ou le bien-être des usagers - Etablir des statistiques - Evaluer la qualité des activités et prestations et les améliorer si besoin - Identification de besoins à couvrir - Garantir le respect des droits des personnes accompagnées - Garantir la protection des biens et des personnes | N62: Toute personne | O62: Nom, prénom | R62: Toute donnée selon la situation | S62: Toute donnée selon la situation | T62: Toute donnée selon la situation | V62: Toute donnée selon la situation | W62: Données sensibles (Art 9) ou données relatives aux condamnations pénales ou aux infractions (Art 10) | X62: Toute personne témoin de l'évènement | Y62: Fondé sur une obligation légale à laquelle le responsable du traitement est soumis | Z62: non | AA62: SO | AB62: SO | AC62: Qualinéo | AD62: User / Mdp | AE62: Qualinéo | AF62: Qualinéo | AG62: Oui | AH62: Qualinéo | AI62: Interne : Personnes utiles suivant la situation Externe : | AJ62: SO | AK62: Non | AL62: SO | AN62: 3 | AO62: 0 | AP62: =$AN62*AO62 -> 0 | AQ62: 0 | AR62: =$AN62*AQ62 -> 0 | AS62: 0 | AT62: =$AN62*AS62 -> 0 | AU62: 0 | AV62: =$AN62*AU62 -> 0 | AW62: 0 | AX62: =$AN62*AW62 -> 0 | AY62: 0 | AZ62: =$AN62*AY62 -> 0 | BA62: 0 | BB62: =$AN62*BA62 -> 0 | BC62: 1 | BD62: =$AN62*BC62 -> 3 | BE62: 0 | BF62: =$AN62*BE62 -> 0 | BG62: 0 | BH62: =$AN62*BG62 -> 0 | BI62: =AP62:AP62+AR62:AR62+AT62:AT62+AV62:AV62+AX62:AX62+AZ62:AZ62+BB62:BB62+BD62:BD62+BF62:BF62+BH62:BH62 -> 3 | BK62: 2 | BO62: X | BR62: X
B63: 57 | C63: SAVA Itinéraire Bis | D63: Professionnels, usagers Familles et proches des usagers | E63: Gestion des évènements indésirables | F63: 45077 | G63: 45853 | H63: Ajout de précision sur la partie emplacement numérique (15/07/25) | I63: Groupe CREATIVE | J63: Directeur de l'organisme | K63: Chef de service | L63: Gestion des évènements indésirables survenues au sein de l'organisme | M63: - Assurer la remontée des informations aux instances et autorités compétentes concernant des dysfonctionnements graves ou évènements pouvant compromettre la santé, la sécurité ou le bien-être des usagers - Etablir des statistiques - Evaluer la qualité des activités et prestations et les améliorer si besoin - Identification de besoins à couvrir - Garantir le respect des droits des personnes accompagnées - Garantir la protection des biens et des personnes | N63: Toute personne | O63: Nom, prénom | R63: Toute donnée selon la situation | S63: Toute donnée selon la situation | T63: Toute donnée selon la situation | V63: Toute donnée selon la situation | W63: Données sensibles (Art 9) ou données relatives aux condamnations pénales ou aux infractions (Art 10) | X63: Toute personne témoin de l'évènement | Y63: Fondé sur une obligation légale à laquelle le responsable du traitement est soumis | Z63: non | AA63: SO | AB63: SO | AC63: Mediateam Qualinéo | AD63: User / Mdp | AE63: Berger Levrault Qualinéo | AF63: Mediateam | AG63: Oui | AH63: Mediateam | AI63: Interne : Personnel concerné Externe : ARS et/ou CD35 | AJ63: SO | AK63: Non | AL63: SO | AM63: Mediateam seulement pour les évènements concernant les usagers, pas les salariés, ni les structures | AN63: 3 | AO63: 0 | AP63: =$AN63*AO63 -> 0 | AQ63: 0 | AR63: =$AN63*AQ63 -> 0 | AS63: 0 | AT63: =$AN63*AS63 -> 0 | AU63: 0 | AV63: =$AN63*AU63 -> 0 | AW63: 0 | AX63: =$AN63*AW63 -> 0 | AY63: 0 | AZ63: =$AN63*AY63 -> 0 | BA63: 0 | BB63: =$AN63*BA63 -> 0 | BC63: 0 | BD63: =$AN63*BC63 -> 0 | BE63: 0 | BF63: =$AN63*BE63 -> 0 | BG63: 0 | BH63: =$AN63*BG63 -> 0 | BI63: =AP63:AP63+AR63:AR63+AT63:AT63+AV63:AV63+AX63:AX63+AZ63:AZ63+BB63:BB63+BD63:BD63+BF63:BF63+BH63:BH63 -> 0 | BK63: 2 | BO63: X | BR63: X
B64: 58 | C64: ESAT LA Simonière | D64: Professionnels, usagers Familles et proches des usagers | E64: Gestion des évènements indésirables | F64: 44277 | G64: 27/09/2024 03/06/2025 | H64: Modif du stockage physique et numérique des données Ajout info Octime | I64: Groupe CREATIVE | J64: Directeur de l'organisme | K64: directeur et chefs de service | L64: Gestion des évènements indésirables survenues au sein de l'organisme | M64: - Assurer la remontée des informations aux instances et autorités compétentes concernant des dysfonctionnements graves ou évènements pouvant compromettre la santé, la sécurité ou le bien-être des usagers - Etablir des statistiques - Evaluer la qualité des activités et prestations et les améliorer si besoin - Identification de besoins à couvrir - Garantir le respect des droits des personnes accompagnées - Garantir la protection des biens et des personnes | N64: Toute personne | O64: Nom, prénom | R64: Toute donnée selon la situation | S64: Toute donnée selon la situation | T64: Toute donnée selon la situation | V64: Toute donnée selon la situation | W64: Données sensibles (Art 9) ou données relatives aux condamnations pénales ou aux infractions (Art 10) | X64: Toute personne témoin de l'évènement | Y64: Fondé sur une obligation légale à laquelle le responsable du traitement est soumis | Z64: non | AA64: Bureau de l'assistante administrative Accueil | AB64: Document papier archivé dans le dossier des usagers, bureau de l'assistante adlinistrative fermé à clé Cahier des plaintes et des réclmations auprès de l'assistate commerciale à l'accueil fermée à clé | AC64: Serveur Mediateam | AD64: User / Mdp | AE64: Interne Berger Levrault | AF64: Aucune | AG64: Oui | AH64: Illimité | AI64: Interne : Personnes utiles suivant la situation Externe : | AJ64: SO | AK64: Non | AL64: SO | AM64: Avec QUALINEO, procédure faite mais pas mise en place suite arrivée du new dir de l'autre ESAT (ESTA La Simmonière : seul établissement n'ont encore totalement déployé, prévu pour cet été, gestion des Evènements indésirables, Incident technique et Procédure qualité) Procédure | AN64: 3 | AO64: 0 | AP64: =$AN64*AO64 -> 0 | AQ64: 0 | AR64: =$AN64*AQ64 -> 0 | AS64: 3 | AT64: =$AN64*AS64 -> 9 | AU64: 3 | AV64: =$AN64*AU64 -> 9 | AW64: 0 | AX64: =$AN64*AW64 -> 0 | AY64: 0 | AZ64: =$AN64*AY64 -> 0 | BA64: 0 | BB64: =$AN64*BA64 -> 0 | BC64: 1 | BD64: =$AN64*BC64 -> 3 | BE64: 0 | BF64: =$AN64*BE64 -> 0 | BG64: 0 | BH64: =$AN64*BG64 -> 0 | BI64: =AP64:AP64+AR64:AR64+AT64:AT64+AV64:AV64+AX64:AX64+AZ64:AZ64+BB64:BB64+BD64:BD64+BF64:BF64+BH64:BH64 -> 21 | BK64: 2 | BO64: X | BR64: X
B65: 59 | C65: ESAT Les espoirs | D65: Professionnels, usagers Familles et proches des usagers | E65: Gestion des évènements indésirables | F65: 45078 | G65: 45645 | H65: Ajout d'un commentaire | I65: Groupe CREATIVE | J65: Directeur de l'organisme | K65: Chef de service | L65: Gestion des évènements indésirables survenues au sein de l'organisme | M65: - Assurer la remontée des informations aux instances et autorités compétentes concernant des dysfonctionnements graves ou évènements pouvant compromettre la santé, la sécurité ou le bien-être des usagers - Etablir des statistiques - Evaluer la qualité des activités et prestations et les améliorer si besoin - Identification de besoins à couvrir - Garantir le respect des droits des personnes accompagnées - Garantir la protection des biens et des personnes | N65: Toute personne | O65: Nom, prénom | R65: Toute donnée selon la situation | S65: Toute donnée selon la situation | T65: Toute donnée selon la situation | V65: Toute donnée selon la situation | W65: Données sensibles (Art 9) ou données relatives aux condamnations pénales ou aux infractions (Art 10) | X65: Toute personne témoin de l'évènement | Y65: Fondé sur une obligation légale à laquelle le responsable du traitement est soumis | Z65: non | AA65: Bureau du directeur | AB65: Fermé à clé | AC65: Serveur de fichier | AD65: Accessible que par la direction | AE65: Interne | AF65: non défini | AG65: Oui | AH65: Non défini | AI65: Interne : Personnes concernées Externe : Personnes concernées | AJ65: Personnes concernées par l'évènement indésirable | AK65: Non | AL65: SO | AM65: Projet de mise ne place du logiciel Qualinéo en cours | AN65: 3 | AO65: 0 | AP65: =$AN65*AO65 -> 0 | AQ65: 0 | AR65: =$AN65*AQ65 -> 0 | AS65: 2 | AT65: =$AN65*AS65 -> 6 | AU65: 0 | AV65: =$AN65*AU65 -> 0 | AW65: 0 | AX65: =$AN65*AW65 -> 0 | AY65: 0 | AZ65: =$AN65*AY65 -> 0 | BA65: 0 | BB65: =$AN65*BA65 -> 0 | BC65: 1 | BD65: =$AN65*BC65 -> 3 | BE65: 0 | BF65: =$AN65*BE65 -> 0 | BG65: 0 | BH65: =$AN65*BG65 -> 0 | BI65: =AP65:AP65+AR65:AR65+AT65:AT65+AV65:AV65+AX65:AX65+AZ65:AZ65+BB65:BB65+BD65:BD65+BF65:BF65+BH65:BH65 -> 9 | BK65: 2 | BO65: X | BR65: X
B66: 60 | C66: Résidence du parc des bois Résidences Les Gantelles et Les Fougères SAVA Itinéraire Bis | D66: Professionnels, usagers Familles et proches des usagers | E66: Gestion des évènements indésirables | F66: 44277 | G66: 20/06/2024 24/06/2025 | H66: Changement de gestionnaire Mise en place de Qualinéo | I66: Groupe CREATIVE | J66: Directeur de l'organisme | K66: Responsable qualité | L66: Gestion des évènements indésirables survenues au sein de l'organisme | M66: - Assurer la remontée des informations aux instances et autorités compétentes concernant des dysfonctionnements graves ou évènements pouvant compromettre la santé, la sécurité ou le bien-être des usagers - Etablir des statistiques - Evaluer la qualité des activités et prestations et les améliorer si besoin - Identification de besoins à couvrir - Garantir le respect des droits des personnes accompagnées - Garantir la protection des biens et des personnes | N66: Toute personne | O66: Nom, prénom | R66: Toute donnée selon la situation | S66: Toute donnée selon la situation | T66: Toute donnée selon la situation | V66: Toute donnée selon la situation | W66: Données sensibles (Art 9) ou données relatives aux condamnations pénales ou aux infractions (Art 10) | X66: Toute personne témoin de l'évènement | Y66: Fondé sur une obligation légale à laquelle le responsable du traitement est soumis | Z66: non | AA66: SO | AB66: SO | AC66: Qualinéo | AD66: User + MDP (lié au compte réseau) | AE66: Interne | AF66: non défini | AG66: Oui | AH66: Non défini | AI66: Interne : Personnes utiles suivant la situation Externe : ARS (CORSSI), informations préoccupantes, signalements au procureur | AJ66: SO | AK66: Non | AL66: SO | AM66: 2024 - Qualinéo : Gestion des évènements indésirables et gestion des plaintes | AN66: 3 | AO66: 0 | AP66: =$AN66*AO66 -> 0 | AQ66: 0 | AR66: =$AN66*AQ66 -> 0 | AS66: 2 | AT66: =$AN66*AS66 -> 6 | AU66: 0 | AV66: =$AN66*AU66 -> 0 | AW66: 0 | AX66: =$AN66*AW66 -> 0 | AY66: 0 | AZ66: =$AN66*AY66 -> 0 | BA66: 0 | BB66: =$AN66*BA66 -> 0 | BC66: 1 | BD66: =$AN66*BC66 -> 3 | BE66: 0 | BF66: =$AN66*BE66 -> 0 | BG66: 0 | BH66: =$AN66*BG66 -> 0 | BI66: =AP66:AP66+AR66:AR66+AT66:AT66+AV66:AV66+AX66:AX66+AZ66:AZ66+BB66:BB66+BD66:BD66+BF66:BF66+BH66:BH66 -> 9 | BK66: 2 | BO66: X | BR66: X
B67: 61 | C67: Résidence La Combe | D67: Professionnels, usagers Familles et proches des usagers | E67: Gestion des évènements indésirables | F67: 45561 | G67: 45561 | H67: Séparation de ce traitement pour la résidence La Combe | I67: Groupe CREATIVE | J67: Directeur de l'organisme | K67: Responsable qualité | L67: Gestion des évènements indésirables survenues au sein de l'organisme | M67: - Assurer la remontée des informations aux instances et autorités compétentes concernant des dysfonctionnements graves ou évènements pouvant compromettre la santé, la sécurité ou le bien-être des usagers - Etablir des statistiques - Evaluer la qualité des activités et prestations et les améliorer si besoin - Identification de besoins à couvrir - Garantir le respect des droits des personnes accompagnées - Garantir la protection des biens et des personnes | N67: Toute personne | O67: Nom, prénom | R67: Toute donnée selon la situation | S67: Toute donnée selon la situation | T67: Toute donnée selon la situation | V67: Toute donnée selon la situation | W67: Données sensibles (Art 9) ou données relatives aux condamnations pénales ou aux infractions (Art 10) | X67: Toute personne témoin de l'évènement | Y67: Fondé sur une obligation légale à laquelle le responsable du traitement est soumis | Z67: non | AA67: Bureau de la cheffe de service de la résidence La Combe | AB67: Dans un classeur du Bureau de la cheffe de service de la résidence La Combe fermé à clé | AC67: SO | AD67: SO | AE67: SO | AF67: non défini | AG67: Oui | AH67: Non défini | AI67: Interne : Personnes utiles suivant la situation Externe : ARS (CORSSI), informations préoccupantes, signalements au procureur | AJ67: SO | AK67: Non | AL67: SO | AM67: Nouveau logiciel de gestion des événements indésirables déployé courant du dernier trimestre 2024 - Qualinéo : Gestion des évènements indésirables et gestion des plaintes | AN67: 3 | AO67: 0 | AP67: =$AN67*AO67 -> 0 | AQ67: 0 | AR67: =$AN67*AQ67 -> 0 | AS67: 2 | AT67: =$AN67*AS67 -> 6 | AU67: 0 | AV67: =$AN67*AU67 -> 0 | AW67: 0 | AX67: =$AN67*AW67 -> 0 | AY67: 0 | AZ67: =$AN67*AY67 -> 0 | BA67: 0 | BB67: =$AN67*BA67 -> 0 | BC67: 1 | BD67: =$AN67*BC67 -> 3 | BE67: 0 | BF67: =$AN67*BE67 -> 0 | BG67: 0 | BH67: =$AN67*BG67 -> 0 | BI67: =AP67:AP67+AR67:AR67+AT67:AT67+AV67:AV67+AX67:AX67+AZ67:AZ67+BB67:BB67+BD67:BD67+BF67:BF67+BH67:BH67 -> 9 | BK67: 2 | BO67: X | BR67: X
B68: 62 | C68: Siège | D68: Usagers Familles et proches des usagers Professionnels Bénévoles | E68: Gestion des bénévoles | F68: 44277 | G68: 45498 | I68: Groupe CREATIVE | J68: Directeur de l'organisme | K68: Assistante de direction | L68: Collecter et utiliser des données permettant de contacter les bénévoles | M68: Gestion des bénévoles Réunir les bénévoles dans le cadre du conseil d'administration Statistiques animation | N68: Bénévoles | O68: Nom, prénom, date de naissance, n°de tel, adresse mail, adresse postale, puissance fiscale du véhicule | R68: Droit à l'image | S68: RIB | T68: Mission | V68: Pas de donnée sensible | W68: Aucun cas retenu | X68: Le bénévole | Y68: Fondé sur la réalisation d'une mission d’intérêt public | Z68: Non | AA68: Bureau de l'assistante de direction | AB68: Armoire fermée à clé dans le bureau de l'assistante de direction | AC68: Serveur RH + mail | AD68: Mot de passe | AE68: Interne | AF68: Pas de délai | AG68: Oui | AH68: Durée du bénévolat | AI68: Interne : Assistante de direction, CA, service RH, directeurs Externe : Bénévoles | AJ68: Invitation et compte-rendu pour les bénévoles | AK68: Non | AL68: SO | AO68: 0 | AP68: =$AN68*AO68 -> 0 | AQ68: 0 | AR68: =$AN68*AQ68 -> 0 | AS68: 2 | AT68: =$AN68*AS68 -> 0 | AU68: 0 | AV68: =$AN68*AU68 -> 0 | AW68: 0 | AX68: =$AN68*AW68 -> 0 | AY68: 0 | AZ68: =$AN68*AY68 -> 0 | BA68: 0 | BB68: =$AN68*BA68 -> 0 | BC68: 0 | BD68: =$AN68*BC68 -> 0 | BE68: 0 | BF68: =$AN68*BE68 -> 0 | BG68: 0 | BH68: =$AN68*BG68 -> 0 | BI68: =AP68:AP68+AR68:AR68+AT68:AT68+AV68:AV68+AX68:AX68+AZ68:AZ68+BB68:BB68+BD68:BD68+BF68:BF68+BH68:BH68 -> 0 | BJ68: Se référer au document word de préconisation | BK68: 1 | BO68: X | BR68: X
B69: 63 | C69: ESAT LA Simonière | D69: Professionnels, usagers Familles et proches des usagers | E69: Gestion des clients de l'ESAT | F69: 44277 | G69: 45562 | H69: Processus en cours d'écriture | I69: Groupe CREATIVE | J69: Directeur de l'organisme | K69: directeur | L69: Gestion des clients | M69: Gestion de la facturation, suivi de la clientèle, devis et signature de contrat | N69: Clients | O69: Nom, prénom, adresse, téléphone, mail | V69: Pas de donnée sensible | W69: Aucun cas retenu | X69: Clients | Y69: Fondé sur une obligation légale à laquelle le responsable du traitement est soumis | Z69: non | AA69: Bureau des MPA Burau de l'assistante commerciale Bureau de la comptable | AB69: Bureau des MPA peuvent fermer à clé Burau de l'assistante commerciale fermé à clé Bureau de la comptable fermé à clé | AC69: Serveur GESCO La GRAINE | AD69: User / Mdp | AE69: Interne Editeur | AF69: Aucune | AG69: Oui | AH69: Illimité | AI69: Interne : MPA, moniteurs, comptable, assistante commerciale, directrice Externe : clients | AJ69: Devis, contrat et facture | AK69: Non | AL69: SO | AM69: Processus de gestion commercial en cours d'écriture (tout suivre en dématérialisé) | AO69: 0 | AP69: =$AN69*AO69 -> 0 | AQ69: 0 | AR69: =$AN69*AQ69 -> 0 | AS69: 2 | AT69: =$AN69*AS69 -> 0 | AU69: 0 | AV69: =$AN69*AU69 -> 0 | AW69: 0 | AX69: =$AN69*AW69 -> 0 | AY69: 0 | AZ69: =$AN69*AY69 -> 0 | BA69: 0 | BB69: =$AN69*BA69 -> 0 | BC69: 0 | BD69: =$AN69*BC69 -> 0 | BE69: 0 | BF69: =$AN69*BE69 -> 0 | BG69: 0 | BH69: =$AN69*BG69 -> 0 | BI69: =AP69:AP69+AR69:AR69+AT69:AT69+AV69:AV69+AX69:AX69+AZ69:AZ69+BB69:BB69+BD69:BD69+BF69:BF69+BH69:BH69 -> 0 | BK69: 1 | BO69: X | BR69: X
B70: 64 | C70: DIME La Bretèche DIME L'espoir DIME Rennes ESAT LA Simonière ESAT Les espoirs Résidence du parc des bois Résidence La Combe SAVA Itinéraire Bis SAVS Tinténiac | D70: Usagers Familles et proches des usagers Professionnels Membre du CA Elus | E70: Fonctionnement des instances | F70: 44277 | G70: 25/06/2024 23/08/2024 26/09/2024 27/09/2024 19/12/2024 03/06/2025 15/07/2025 17/07/2025 18/07/2025 28/07/2025 | H70: Modification en commentaire des infos de trt des CR CVS (infos résidence du parc des bois) Info en commentaire sur les RP pour le DIME La bretèche CR sur le serveur S pour la Résidence La Combe Info en commentaire pour l'ESAT la Simonière Ajout de l'AG des travailleurs pour l'ESAT Les espoirs Ajout info ESAT La Simmonière Ajout info papier pour SAVS Mordelles Ajoint infos papier pour DIME Rennes Ajout infos papier DIME La Bretèche (18/07/25) Ajout commentaire - 28/07/25 | I70: Groupe CREATIVE | J70: Directeur de l'organisme | K70: Assistante de direction | L70: Collecter et utiliser des données permettant de réunir les instances (bureau, CA, CVS, représentant de proximité...) et de communiquer les compte-rendus ou autres documents | M70: - Réunion les instances - Communiquer les informations des instances - Réaliser des statistiques - Fonctionnements pour répondre à des besoins de gestion administrative | N70: Professionnels Membre du CA Elus Membre du CVS Membre de l'AG Travailleurs Financeurs Partenaires | O70: Nom, prénom, date de naissance, n°de tel, adresse mail, adresse postale | T70: Mission | V70: Pas de donnée sensible | W70: Aucun cas retenu | X70: Le représentant | Y70: Fondé sur la réalisation d'une mission d’intérêt public | Z70: Non | AA70: Bureau de l'assistante de direction Bureau de la directrice Atelier de l'ESAT Tous les établissements Couloir de l'ESAT la simonière Bureau de la cheffe de service du SAVS Mordelles Bureau de l'assistante de direction du DIME Rennes Hall du DIME Rennes DIME La Bretèche | AB70: Armoire fermée à clé dans le bureau de l'assistante de direction Compte-rendu dans le bureau de la directrice fermé à clé Affichage dans tous les établissements Cahier des comptes rendu de réunion RP dans le couloir de l'ESAT la simonière CR de réunion hebdomadaire équipe dans un classeur dans le bureau de la cheffe de service du SAVS Mordelles Dossier du CVS Bureau de l'assistante de direction du DIME Rennes fermé à clé Affichage des CR, liste élus et règlement intérieur dans le Hall du DIME Rennes Classeur des comptes-rendus des délégués du personnel dans la salle du personnel du DIME La Bretèche | AC70: Serveur & Mail & Toutateam | AD70: Fichier de suivi du Conseil d'administration dans le cloud avec accès restreint au Dir & Ass Dir Boite mail accessible par tous les salariés | AE70: Interne | AF70: non défini | AG70: Oui | AH70: Non défini | AI70: Interne : Gestionnaire RH, Assistante de direction, secrétaires, Directeur Général, membres des instances Externe : Membres externes | AJ70: Invitation et compte-rendu pour les membres externes | AK70: Non | AL70: SO | AM70: Conseil d'administration Journal associatif (Sollicite le droit à l'image) Fichier des adhérent du graal 35 Fichier des vœux avec en plus les partenaires Accès au fichier CSE (liste des membres) CVS : envoi à toutes les familles des infos de vote, CR stocké sur le serveur, envoi du CR aux familles, affichage du CR dans l'espace Usagers Tous les etablissements : envoi du CR à tous les professionnels par mail Résidence La Combe : CR sur le serveur S ESAT : Nomme des délégués aux personnes et bientôt une commission mixte ESAT : AG des travailleurs mensuelle sans nom, afficher en salle de pause ESAT La Simmonière : Journal interne diffusée au personnes du CVS et à disposition au siège, on peut avoir une interview d'un professionnel (consentement) SAVS Tinténiac - Qualinéo & Envoi mail - CR CSE & DP | AO70: 0 | AP70: =$AN70*AO70 -> 0 | AQ70: 0 | AS70: 2 | AU70: 0 | AW70: 0 | AY70: 0 | BA70: 0 | BC70: 0 | BD70: =$AN70*BC70 -> 0 | BG70: 0 | BK70: 0
B71: 65 | C71: Résidences Les Gantelles et Les Fougères | D71: Usagers Familles et proches des usagers Professionnels Membre du CA Elus | E71: Fonctionnement des instances | F71: 45582 | G71: 45838 | H71: Ajout envoi par mail | I71: Groupe CREATIVE | J71: Directeur de l'organisme | K71: Cheffe de service | L71: Collecter et utiliser des données permettant de réunir les instances (bureau, CA, CVS, représentant de proximité...) et de communiquer les compte-rendus ou autres documents | M71: - Réunion les instances - Communiquer les informations des instances - Réaliser des statistiques - Fonctionnements pour répondre à des besoins de gestion administrative | N71: Professionnels Membre du CA Elus Membre du CVS Financeurs Partenaires | O71: Nom, prénom, date de naissance, n°de tel, adresse mail, adresse postale | T71: Mission | V71: Pas de donnée sensible | W71: Aucun cas retenu | X71: Le représentant | Y71: Fondé sur la réalisation d'une mission d’intérêt public | Z71: Non | AA71: Salle commune Les Fougères Couloir Foyer Les Gantelles Bureau des salariés Foyer Les Gantelles | AB71: Affichage des CR de CVS dans la salle commune Les Fougères Affichage CR CVS dans le couloir Foyer Les Gantelles Affichage CR CVS dans le bureau des salariés Foyer Les Gantelles fermés à clé | AC71: Mail | AD71: Envoi du CR par mail à tous les membres du CVS | AE71: SO | AF71: non défini | AG71: Oui | AH71: Non défini | AI71: Interne : Salariés et usagers Externe : Membres externes | AJ71: Invitation et compte-rendu pour les membres externes | AK71: Non | AL71: SO | AO71: 0 | AP71: =$AN71*AO71 -> 0 | AQ71: 0 | AR71: =$AN71*AQ71 -> 0 | AT71: =$AN71*AS71 -> 0 | AV71: =$AN71*AU71 -> 0 | AW71: 0 | AX71: =$AN71*AW71 -> 0 | AY71: 0 | AZ71: =$AN71*AY71 -> 0 | BA71: 0 | BB71: =$AN71*BA71 -> 0 | BD71: =$AN71*BC71 -> 0 | BE71: 0 | BF71: =$AN71*BE71 -> 0 | BG71: 0 | BH71: =$AN71*BG71 -> 0 | BI71: =AP71:AP71+AR71:AR71+AT71:AT71+AV71:AV71+AX71:AX71+AZ71:AZ71+BB71:BB71+BD71:BD71+BF71:BF71+BH71:BH71 -> 0 | BJ71: Se référer au document word de préconisation | BK71: 0 | BO71: X | BR71: X
B72: 66 | C72: Siège | D72: Logs | E72: Gestion du SI / Logs / AD | F72: 44277 | I72: Groupe CREATIVE | J72: Directeur de l'organisme | K72: Responsable informatique | L72: Tracabilité des actions informatiques | M72: - Gestion des droits d'accès aux application et réseau - Gestion du parc informatique - Getsion de la téléphonie (fixe, mobile, bip) - Gestion des annuaires internes - Journalisation des évènements - Gestion des logs réseaux et applicatifs - Concervation des preuves - Gestion des fichiers - Gestion téléphonie mobile - Sauvegardes / archivage | N72: Salariés, Stagiaires/Apprenti | O72: Nom, prénom, adresse IP, N° de poste et N° de portable professionnel, date d'entrée et/ou de sortie | P72: Login, IP, Mot de passe possibe | Q72: NON | T72: Profil d'accès | U72: Journalisation d'évènements (données traitées uniquement en cas d'incident sécurité) | V72: Pas de donnée sensible | W72: Aucun cas retenu | X72: Jounalisation, administration, mise à disposition, annuaire | Y72: Aux fins des intérêts légitimes poursuivis par le responsable du traitement (C47 -48- 49) | Z72: Non | AA72: SO | AB72: SO | AC72: Bretagne Télécom | AD72: Droits d'acces validé par la Direction | AE72: Bretagne Télécom | AF72: Durée du contrat | AG72: Oui | AH72: 14 jours | AI72: Interne : Externe : AJP (avec hébergement chez Bretagne télécom) | AJ72: Hébergeur | AK72: Non | AL72: SO | AM72: Hébergement à ChateauBourg, à voir le contrat de sous-traitance sur la durée de conservation des logs | AO72: 0 | AP72: =$AN72*AO72 -> 0 | AQ72: 0 | AR72: =$AN72*AQ72 -> 0 | AT72: =$AN72*AS72 -> 0 | AV72: =$AN72*AU72 -> 0 | AW72: 0 | AX72: =$AN72*AW72 -> 0 | AY72: 0 | AZ72: =$AN72*AY72 -> 0 | BA72: 0 | BB72: =$AN72*BA72 -> 0 | BD72: =$AN72*BC72 -> 0 | BE72: 0 | BF72: =$AN72*BE72 -> 0 | BG72: 0 | BH72: =$AN72*BG72 -> 0 | BI72: =AP72:AP72+AR72:AR72+AT72:AT72+AV72:AV72+AX72:AX72+AZ72:AZ72+BB72:BB72+BD72:BD72+BF72:BF72+BH72:BH72 -> 0 | BJ72: Se référer au document word de préconisation | BK72: 1 | BO72: X | BR72: X
B73: 67 | C73: Siège | D73: Usagers Familles et proches des usagers Professionnels Membre du CA Elus | E73: Gestion du site internet | F73: 44277 | I73: Groupe CREATIVE | J73: Directeur de l'organisme | K73: Responsabkle du service informatique / LINKEO | L73: Responsabkle du service informatique / LINKEO | M73: - Preparation et publication de contenu - Mise en ligne de formulaire de contact - Dépôt de CV et de lettre de motivation - Gestion de la sécurité du site - Production de statistiques d'audience - Mise à disposition d'informations interne à la structure - Don via HelloAsso | N73: Salariés, Stagiaires/Apprenti, publique | O73: nom prénom des contacts commerciaux, adresse, téléphone portable et bureau, @IP | P73: Login, IP, Mot de pass possibe | Q73: Pays | T73: CV et lettre de motivation pour les candidatures | U73: Données relatives à la navigation | V73: Pas de donnée sensible | W73: Aucun cas retenu | X73: Par l'hebergeur | Y73: Fondé sur une obligation légale à laquelle le responsable du traitement est soumis | Z73: oui (statistiques d'audience) | AA73: SO | AB73: SO | AC73: O2Switch | AD73: Droits d'acces administration pour le Secrétariat direction générale, RH, plateforme Sport et Culture et le responsable informatique | AE73: Chez le prestataire (O2Switch via OVH) | AF73: Non | AG73: Oui | AH73: Illimité | AI73: Interne : Externe : OVH, MAMOTO | AJ73: Hébergeur | AK73: Non | AL73: SO | AM73: A voir durée de conservation avec Mamoto Projet de refonte des sites internet en 2025 | AO73: 0 | AP73: =$AN73*AO73 -> 0 | AQ73: 0 | AR73: =$AN73*AQ73 -> 0 | AT73: =$AN73*AS73 -> 0 | AV73: =$AN73*AU73 -> 0 | AW73: 0 | AX73: =$AN73*AW73 -> 0 | AY73: 0 | AZ73: =$AN73*AY73 -> 0 | BA73: 0 | BB73: =$AN73*BA73 -> 0 | BD73: =$AN73*BC73 -> 0 | BE73: 0 | BF73: =$AN73*BE73 -> 0 | BG73: 0 | BH73: =$AN73*BG73 -> 0 | BI73: =AP73:AP73+AR73:AR73+AT73:AT73+AV73:AV73+AX73:AX73+AZ73:AZ73+BB73:BB73+BD73:BD73+BF73:BF73+BH73:BH73 -> 0 | BJ73: Se référer au document word de préconisation | BK73: 1 | BO73: X | BR73: X
B74: 68 | C74: ESAT Les espoirs | D74: clients et fournisseurs | E74: Progiciel de gestion intégré WORKPLAN | F74: 45078 | G74: 19/12/2024 19/08/2025 | H74: Ajout d'un commentaire Modif du commentaire (19/08/25) | I74: Groupe CREATIVE | J74: Directeur de l'organisme | K74: Laurent PIEN | L74: ERP | N74: clients fournisseurs | O74: nom prénom des contacts commerciaux, adresse, téléphone portable et bureau | S74: RIB clients et fournisseurs | V74: Pas de donnée sensible | W74: Aucun cas retenu | X74: par le client ou le fournisseur | Y74: Aux fins des intérêts légitimes poursuivis par le responsable du traitement (C47 -48- 49) | Z74: non | AA74: SO | AB74: SO | AC74: WORKPLAN | AD74: accès réservé et droits d'accès (identification mot de passe) selon les fonctions | AE74: OVH? | AF74: 10 ans | AG74: Non | AH74: SO | AI74: Interne : chef d'atelier, responsable commercial, comptable Externe : Clients & Fournisseurs | AJ74: facturation des clients et règlement des fournisseurs | AK74: Non | AL74: SO | AM74: Projet de changement de logiciel, passage à GESCO en stand by | AO74: 0 | AP74: =$AN74*AO74 -> 0 | AQ74: 0 | AR74: =$AN74*AQ74 -> 0 | AS74: 3 | AT74: =$AN74*AS74 -> 0 | AU74: 0 | AV74: =$AN74*AU74 -> 0 | AW74: 0 | AX74: =$AN74*AW74 -> 0 | AY74: 0 | AZ74: =$AN74*AY74 -> 0 | BA74: 0 | BB74: =$AN74*BA74 -> 0 | BC74: 0 | BD74: =$AN74*BC74 -> 0 | BE74: 0 | BF74: =$AN74*BE74 -> 0 | BG74: 0 | BH74: =$AN74*BG74 -> 0 | BI74: =AP74:AP74+AR74:AR74+AT74:AT74+AV74:AV74+AX74:AX74+AZ74:AZ74+BB74:BB74+BD74:BD74+BF74:BF74+BH74:BH74 -> 0 | BJ74: Se référer au document word de préconisation | BK74: 0 | BO74: X | BR74: X
B75: 69 | C75: DIME La Bretèche DIME L'espoir DIME Rennes ESAT LA Simonière ESAT Les espoirs Résidence du parc des bois Résidence La Combe Résidences Les Gantelles et Les Fougères SAVA Itinéraire Bis SAVS Tinténiac | D75: Usagers | E75: Progiciel de suivi du dossier unique de l'usager MEDIATEAM | F75: 44277 | G75: 45468 | H75: Modification de l'emplacement numérique | I75: Groupe CREATIVE | J75: Directeur de l'organisme | K75: MEDIALIS éditeur du logiciel | L75: suivi du projet social et professionnel de l'usager | M75: Statistiques ? | N75: personnes accueillies, usagers bénéficiaires | O75: Nom, prénom, date de naissance, n°de tel, adresse mail, adresse postale | P75: N/A | Q75: N/A | R75: Données de vie sociale | S75: Prestations handicap | T75: Projet professionnel dont formations, expériences antérieures | U75: nom prénom date de naissance des enfants, n° SS, attestation RQTH, orientation MDPH; contrat d'aide et de soutien, contrat de séjour, dossier médical, contact en cas d'urgence | V75: NIR (N° SS) | W75: Données sensibles (Art 9) ou données relatives aux condamnations pénales ou aux infractions (Art 10) | X75: Par les assistantes / éducateurs | Y75: Fondé sur l’exécution d’un contrat avec la personne physique concernée, | Z75: Non | AA75: SO | AB75: SO | AC75: Mediateam | AD75: Connexion avec authentification forte via un certificat | AE75: Berger Levrault | AF75: aucune | AG75: Oui | AH75: Gérée par l'éditeur BL | AI75: Interne : Tous le personnel sauf agent d'entretien et de restauration | AJ75: SO | AK75: Non | AL75: SO | AN75: 2 | AO75: 0 | AP75: =$AN75*AO75 -> 0 | AQ75: 0 | AR75: =$AN75*AQ75 -> 0 | AS75: 0 | AT75: =$AN75*AS75 -> 0 | AU75: 0 | AV75: =$AN75*AU75 -> 0 | AW75: 0 | AX75: =$AN75*AW75 -> 0 | AY75: 0 | AZ75: =$AN75*AY75 -> 0 | BA75: 0 | BB75: =$AN75*BA75 -> 0 | BC75: 0 | BD75: =$AN75*BC75 -> 0 | BE75: 0 | BF75: =$AN75*BE75 -> 0 | BG75: 0 | BH75: =$AN75*BG75 -> 0 | BI75: =AP75:AP75+AR75:AR75+AT75:AT75+AV75:AV75+AX75:AX75+AZ75:AZ75+BB75:BB75+BD75:BD75+BF75:BF75+BH75:BH75 -> 0 | BJ75: Se référer au document word de préconisation | BK75: 0 | BO75: X | BR75: X
B76: 70 | C76: ESAT LA Simonière | D76: clients | E76: logiciel de gestion commerciale LA GRAINE INFORMATIQUE | F76: 44277 | I76: Groupe CREATIVE | J76: Directeur de l'organisme | L76: gestion commerciale | N76: clients fournisseurs | O76: nom prénom des contacts commerciaux, adresse, téléphone portable et bureau | R76: RIB clients et fournisseurs | V76: Pas de donnée sensible | W76: Aucun cas retenu | X76: par leclient ou le fournisseur | Y76: Aux fins des intérêts légitimes poursuivis par le responsable du traitement (C47 -48- 49) | Z76: Non | AA76: SO | AB76: SO | AC76: LA GRAINE INFORMATIQUE | AD76: identifiant mot de passe, accès réservé et droits d'accès selon les fonctions | AE76: Editeur | AF76: 10 ans | AG76: Non | AH76: SO | AI76: Externe : cloud éditeur | AJ76: Logiciel SAAS | AK76: Non | AL76: SO | AO76: 0 | AP76: =$AN76*AO76 -> 0 | AQ76: 0 | AR76: =$AN76*AQ76 -> 0 | AT76: =$AN76*AS76 -> 0 | AV76: =$AN76*AU76 -> 0 | AW76: 0 | AX76: =$AN76*AW76 -> 0 | AY76: 0 | AZ76: =$AN76*AY76 -> 0 | BA76: 0 | BB76: =$AN76*BA76 -> 0 | BD76: =$AN76*BC76 -> 0 | BF76: =$AN76*BE76 -> 0 | BG76: 0 | BH76: =$AN76*BG76 -> 0 | BI76: =AP76:AP76+AR76:AR76+AT76:AT76+AV76:AV76+AX76:AX76+AZ76:AZ76+BB76:BB76+BD76:BD76+BF76:BF76+BH76:BH76 -> 0 | BJ76: Se référer au document word de préconisation | BK76: 0
B77: 71 | C77: DIME La Bretèche DIME L'espoir DIME Rennes ESAT LA Simonière ESAT Les espoirs Résidence du parc des bois Résidence La Combe SAVA Itinéraire Bis SAVS Tinténiac | D77: usagers Familles et proches des usagers Professionnels Membre du CA Elus | E77: Gestion du CSE | F77: 44277 | G77: 23/08/2024 26/09/2024 27/09/2024 19/12/2024 | H77: Ajout info sur l'envoi des CR Ajout info pour la Résidence La Combe ajout info affichage pour l'ESAT La Simonière et Les espoirs | I77: Groupe CREATIVE | J77: Directeur de l'organisme | K77: CSE | L77: Collecter et utiliser des données permettant de réunir les instances et de communiquer les compte-rendus ou autres documents | M77: - Réunion les instances - Communiquer les informations des instances - Réaliser des statistiques - fonctionnement s pour répondre à des besoins de gestion administrative ; - Gestion des évènements indésirables | N77: Collaborateur et leur famille | O77: Nom, prénom | R77: Nom, prénom et âge des enfants | T77: mail | V77: Pas de donnée sensible | W77: Aucun cas retenu | X77: Listing collaborateurs par les RH Autres informations : saisie volontaire du salarié | Y77: Fondé sur le consentement préalable de la personne physique, | Z77: non | AA77: SO | AB77: SO | AC77: Géré par le CSE | AD77: Géré par le CSE | AE77: CSE | AF77: SO | AG77: SO | AH77: SO | AI77: Interne : Externe : | AJ77: SO | AK77: Non | AL77: SO | AM77: CR transmis par mail et affiché sur TOUTATEAM Résidence du parc : géré par le CSE, rien à la résidence Résidence La Combe : réception des CR par mail par chaque salarié ESAT la simonière : recu par mail, Affichage des CR dans le couloir ESAT Les espoirs : CR afficher en salle de pause professionnelle | AO77: 0 | AP77: =$AN77*AO77 -> 0 | AQ77: 0 | AS77: 0 | AU77: 0 | AW77: 0 | AY77: 0 | BA77: 0 | BC77: 0 | BG77: 0 | BK77: 1
B78: 72 | C78: Résidences Les Gantelles et Les Fougères | D78: usagers Familles et proches des usagers Professionnels Membre du CA Elus | E78: Gestion du CSE | F78: 45582 | G78: 45838 | H78: Envoi mail des CR | I78: Groupe CREATIVE | J78: Directeur de l'organisme | K78: CSE | L78: Collecter et utiliser des données permettant de réunir les instances et de communiquer les compte-rendus ou autres documents | M78: - Réunion les instances - Communiquer les informations des instances - Réaliser des statistiques - fonctionnement s pour répondre à des besoins de gestion administrative ; - Gestion des évènements indésirables | N78: Collaborateur et leur famille | O78: Nom, prénom | R78: Nom, prénom et âge des enfants | T78: mail | V78: Pas de donnée sensible | W78: Aucun cas retenu | X78: Listing collaborateurs par les RH Autres informations : saisie volontaire du salarié | Y78: Fondé sur le consentement préalable de la personne physique, | Z78: non | AA78: Bureau de la direction Bureau du personnel Les Fougères Bureau des salariés Foyer Les Gantelles | AB78: Armoire fermée à clé contenant les CR CSE dans le bureau de la direction fermé à clé Panneau des affichages CSE et Répertoire CSE sur l'ordinateur fixe dans le bureau du personnel Les Fougères fermé à clé Affichage CR CSE dans le bureau des salariés Foyer Les Gantelles fermés à clé | AC78: Mail | AD78: Envoyé par mail par La Bretèche | AE78: SO | AF78: SO | AG78: SO | AH78: SO | AI78: Interne : Externe : | AJ78: SO | AK78: Non | AL78: SO | AO78: 0 | AP78: =$AN78*AO78 -> 0 | AQ78: 0 | AR78: =$AN78*AQ78 -> 0 | AT78: =$AN78*AS78 -> 0 | AV78: =$AN78*AU78 -> 0 | AW78: 0 | AX78: =$AN78*AW78 -> 0 | AY78: 0 | AZ78: =$AN78*AY78 -> 0 | BA78: 0 | BB78: =$AN78*BA78 -> 0 | BD78: =$AN78*BC78 -> 0 | BF78: =$AN78*BE78 -> 0 | BG78: 0 | BH78: =$AN78*BG78 -> 0 | BI78: =AP78:AP78+AR78:AR78+AT78:AT78+AV78:AV78+AX78:AX78+AZ78:AZ78+BB78:BB78+BD78:BD78+BF78:BF78+BH78:BH78 -> 0 | BJ78: Se référer au document word de préconisation | BK78: 1
B79: 73 | C79: Siège | D79: Sous-traitants | E79: Gestion des sous traitants | F79: 45093 | G79: 10/07/2025 24/07/2025 | H79: Ajout info SI du service Paie Modification des emplacements physiques - 24/07/25 | I79: Groupe CREATIVE | J79: Directeur de l'organisme | K79: Responsable Informatique Responsable qualité (QUALINEO) Controleuse de gestion social (Octime) RAF (Compta) responsable Paie Responsable immobilier Bati | L79: Collecter et transmettre des données permettant de travailler avec un sous traitant | M79: - Gestion des interventions - Gestion contractuelle et comptable | N79: Sous-traitants | O79: Nom, prénom, adresse professionnelle, mail, téléphone | T79: RiB | V79: Pas de donnée sensible | W79: Aucun cas retenu | X79: Par le sous-traitant | Y79: Fondé sur l’exécution d’un contrat avec la personne physique concernée, | Z79: Non | AA79: Bureau de la RAF Bureau des comptables d'établissement Bureau des directeurs | AB79: Armoire fermée à clé et bureau fermé à clé Bureau des comptables fermé à clé Contrats dans les Bureau des directeurs fermés à clé | AC79: Serveur Octime ALPHA GRH (Paie, remplacé par Paynext) | AD79: Accès à revoir pour savoir qui accès OCTIME avec user/mdp Paie avce User / mdp | AE79: Interne Octime CEGI | AF79: Géré par les éditeurs | AG79: oui | AH79: Géré par les éditeurs | AI79: Interne : RAF, comptables Externe : sous-traitants | AJ79: Facturation et gestion de contrat | AK79: Non | AL79: SO | AM79: AGEVAL remplacé par QUALINEO | AO79: 0 | AP79: =$AN79*AO79 -> 0 | AQ79: 0 | AR79: =$AN79*AQ79 -> 0 | AT79: =$AN79*AS79 -> 0 | AV79: =$AN79*AU79 -> 0 | AW79: 0 | AX79: =$AN79*AW79 -> 0 | AY79: 0 | AZ79: =$AN79*AY79 -> 0 | BA79: 0 | BB79: =$AN79*BA79 -> 0 | BD79: =$AN79*BC79 -> 0 | BF79: =$AN79*BE79 -> 0 | BG79: 0 | BH79: =$AN79*BG79 -> 0 | BI79: =AP79:AP79+AR79:AR79+AT79:AT79+AV79:AV79+AX79:AX79+AZ79:AZ79+BB79:BB79+BD79:BD79+BF79:BF79+BH79:BH79 -> 0 | BJ79: Se référer au document word de préconisation | BK79: 1
B80: 74 | C80: Siège | D80: Anciens et nouveaux donateurs et sociétés | E80: Dons et taxe professionnelle | F80: 45096 | G80: 45862 | H80: Modification des emplacements physiques - 24/07/25 | I80: Groupe CREATIVE | J80: Directeur de l'organisme | K80: Assistante de direction | L80: Collecter et utiliser des données permettant de sollciter les donateurs et les sociétés pour déductions fiscales sur les dons et taxe professionnelle | M80: - Relance des anciens donateurs - Démarchage pour des demandes de dons - Gestion des dons via le site ou directement - Incitation des entreprises cotoyés pour déduction de leur taxe professionnelle via l'organisme - Relance pour la taxe professionnelle - Suivi des professionnels et donateurs - Traitement administratif, financier et fiscal des dons - Déclaration administratives et fiscale des dons - Gestion des adhérents (donateurs + vote à l'AG) | N80: Donateurs et sociétés | O80: Nom, Prénom, Adresse, Adresse e-mail, Numéro de téléphone | S80: RIB | T80: mail, fonction | V80: Pas de donnée sensible | W80: Aucun cas retenu | X80: Listing collaborateurs par les RH Autres informations : saisie volontaire du donateur ou de l'entreprise | Y80: Fondé sur le consentement préalable de la personne physique, | Z80: Oui | AA80: Bureau de l'assistante de direction et de la responsable administrative et financière Bureau des comptables | AB80: Armoire fermée à clé dans le bureau de l'assistante de direction Taxes professionnelles stockées dans le Bureau des comptables | AC80: Sur le serveur local | AD80: Accès par connexion avec login et mot de passe réservé aux personnes autorisées | AE80: Serveur local | AF80: Illimité | AG80: Non | AH80: SO | AI80: Interne : Assistante de direction et RAF Externe : | AJ80: SO | AK80: Non | AL80: SO | AM80: Relance des familles pour un don lors de l'appel à cotisation | AO80: 0 | AP80: =$AN80*AO80 -> 0 | AQ80: 0 | AR80: =$AN80*AQ80 -> 0 | AS80: 3 | AT80: =$AN80*AS80 -> 0 | AU80: 0 | AV80: =$AN80*AU80 -> 0 | AW80: 0 | AX80: =$AN80*AW80 -> 0 | AY80: 0 | AZ80: =$AN80*AY80 -> 0 | BA80: 0 | BB80: =$AN80*BA80 -> 0 | BC80: 0 | BD80: =$AN80*BC80 -> 0 | BF80: =$AN80*BE80 -> 0 | BG80: 0 | BH80: =$AN80*BG80 -> 0 | BI80: =AP80:AP80+AR80:AR80+AT80:AT80+AV80:AV80+AX80:AX80+AZ80:AZ80+BB80:BB80+BD80:BD80+BF80:BF80+BH80:BH80 -> 0 | BJ80: Se référer au document word de préconisation | BK80: 1
B81: 75 | C81: DIME L'espoir DIME Rennes | D81: Usagers et Professionnels | E81: Modélisation et simulation du financement des ESMS | F81: 45701 | G81: 45856 | H81: Ajout infos en commentaire | I81: Groupe CREATIVE | J81: Directeur de l'organisme | K81: Responsable Qualité | L81: Modélisation et de simulation du financement des ESMS | M81: Disposer d’un état des lieux national sur l’activité et les coûts des établissements et services sociaux et médico-sociaux mentionnés au I du présent article ; Simuler et ajuster les différents scénarios du modèle de fnancement de ces établissements et services ; Mettre à disposition de ces établissements et services des données leur permettant d’évaluer les effets du modèle retenu sur leurs fnancements ; Produire des études à des fns de pilotage et d’évaluation du fnancement de ces établissements et services ainsi qu’à des fins d’appui aux politiques publiques mises en œuvre par la direction générale de la cohésion sociale et la Caisse nationale de solidarité pour l’autonomie dans le cadre de leurs missions | N81: Usagers et Professionnels | O81: Usagers : le code interne d’identification de la personne accompagnée, son mois et son année de naissance, ainsi que son sexe Professionnels : Les données d’identifcation et d’activité, code interne de l’intervenant (nom, prénom, fonction, courriel et numéro de téléphone), statut à l’égard de l’établissement (salarié, intérimaire, libéral, famille, prestataire, agent de droit public), fonction exercée, date et période de présence, description du ou des trajets effectués | R81: Usagers : informations relatives à la situation de handicap ; Les informations relatives aux modalités d’accueil ; Les données de présence dans l’établissement ; Les données relatives à la scolarisation et à l’accompagnement par un service. | X81: Les usagers et les professionnels | Y81: Fondé sur une obligation légale à laquelle le responsable du traitement est soumis | Z81: Oui | AC81: Coupe SERAPHIN PH | AF81: 10 ans | AG81: Non | AH81: SO | AI81: Interne : Tous les professionnels Externe : Les agents de l’Agence technique de l’information sur l’hospitalisation individuellement désignés et dûment habilités par le directeur de l’agence ; Les agents de la Caisse nationale de solidarité pour l’autonomie individuellement désignés et dûment habilités par le directeur de la caisse. La direction générale de la cohésion sociale ; | AK81: Non | AM81: Nouveau traitement imposé par l'état pour les IME Extrait des données envoyées à l'ATIH en test. Au 1er janv 2026, l'ensemble des actions seront typés SERAPHIN | AP81: =$AN81*AO81 -> 0 | AR81: =$AN81*AQ81 -> 0 | AT81: =$AN81*AS81 -> 0 | AV81: =$AN81*AU81 -> 0 | AX81: =$AN81*AW81 -> 0 | AZ81: =$AN81*AY81 -> 0 | BB81: =$AN81*BA81 -> 0 | BD81: =$AN81*BC81 -> 0 | BF81: =$AN81*BE81 -> 0 | BH81: =$AN81*BG81 -> 0 | BI81: =AP81:AP81+AR81:AR81+AT81:AT81+AV81:AV81+AX81:AX81+AZ81:AZ81+BB81:BB81+BD81:BD81+BF81:BF81+BH81:BH81 -> 0 | BJ81: Se référer au document word de préconisation
B82: 76 | C82: DIME L'espoir | D82: Usagers et leurs familles | E82: Transport des élèves | F82: 45848 | I82: Groupe CREATIVE | J82: Directeur de l'organisme | K82: Chef de service | L82: Gestion du transport des élèves avec la société concernée | N82: Usagers et leurs familles | O82: Nom, prénom, adresse et téléphone | V82: Pas de donnée sensible | W82: Données sensibles (Art 9) ou données relatives aux condamnations pénales ou aux infractions (Art 10) | X82: Inscription à l'IME | Y82: Fondé sur l’exécution d’un contrat avec la personne physique concernée, | Z82: Non | AA82: SO | AB82: SO | AC82: Envoi mail de la liste des enfants à transporter jusqu'à l'IME | AD82: - | AE82: RAOUL TSH | AF82: ? | AG82: Non | AH82: ? | AI82: Interne : Externe : Société de transport | AJ82: Organiser le transport des élèves | AK82: Non | AM82: Nouveau traitement, Convention à créer avec la société de transport pour lui indiquer de ne pas utiliser ses données pour autre chose que le transport des enfants | AN82: 1 | AO82: 0 | AP82: =$AN82*AO82 -> 0 | AQ82: 0 | AR82: =$AN82*AQ82 -> 0 | AS82: 2 | AT82: =$AN82*AS82 -> 2 | AU82: 0 | AV82: =$AN82*AU82 -> 0 | AW82: 0 | AX82: =$AN82*AW82 -> 0 | AY82: 0 | AZ82: =$AN82*AY82 -> 0 | BA82: 0 | BB82: =$AN82*BA82 -> 0 | BC82: 2 | BD82: =$AN82*BC82 -> 2 | BE82: 0 | BF82: =$AN82*BE82 -> 0 | BG82: 0 | BH82: =$AN82*BG82 -> 0 | BI82: =AP82:AP82+AR82:AR82+AT82:AT82+AV82:AV82+AX82:AX82+AZ82:AZ82+BB82:BB82+BD82:BD82+BF82:BF82+BH82:BH82 -> 4 | BJ82: Se référer au document word de préconisation | BK82: 1 | BO82: X | BR82: X
B83: 77 | C83: DIME Rennes | D83: Demandeurs Familles et proches des demandeurs | E83: Gestion des stagiaires usagers | F83: 45855 | I83: Groupe CREATIVE | J83: Directeur de l'organisme | K83: Chargée d'Insertion Professionnelle | L83: Permettre de découvrir un nouvel environnement de travail | M83: Premier stage pour permettre de découvrir un nouvel environnement de travail Deuxième stage, pour préparer une admission | N83: Demandeur, Familles et partenaires | O83: Nom d’usage Nom de naissance Prénom(s) Date de naissance, N° MSA/CAF, adresse, téléphone, email | R83: Situation familiale Nombre d’enfant(s) Etablissement d'origine, présence d’un aidant, prestation en place (SSIAD, ADMR…) Mesure de protection juridique | S83: Financements, aides, allocation et prestation de compensation | T83: Savoir fondamentaux (lire/écrire/compter) CV Bilans professionnels | U83: NIR Données comportement et handicap | V83: NIR (N° SS) + Concernant le santé | W83: Données sensibles (Art 9) ou données relatives aux condamnations pénales ou aux infractions (Art 10) | X83: Par le demandeur (usager / famille / xxx ) par mail ou courrier | Y83: Fondé sur le consentement préalable de la personne physique, | Z83: Non | AA83: Bureau de la personne Chargée d'Insertion Professionnelle | AB83: Dans un classeur dans une armoire du bureau fermé à clé de la personne Chargée d'Insertion Professionnelle | AC83: Mediateam Serveur de fichier | AD83: User + Mdp | AE83: Berger Levrault Interne | AF83: Mediateam | AG83: Oui | AH83: Mediateam | AI83: Interne :Service social, service de paie Externe : MDPH | AJ83: SO | AK83: Non | AL83: SO | AN83: =SUM(AN4:AN76) -> 71 | AP83: =SUM(AP4:AP76) -> 0 | AR83: =SUM(AR4:AR76) -> 0 | AT83: =SUM(AT4:AT76) -> 84 | AV83: =SUM(AV4:AV76) -> 17 | AX83: =SUM(AX4:AX76) -> 14 | AZ83: =SUM(AZ4:AZ76) -> 0 | BB83: =SUM(BB4:BB76) -> 0 | BD83: =SUM(BD4:BD76) -> 28 | BF83: =SUM(BF4:BF76) -> 0 | BH83: =SUM(BH4:BH76) -> 0
B84: 78 | C84: DIME Rennes | D84: Professionnels | E84: Gestion administrative du personnel | F84: 45855 | H84: Séparation du traitement pour le DIME Rennes | I84: Groupe CREATIVE | J84: Directeur de l'organisme | K84: Responsables RH | L84: Gestion administrative et paye du personnel spécifique du DIME Rennes, en plus du siège | M84: - Gestion du dossier professionnel des salariés; (( CV, pièce administrative tel que casier judiciaire, carte d'identité, diplome, RIB, carte vitale, permis) - gestion de la paie - gestion des aptitudes médicales par rapport au poste - gestion des contacts en cas d'urgence - gestion des absences (congés, maladie, évènements familaiux, …) - gestion des accidents de travail (et presque accident) - gestion RQTH - entretien de carrière / individuel - gestion du droit à l'image | N84: Salariés | O84: Nom, prénom, adresse, dt nais, lieu de naissance, contacts, poste, date d'arrivée, contact en cas d'urgence | U84: NIR | V84: NIR (N° SS) | W84: Données sensibles (Art 9) ou données relatives aux condamnations pénales ou aux infractions (Art 10) | X84: Par le salarié | Y84: Fondé sur l’exécution d’un contrat avec la personne physique concernée, | Z84: Non | AA84: Bureau de l'adjointe de direction Infirmerie | AB84: Fiche horaire et demande de congés dans le bureau de l'adjointe de direction fermé à clé Classeur des accidents du travail à l'infirmerie fermée à clé | AC84: Serveur PST35 | AD84: Base de données contenant tous le dossier du salarié Fichier de pré-paye avec les heures/arrêt maladie/congés Correspondance de médecine du travail (PST35) RIB des salariés pour la comptable Fiche de suivi sur divers documents sur le serveur | AE84: Interne Médecine du travail | AF84: Non | AG84: Oui | AH84: Indéfini + Editeur | AI84: Interne : Service RH Directeur, chefs de service Adjointe de direction IME Externe : Paie & Médecine du travail | AJ84: Transmission des informations obligatoires | AK84: Non | AL84: SO | AM84: En complément du traitement de Gestion administrative du personnel global de l'association, pour des spécificités du DIME Rennes | AN84: =SUM(AN5:AN77) -> 71 | AP84: =SUM(AP5:AP77) -> 0 | AR84: =SUM(AR5:AR77) -> 0 | AT84: =SUM(AT5:AT77) -> 84 | AV84: =SUM(AV5:AV77) -> 17 | AX84: =SUM(AX5:AX77) -> 14 | AZ84: =SUM(AZ5:AZ77) -> 0 | BB84: =SUM(BB5:BB77) -> 0 | BD84: =SUM(BD5:BD77) -> 28 | BF84: =SUM(BF5:BF77) -> 0 | BH84: =SUM(BH5:BH77) -> 0
B85: 79 | C85: DIME La Bretèche | D85: Demandeurs Familles et proches des demandeurs | E85: Gestion des stagiaires usagers | F85: 45856 | I85: Groupe CREATIVE | J85: Directeur de l'organisme | K85: Chargée d'Insertion Professionnelle | L85: Permettre de découvrir un nouvel environnement de travail | M85: Premier stage pour permettre de découvrir un nouvel environnement de travail Deuxième stage, pour préparer une admission | N85: Demandeur, Familles et partenaires | O85: Nom d’usage Nom de naissance Prénom(s) Date de naissance, N° MSA/CAF, adresse, téléphone, email | R85: Situation familiale Nombre d’enfant(s) Etablissement d'origine, présence d’un aidant, prestation en place (SSIAD, ADMR…) Mesure de protection juridique | S85: Financements, aides, allocation et prestation de compensation | T85: Savoir fondamentaux (lire/écrire/compter) CV Bilans professionnels | U85: NIR Données comportement et handicap | V85: NIR (N° SS) + Concernant le santé | W85: Données sensibles (Art 9) ou données relatives aux condamnations pénales ou aux infractions (Art 10) | X85: Par le demandeur (usager / famille / xxx ) par mail ou courrier | Y85: Fondé sur le consentement préalable de la personne physique, | Z85: Non | AA85: SO | AB85: SO | AC85: Serveur de fichier K | AD85: User + Mdp | AE85: Interne | AF85: Non | AG85: Oui | AH85: Illimité | AI85: Interne :Service social, service de paie Externe : MDPH | AJ85: SO | AK85: Non | AL85: SO | AM85: Entre 1 et 6 jeunes en stage chaque semaine Actuellement pas dans Mediateam mais possible | AN85: =SUM(AN6:AN78) -> 71 | AP85: =SUM(AP6:AP78) -> 0 | AR85: =SUM(AR6:AR78) -> 0 | AT85: =SUM(AT6:AT78) -> 84 | AV85: =SUM(AV6:AV78) -> 17 | AX85: =SUM(AX6:AX78) -> 14 | AZ85: =SUM(AZ6:AZ78) -> 0 | BB85: =SUM(BB6:BB78) -> 0 | BD85: =SUM(BD6:BD78) -> 28 | BF85: =SUM(BF6:BF78) -> 0 | BH85: =SUM(BH6:BH78) -> 0
B86: 80 | C86: ESAT Les espoirs | D86: Logs | E86: Alarme | F86: 45888 | I86: Groupe CREATIVE | J86: Directeur de l'organisme | K86: Responsable informatique | L86: Tracabilité des activations/désactivations de l'alarme | M86: - Gestion des droits d'accès à l'alarme - Journalisation des évènements - Concervation des preuves | N86: Salariés | O86: Nom, prénom, date/heure activation/désactivation par zone | V86: Pas de donnée sensible | W86: Aucun cas retenu | X86: Clavier des arlarmes | Y86: Aux fins des intérêts légitimes poursuivis par le responsable du traitement (C47 -48- 49) | Z86: Non | AA86: SO | AB86: SO | AC86: Risco Group | AD86: Géré par Risco Group | AE86: Risco Group | AF86: Non | AG86: Oui | AH86: 3 ans | AI86: Interne : Externe : Risco Group | AJ86: Hébergeur | AK86: Oui | AL86: Angleterre (norme GDPR-UK) | AM86: Contrat souscrit auprès de Adrien Alarme qui sous-traite à Risco Group | AO86: 0 | AP86: =$AN86*AO86 -> 0 | AQ86: 0 | AR86: =$AN86*AQ86 -> 0 | AT86: =$AN86*AS86 -> 0 | AV86: =$AN86*AU86 -> 0 | AW86: 0 | AX86: =$AN86*AW86 -> 0 | AY86: 0 | AZ86: =$AN86*AY86 -> 0 | BA86: 0 | BB86: =$AN86*BA86 -> 0 | BD86: =$AN86*BC86 -> 0 | BE86: 0 | BF86: =$AN86*BE86 -> 0 | BG86: 0 | BH86: =$AN86*BG86 -> 0 | BI86: =AP86:AP86+AR86:AR86+AT86:AT86+AV86:AV86+AX86:AX86+AZ86:AZ86+BB86:BB86+BD86:BD86+BF86:BF86+BH86:BH86 -> 0 | BJ86: Se référer au document word de préconisation | BK86: 1 | BO86: X | BR86: X
B87: 81 | AN87: =SUM(AN7:AN79) -> 71 | AP87: =SUM(AP7:AP79) -> 0 | AR87: =SUM(AR7:AR79) -> 0 | AT87: =SUM(AT7:AT79) -> 84 | AV87: =SUM(AV7:AV79) -> 17 | AX87: =SUM(AX7:AX79) -> 14 | AZ87: =SUM(AZ7:AZ79) -> 0 | BB87: =SUM(BB7:BB79) -> 0 | BD87: =SUM(BD7:BD79) -> 28 | BF87: =SUM(BF7:BF79) -> 0 | BH87: =SUM(BH7:BH79) -> 0

Sheet Mapping_Registre_fichier
A1: Colonne fichier | B1: Colonne Registre BDD | C1: Type | D1: Table | E1: Commentaire
A2: Archivage ? (Oui / Non) | B2: archivage | C2: =VLOOKUP(B2,Mapping_Registre_bdd!A$2:B$41,2) -> boolean NULL
A3: Canaux de collecte des données | B3: canaux_collecte_donnees | C3: =VLOOKUP(B3,Mapping_Registre_bdd!A$2:B$41,2) -> character varying(255) NULL
A4: Catégories de destinataires | B4: categories_destinataires | C4: =VLOOKUP(B4,Mapping_Registre_bdd!A$2:B$41,2) -> text NULL
A5: Catégories de personnes concernées par le traitement | B5: categories_personnes_concernees | C5: =VLOOKUP(B5,Mapping_Registre_bdd!A$2:B$41,2) -> character varying(255) NULL
A6: Catégories particulières de données (NIR, santé par exemple) | B6: categories_particulieres_donnees | C6: =VLOOKUP(B6,Mapping_Registre_bdd!A$2:B$41,2) -> text NULL
A7: Commentaires | B7: commentaires | C7: =VLOOKUP(B7,Mapping_Registre_bdd!A$2:B$41,2) -> text NULL
A8: Data Protection Officer | B8: data_protection_officer | C8: =VLOOKUP(B8,Mapping_Registre_bdd!A$2:B$41,2) -> character varying(255) NULL
A9: Date de mise à jour | B9: date_mise_a_jour | C9: =VLOOKUP(B9,Mapping_Registre_bdd!A$2:B$41,2) -> date NULL | D9: Table miseajour datemaj : date Motif : text client_id | E9: Doit-être dans une table étranfgère : Jira à produire : A chaque modification de traitement une modale demandant la justification de la modification doit s'ouvrir. Si la dernière date de mise à jour est supérieure à la date de dernière version alors proposer le texte déjà saisi. Faire la mise à jour de la date du Registre de traitement dans la table client
A10: Date d'identification du traitement | B10: date_identification | C10: =VLOOKUP(B10,Mapping_Registre_bdd!A$2:B$41,2) -> date
A11: Dispositions existantes pour assurer la sécurité des données | B11: dispositions_securite_donnees_numerique | C11: =VLOOKUP(B11,Mapping_Registre_bdd!A$2:B$41,2) -> text NULL
A12: Dispositions existantes pour assurer la sécurité des données | B12: dispositions_securite_donnees_physique | C12: =VLOOKUP(B12,Mapping_Registre_bdd!A$2:B$41,2) -> text NULL
A13: Données concernées | B13: donnees_concernees | C13: =VLOOKUP(B13,Mapping_Registre_bdd!A$2:B$41,2) -> text NULL
A14: Données de connexion | B14: donnees_connexion | C14: =VLOOKUP(B14,Mapping_Registre_bdd!A$2:B$41,2) -> character varying(255) NULL
A15: Données de localisation | B15: donnees_localisation | C15: =VLOOKUP(B15,Mapping_Registre_bdd!A$2:B$41,2) -> character varying(255) NULL
A16: Données d'identification | B16: donnees_identification | C16: =VLOOKUP(B16,Mapping_Registre_bdd!A$2:B$41,2) -> text NULL
A17: Données économiques et financières | B17: donnees_economiques_financieres | C17: =VLOOKUP(B17,Mapping_Registre_bdd!A$2:B$41,2) -> character varying(255) NULL
A18: Données professionnelles | B18: donnees_professionnelles | C18: =VLOOKUP(B18,Mapping_Registre_bdd!A$2:B$41,2) -> character varying(255) NULL
A19: Données sur le comportement et la vie personnelle | B19: donnees_comportement_vie_perso | C19: =VLOOKUP(B19,Mapping_Registre_bdd!A$2:B$41,2) -> character varying(255) NULL
A20: Durée d'archivage | B20: duree_archivage | C20: =VLOOKUP(B20,Mapping_Registre_bdd!A$2:B$41,2) -> character varying(255) NULL | D20: Table duree Conservation_or_archivage : boolean duree : charactere varying(255) Client_ID : ID de la table client | E20: Pourrait être déportée dans une table externe
A21: Durée de conservation | B21: duree_conservation | C21: =VLOOKUP(B21,Mapping_Registre_bdd!A$2:B$41,2) -> character varying(255) NULL | D21: Table duree Conservation_or_archivage : boolean duree : charactere varying(255) Client_ID : ID de la table client | E21: Pourrait être déportée dans une table externe
A22: Emplacement numérique du traitement | B22: emplacement_numerique | C22: =VLOOKUP(B22,Mapping_Registre_bdd!A$2:B$41,2) -> text NULL
A23: Emplacement physique du traitement | B23: emplacement_physique | C23: =VLOOKUP(B23,Mapping_Registre_bdd!A$2:B$41,2) -> text NULL
A24: Etablissement(s) | C24: =VLOOKUP(B24,Mapping_Registre_bdd!A$2:B$41,2) -> #N/A | E24: Clé etrangère
A25: Etude d'impact (PIA) | B25: etude_impact | C25: =VLOOKUP(B25,Mapping_Registre_bdd!A$2:B$41,2) -> character varying(255) NULL | D25: Table Definition qui : enum(etude_impact, finalite_principale,) libelle : varchar(255) client_id MotivationCNIL : text | E25: Doit etre pris dans une table étrangère "onglet FR_Définitions"
A26: Finalité principale | B26: finalite_principale | C26: =VLOOKUP(B26,Mapping_Registre_bdd!A$2:B$41,2) -> character varying(255) NULL | D26: Table Definition qui : enum(etude_impact, finalite_principale,) libelle : varchar(255) client_id MotivationCNIL : text | E26: Pourrait être déportée dans une table externe
A27: Gestionnaire de la mise en œuvre du traitement | B27: gestionnaire_mise_en_oeuvre | C27: =VLOOKUP(B27,Mapping_Registre_bdd!A$2:B$41,2) -> character varying(255) NULL
A28: Hébergement | B28: hebergement | C28: =VLOOKUP(B28,Mapping_Registre_bdd!A$2:B$41,2) -> character varying(255) NULL
A29: Historique des modifications | B29: historique_modifications | C29: =VLOOKUP(B29,Mapping_Registre_bdd!A$2:B$41,2) -> text NULL | E29: Prévoir une US pour valoriser l'historique
A30: ID | C30: =VLOOKUP(B30,Mapping_Registre_bdd!#REF!,2) -> #REF!
A31: Licéité du traitement | B31: liceite_traitement | C31: =VLOOKUP(B31,Mapping_Registre_bdd!A$2:B$41,2) -> character varying(255) NULL | D31: Table Definition | E31: Doit etre pris dans une table étrangère "onglet FR_Définitions"
A32: Nom du traitement | B32: nom | C32: =VLOOKUP(B32,Mapping_Registre_bdd!A$2:B$41,2) -> character varying(255)
A33: Pays destinataires | B33: pays_destinataires | C33: =VLOOKUP(B33,Mapping_Registre_bdd!A$2:B$41,2) -> character varying(255) NULL
A34: Raisons du transfert vers les catégories de destinataires | B34: raisons_transfert_destinataires | C34: =VLOOKUP(B34,Mapping_Registre_bdd!A$2:B$41,2) -> text NULL | E34: SO ?
A35: Recours au traitements automatisés (y compris profilage) ? (Oui / Non) | B35: recours_traitements_automatises | C35: =VLOOKUP(B35,Mapping_Registre_bdd!A$2:B$41,2) -> boolean NULL
A36: Responsable de traitement | B36: responsable_traitement | C36: =VLOOKUP(B36,Mapping_Registre_bdd!A$2:B$41,2) -> character varying(255) NULL | D36: Table ResponsableTraitement | E36: Pourrait être déportée dans une table externe
A37: Sensibilité | B37: sensibilite | C37: =VLOOKUP(B37,Mapping_Registre_bdd!A$2:B$41,2) -> character varying(255) NULL | D37: Table Definition | E37: Doit etre pris dans une table étrangère "onglet FR_Définitions"
A38: Sous-finalités | B38: sous_finalites | C38: =VLOOKUP(B38,Mapping_Registre_bdd!A$2:B$41,2) -> text NULL
A39: Transferts hors UE (Oui / Non) | B39: transferts_hors_ue | C39: =VLOOKUP(B39,Mapping_Registre_bdd!A$2:B$41,2) -> boolean NULL
A40: …................... | B40: version_registre | C40: varchar(30) | D40: Champ à ajouter dans la table CLIENT il s'agit de la dernière version générée d'un fichier | E40: il s'agit de la version du registre de traitement càd l'ensemble des traitements d'un client
